Workbook

Sheet Presentación
A1: TICKER | B1: ='Input sheet'!A1 -> Novo Nordisk (NYSE:NVO) | C1: Precio | D1: ='Input sheet'!D1 -> 39.4
B3: Resumen de Inversión y Beneficios
B6: PRECIO ACTUAL | E6: PRECIO OBJETIVO (BASE) | H6: BENEFICIO ESPERADO (CAGR 3A) | K6: ="PRECIO ("&TEXT('Input sheet'!B4,"dd-mmm-yy")&")" -> PRECIO (23-Sep-26)
B7: ='Input sheet'!D1 -> 39.4 | E7: ='Resumen de Valoración'!D12 -> 58.164425 | H7: ='Resumen de Valoración'!D13 -> 0.13864167 | K7: ='Resumen de Valoración'!C25 -> 39.4
B11: ='Resumen de Valoración'!A15 -> Valores de compra | C11: ='Resumen de Valoración'!B15 -> Max | D11: ='Resumen de Valoración'!C15 -> Min
B12: ='Resumen de Valoración'!A16 -> Value | C12: ='Resumen de Valoración'!B16 -> 40.715098 | D12: ='Resumen de Valoración'!C16 -> 37.806876
B13: ='Resumen de Valoración'!A17 -> Deep Value | C13: ='Resumen de Valoración'!B17 -> 34.898655 | D13: ='Resumen de Valoración'!C17 -> 31.990434
B14: ='Resumen de Valoración'!A18 -> Valoración histórica | C14: ='Resumen de Valoración'!B18 -> 29.082213 | D14: ='Resumen de Valoración'!C18 -> 26.173991
B15: ='Resumen de Valoración'!A19 -> Precio con MOS | C15: ='Resumen de Valoración'!B19 -> 37.806876 | D15: ='Resumen de Valoración'!C19 -> 37.104445

Sheet Resumen de Valoración
A1: ='Input sheet'!A1 -> Novo Nordisk (NYSE:NVO) | C1: Precio | D1: ='Input sheet'!D1 -> 39.4
A2: Fecha del análisis | B2: =TODAY() -> 2026-09-23 00:00:00
A3: Precio al día del análisis | B3: =C25 -> 39.4 | F3: Tipo de Empresa | G3: Biotech/Farma
F4: Margen de Seguridad (MOS) | G4: 0.35
A5: Método | B5: Peso | C5: Conservador | D5: Base | E5: Optimista | I5: Método | J5: Crecimiento | K5: Madura | L5: Genérico | M5: Defensiva | N5: Cíclica/Commodity | O5: Intensiva en Capital | P5: Financiera | Q5: Infraestructura | R5: REIT/Inmobiliaria | S5: Software | T5: Hyper-Crecimiento / Pre-Rentable | U5: Biotech/Farma
A6: DCF Damodaran | B6: =VLOOKUP(A6, $I$6:$U$11, MATCH($G$3, $I$5:$U$5, 0), FALSE) -> 0.55 | C6: ='Valuation output'!B86 -> 45.524667 | D6: ='Valuation output'!B35 -> 44.090876 | E6: ='Valuation output'!B137 -> 35.681534 | I6: DCF Damodaran | J6: 0.6 | K6: 0.4 | L6: 0.5 | M6: 0.3 | N6: 0.4 | O6: 0.2 | P6: 0.4 | Q6: 0.4 | R6: 0.25 | S6: 0.6 | T6: 0.8 | U6: 0.55
A7: EV/EBITDA | B7: =VLOOKUP(A7, $I$6:$U$11, MATCH($G$3, $I$5:$U$5, 0), FALSE) -> 0.05 | C7: =EVEBITDA!$H$12 -> 59.774653 | D7: =EVEBITDA!$H$23 -> 63.887099 | E7: =EVEBITDA!$H$34 -> 61.622859 | I7: EV/EBITDA | J7: 0.1 | K7: 0.2 | L7: 0.1 | M7: 0.2 | N7: 0.25 | O7: 0.4 | P7: 0 | Q7: 0.15 | R7: 0.15 | S7: 0.1 | T7: 0 | U7: 0.05
A8: EV/FCFF | B8: =VLOOKUP(A8, $I$6:$U$11, MATCH($G$3, $I$5:$U$5, 0), FALSE) -> 0.2 | C8: =EVFCFF!H12 -> 81.464376 | D8: =EVFCFF!H23 -> 85.448445 | E8: =EVFCFF!H34 -> 83.128069 | I8: EV/FCFF | J8: 0.15 | K8: 0.1 | L8: 0.1 | M8: 0.1 | N8: 0.15 | O8: 0.15 | P8: 0 | Q8: 0.25 | R8: 0.15 | S8: 0.15 | T8: 0.1 | U8: 0.2
A9: P/E | B9: =VLOOKUP(A9, $I$6:$U$11, MATCH($G$3, $I$5:$U$5, 0), FALSE) -> 0.05 | C9: =PE!$H$12 -> 58.144795 | D9: =PE!H23 -> 61.727745 | E9: =PE!$H$34 -> 59.982748 | I9: P/E | J9: 0.05 | K9: 0.2 | L9: 0.1 | M9: 0.25 | N9: 0.05 | O9: 0.05 | P9: 0.35 | Q9: 0.1 | R9: 0.05 | S9: 0.05 | T9: 0 | U9: 0.05
A10: P/FCFE | B10: =VLOOKUP(A10, $I$6:$U$11, MATCH($G$3, $I$5:$U$5, 0), FALSE) -> 0.1 | C10: =PFCFE!$H$12 -> 69.896077 | D10: =PFCFE!$H$23 -> 74.668456 | E10: =PFCFE!$H$34 -> 71.423862 | I10: P/FCFE | J10: 0.05 | K10: 0.05 | L10: 0.1 | M10: 0.1 | N10: 0.1 | O10: 0.1 | P10: 0.2 | Q10: 0.05 | R10: 0.3 | S10: 0.05 | T10: 0.05 | U10: 0.1
A11: P/OCF | B11: =VLOOKUP(A11, $I$6:$U$11, MATCH($G$3, $I$5:$U$5, 0), FALSE) -> 0.05 | C11: =POCF!$H$12 -> 57.334781 | D11: =POCF!H23 -> 61.543329 | E11: =POCF!$H$34 -> 58.601973 | I11: P/OCF | J11: 0.05 | K11: 0.05 | L11: 0.1 | M11: 0.05 | N11: 0.05 | O11: 0.1 | P11: 0.05 | Q11: 0.05 | R11: 0.1 | S11: 0.05 | T11: 0.05 | U11: 0.05
A12: Precio Objetivo Ponderado | B12: =SUM(B6:B11) -> 1 | C12: =SUMPRODUCT($B6:$B11, C6:C11) -> 57.083761 | D12: =SUMPRODUCT($B6:$B11, D6:D11) -> 58.164425 | E12: =SUMPRODUCT($B6:$B11, E6:E11) -> 52.403222 | I12: Total | J12: 1 | K12: 1 | L12: 1 | M12: 1 | N12: 1 | O12: 1 | P12: 1 | Q12: 1 | R12: 1 | S12: 1 | T12: =SUM(T6:T11) -> 1 | U12: =SUM(U6:U11) -> 1
A13: CAGR a 3 años | C13: =(C12 / $B$3) ^ (1 / 3) - 1 -> 0.13154576 | D13: =(D12 / $B$3) ^ (1 / 3) - 1 -> 0.13864167 | E13: =(E12 / $B$3) ^ (1 / 3) - 1 -> 0.099733
A14: MOS vs Precio Actual | C14: =(C12-$B$3)/C12 -> 0.3097862 | D14: =(D12-$B$3)/D12 -> 0.32261 | E14: =(E12-$B$3)/E12 -> 0.24813784
A15: Valores de compra | B15: Max | C15: Min | D15: CAGR Max | E15: CAGR Min
A16: Value | B16: =$D$12 * 0.7 -> 40.715098 | C16: =$D$12 * 0.65 -> 37.806876 | D16: =(B16 / $B$3) ^ (1 / 3) - 1 -> 0.011004495 | E16: =(C16 / $B$3) ^ (1 / 3) - 1 -> -0.013664059
A17: Deep Value | B17: =$D$12 * 0.6 -> 34.898655 | C17: =$D$12 * 0.55 -> 31.990434 | D17: =(B17 / $B$3) ^ (1 / 3) - 1 -> -0.039632422 | E17: =(C17 / $B$3) ^ (1 / 3) - 1 -> -0.06708666
A18: Valoración histórica | B18: =$D$12 * 0.5 -> 29.082213 | C18: =$D$12 * 0.45 -> 26.173991 | D18: =(B18 / $B$3) ^ (1 / 3) - 1 -> -0.096259508 | E18: =(C18 / $B$3) ^ (1 / 3) - 1 -> -0.12744815
A19: Precio con MOS | B19: =D12 * (1 - $G$4) -> 37.806876 | C19: =C12 * (1 - $G$4) -> 37.104445
A21: RESUMEN RÁPIDO
A22: Precio Objetivo (Base) | B22: =D12 -> 58.164425
A23: Rango Objetivo (Conservador – Optimista) | B23: =C12 -> 57.083761 | C23: =E12 -> 52.403222
A24: Precio de Hoy | B24: ='Input sheet'!D1 -> 39.4
A25: ="Precio al Día del Análisis ("&TEXT('Input sheet'!B4,"dd-mmm-yyyy")&")" -> Precio al Día del Análisis (23-Sep-2026) | C25: ='Input sheet'!D1 -> 39.4
A26: Potencial vs. Precio Objetivo Base | B26: =(D12-B24)/B24 -> 0.47625445

Sheet Tesis de Inversión y Supuestos
A1: NVO (Novo Nordisk A/S) — Tesis de Inversión: De la Historia a los Números
A2: Metodología Damodaran (NYU Stern) | Precio al día del análisis: USD 39,40 (cierre NYSE 22-sep-2026) | WACC: 10,04% | Cifras en USD millones convertidas desde DKK (tipos BCE)
A4: 1. LA HISTORIA
A5: Novo Nordisk pasó de crecer 25-31% anual en ventas (2022-2024, en DKK) a una fase de normalización: las ventas IFRS 2025 crecieron 6,4% en DKK y la guía de agosto de 2026 prevé ventas ajustadas de 0% a -6% a tipo de cambio constante (TCC) para 2026. Lo ya demostrado en los datos es que el volumen de GLP-1 sigue creciendo (Obesity care ajustado +19% TCC en H1 2026; Wegovy® pill >5 millones de recetas en EE. UU. desde su lanzamiento en enero de 2026) mientras el precio realizado cae (acuerdo MFN con el Gobierno de EE. UU., recorte de precio de lista a USD 675 desde el 1-ene-2027, pérdida de exclusividad de semaglutida en algunos mercados de International Operations). El margen operativo ajustado sigue alto (44,6% en H1 2026) pero la rentabilidad sobre capital cayó de 88,5% (2023) a 39,3% (2025) por la ola de capex (DKK 60,1 mil M en 2025) y la compra de plantas de Catalent. La tensión central: un negocio de altísima calidad cuyo precio unitario se está reajustando; el mercado (EV/EBITDA LTM ajustado ~8,5x) descuenta que la erosión de precio y la competencia de Eli Lilly pesen más que la expansión de volumen. Base del LTM: IFRS jul-25/jun-26 excluyendo la reversión no recurrente y sin efecto caja de la provisión 340B (DKK 26,8 mil M) y el deterioro de activos de pipeline (DKK 6,3 mil M).
A7: Caso alcista (Bull) | B7: Caso bajista (Bear)
A8: Volumen: Obesity care ajustado creció 19% a TCC en H1 2026 y 40% en International Operations; pacientes con productos de obesidad +69% interanual a 4,9 millones (informe H1 2026, 4-ago-2026). | B8: Precio: la guía 2026 prevé ventas ajustadas de 0% a -6% a TCC; en EE. UU. las ventas ajustadas H1 2026 cayeron 4% a TCC por menores precios realizados (informe H1 2026).
A9: Nuevo formato oral: Wegovy® pill superó 265.000 recetas semanales (semana al 17-jul-2026) y fue aprobado por la EMA en julio de 2026; Wegovy® HD (7,2 mg) lanzado en EE. UU. en abril de 2026. | B9: Reinicio de precio: desde el 1-ene-2027 el precio de lista de Wegovy®/Ozempic® en EE. UU. baja a USD 675 (≈-50% y -35%), con impacto esperado en el flujo de caja de 2027 (informe H1 2026).
A10: Caja: flujo de caja libre H1 2026 de DKK 55,3 mil M (+44%) y guía 2026 elevada a DKK 45-55 mil M; recompras 2026 de hasta DKK 15 mil M y dividendo 2025 de DKK 11,70/acción. | B10: Intensidad de capital: capex PP&E DKK 60,1 mil M en 2025 y ~55 mil M en 2026; ROIC reportado cayó de 88,5% (2023) a 39,3% (2025) (Five-year overview AR2025).
A11: Pipeline y plazos: patente de compuesto de semaglutida en EE. UU. hasta 2032; objetivos CMD (21-sep-2026) de >5 multi-blockbusters a 2030 y >DKK 150 mil M de ventas de pipeline ajustadas por riesgo en 2035. | B11: Ejecución de I+D: ZEUS (ziltivekimab) no alcanzó su objetivo primario (31-jul-2026); monlunabant terminado con deterioro de DKK 4,0 mil M; CagriSema no demostró no-inferioridad en HbA1c frente a tirzepatida (REIMAGINE 4).
A13: 2. DE LA HISTORIA A LOS NÚMEROS — LOS TRES ESCENARIOS
A14: Supuesto | B14: Conservador | C14: Base | D14: Optimista | E14: Justificación (dato real)
A15: Crecimiento Ingresos — Año 1 | B15: 0.0048 | C15: -0.04 | D15: -0.052 | E15: Base -4%: guía 2026 ventas ajustadas 0% a -6% TCC (≈-1 pp adicional en DKK) y recorte de precio de lista EE. UU. en 2027; LTM en USD convertido a 6,405 DKK/USD vs spot 6,55. Conservador y optimista NO son supuestos del analista: la plantilla los deriva de B27 (conservador = promedio(B27; Rf) = 0,48%; optimista = 1,3×B27 = -5,2%), por lo que con crecimiento negativo el orden económico se invierte.
A16: Crecimiento Ingresos — Años 2-5 | B16: 0.0048 | C16: 0.035 | D16: -0.052 | E16: Base 3,5%: el CMD (21-sep-2026) apunta a una TCAC 2026-30 "en línea con pares"; la mediana de crecimiento de consenso a 3 años de los pares (LLY, AZN, SNY, MRK, AMGN, PFE) es ~4,6% (stockanalysis, 23-sep-2026). Se aplica un descuento por reajuste de precio y expiración de semaglutida (EE. UU. 2032). Conservador/optimista replican C55/C106 de Valuation output.
A17: Margen Operativo — Año 1 | B17: 0.475 | C17: 0.475 | D17: 0.475 | E17: Margen año 1 = 'Valuation output'!B6 - 2 pp = 47,5% (valor predeterminado de la plantilla). B6 = 49,5% es el margen LTM ajustado con I+D capitalizada (vida 10 años); el margen EBIT IFRS ajustado LTM es 40,2%. Los -2 pp reflejan el recorte de precios de 2027 y el aumento de I+D y promoción previsto para H2 2026.
A18: Margen Objetivo (convergencia) | B18: 0.495 | C18: 0.45 | D18: 0.5 | E18: Base 45%: el CMD fija "margen operativo ampliamente estable"; se deja 2,5 pp bajo el año 1 por erosión de precio. Conservador = margen actual B6 (49,5%) y optimista = B30+5 pp (50%) por diseño de la plantilla: el conservador supera al base porque el margen actual excede el objetivo base (incongruencia de diseño documentada).
A19: Años de convergencia de margen | B19: 5 | C19: 5 | D19: 5 | E19: Cinco años: el recorte de precios de lista en EE. UU. (ene-2027) y la expiración de semaglutida en 2031-32 concentran la presión dentro del horizonte; se mantiene el valor predeterminado.
A20: Sales-to-Capital (años 1-5 / 6-10) | B20: 0,80x / 1,07x | C20: 0,80x / 1,07x | D20: 0,80x / 1,07x | E20: 0,80x años 1-5 (entrada manual): refleja capex de DKK 60 mil M (2025) y ~55 mil M (2026) en API y llenado, con guía de descenso posterior; ingresos/capital invertido actual (con I+D capitalizada) = 0,61x. 1,07x años 6-10 = mediana global de farmacéuticas (Damodaran, K28).
A21: Costo de Capital (WACC) | B21: 0.1004 | C21: 0.1004 | D21: 0.1004 | E21: Método "Detailed": Rf 4,96% (UST 10 años, 22-sep-2026); beta desapalancada global Drugs (Pharmaceutical) 0,999 → apalancada 1,07; ERP por regiones operativas 5,25% (ventas ajustadas H1 2026); Kd = Rf + spread de rating real Aa3/AA (tabla "Aa2/AA", 0,55%); D/(D+E) 8,6%. El WACC no cambia entre escenarios en esta plantilla.
A23: 3. RESULTADO DEL DCF POR ESCENARIO
A24: Escenario | B24: Valor DCF / acción | C24: Precio Objetivo Ponderado* | D24: vs. Precio Actual (USD 39,40)
A25: Conservador | B25: 45.52 | C25: 57.08 | D25: 0.449
A26: Base | B26: 44.09 | C26: 58.16 | D26: 0.476
A27: Optimista | B27: 35.68 | C27: 52.4 | D27: 0.33
A28: *Precio Objetivo Ponderado combina el DCF (55%) con EV/FCFF (20%), P/FCFE (10%), EV/EBITDA (5%), P/E (5%) y P/OCF (5%), ponderación "Biotech/Farma" de la hoja Resumen de Valoración. Los múltiplos usan por defecto el MÍNIMO de 2022-2025 (años de hipercrecimiento): EV/EBITDA 10,8x, EV/FCFF 27,4x, P/E 14,7x. Sensibilidad (no incorporada al archivo): con los múltiplos LTM actuales en las celdas J19 (EV/EBITDA 8,5x, EV/FCF 15,9x, P/E 11,2x, P/FCF 14,7x, P/OCF 8,5x) el precio ponderado base sería USD 47,91 en lugar de 58,16. Resultados con precio de prueba USD 39,40; en Google Sheets se recalculan con GOOGLEFINANCE.
A30: 4. AJUSTES METODOLÓGICOS APLICADOS (sobre la plantilla ya corregida)
A31: # | B31: Ajuste | C31: Razón
A32: 1 | B32: Datos: LTM jun-26 ajustado (excluye reversión 340B de DKK 26,8 mil M y deterioros mayores de DKK 6,3 mil M); estados en USD (flujos a tipo medio, balance a tipo de cierre BCE). | C32: Sin ajuste, el LTM incluiría ingresos no recurrentes y sin efecto caja equivalentes al 8,8% de las ventas ajustadas, inflando la base del DCF.
A33: 2 | B33: Categoría de ponderación en Resumen de Valoración!G3: "Genérico" → "Biotech/Farma"; I+D capitalizada a 10 años (R&D converter F7: 3 → 10); costo de capital con ERP por regiones operativas y rating real. | C33: Perfil farmacéutico: vida económica de la I+D según la tabla de Damodaran para "Drug" (10 años); 51% de las ventas ajustadas H1 2026 se generan en EE. UU. y rating Aa3/AA (Moody's/S&P).
A34: 3 | B34: Supuestos base recalibrados: B27 -4%, B29 3,5%, B30 45%, B32 0,80x (B33 = K28); se mantienen B28 (B6-2 pp) y B31 (5 años) por defecto. Múltiplos: sin override (mínimo 4 años por defecto). | C34: Guía 2026 (4-ago-2026), objetivos CMD (21-sep-2026) y capex guiado. Advertencia: con B27 negativo las fórmulas automáticas invierten los escenarios (optimista < base < conservador en DCF).
A36: 5. CONCLUSIÓN
A37: Con el precio de USD 39,40 (22-sep-2026), el DCF del Modelo JMR entrega USD 44,09 por ADR en el escenario base (precio = 89% del valor) y el precio objetivo ponderado base es USD 58,16 (+47,6%), pero esta cifra depende mucho de múltiplos anclados en 2022-2025: con múltiplos LTM el ponderado base baja a ~USD 47,9 y el DCF solo deja un margen de ~11%, inferior al MOS de 35% exigido. Los escenarios automáticos no son interpretables como rango (el optimista da USD 35,68 porque multiplica un crecimiento negativo). La variable que más mueve el valor es el precio neto por paciente en EE. UU. tras 2027 (define si el crecimiento de volumen de Wegovy® pill y de International Operations compensa el reajuste de precio y sostiene el margen del 45%); le sigue la intensidad de capital (ingresos/capital 0,8x) que determina si el ROIC se estabiliza por encima del WACC de 10%.

Sheet EVFCFF
A1: ='Input sheet'!A1 -> Novo Nordisk (NYSE:NVO) | C1: Precio | D1: ='Input sheet'!D1 -> 39.4
A2: ⚠️ Advertencia: Las celdas en VERDE, AMARILLO y ROJO son para entrada manual de datos.
A3: Price today: | B3: ='Input sheet'!D1 -> 39.4
A5: --- FORECASTED SUMMARY --- | B5: CONSERVADOR
A6: Realized At | B6: Dec '22 | C6: Dec '23 | D6: Dec '24 | E6: Dec '25 | F6: FY+1 (Estimate) | G6: FY+2 (Estimate) | H6: FY+3 (Estimate)
A7: Enterprise Value | B7: ='Trailing Valuation'!H6 -> 305090.36 | C7: ='Trailing Valuation'!I6 -> 463447.07 | D7: ='Trailing Valuation'!J6 -> 397831.33 | E7: ='Trailing Valuation'!K6 -> 243531.19 | F7: ='Trailing Valuation'!L6 -> 188525.82 | J7: Cambiar múltiplo
A8: NTM EV/FCFF Multiple | B8: ='Trailing Valuation'!H24 -> 32.367926 | C8: =C7/C9 -> 37.103061 | D8: =D7/D9 -> 32.195339 | E8: =E7/E9 -> 27.348717 | F8: =IFERROR(IF(J8<>"",J8,F19*0.9),"") -> 24.613845 | G8: =F8 -> 24.613845 | H8: =F8 -> 24.613845
A9: FCFF | B9: =B7/B8 -> 9425.7 | C9: ='Financials Multiples'!B24 -> 12490.804 | D9: ='Financials Multiples'!C24 -> 12356.799 | E9: ='Financials Multiples'!D24 -> 8904.6661 | F9: ='Financials Multiples'!E24 -> 13306.42 | G9: ='Financials Multiples'!F24 -> 13964.54 | H9: ='Financials Multiples'!G24 -> 14176.17
A10: Implied Target Stock Price | F10: =F8*(F9/'Financials Multiples'!E31) -> 73.729717 | G10: =G8*(G9/'Financials Multiples'!F31) -> 77.784791 | H10: =H8*(H9/'Financials Multiples'!G31) -> 79.380474
A11: Cumulative Dividends/Share | F11: ='Financials Multiples'!E35 -> 1.8266 | G11: ='Financials Multiples'!F35 -> 1.9552514 | H11: ='Financials Multiples'!G35 -> 2.0839027
A12: Total Target Price + Dividends | F12: =F10+F11 -> 75.556317 | G12: =G10+G11 -> 79.740043 | H12: =H10+H11 -> 81.464376
A13: Total Return | F13: =(F12-B3)/B3 -> 0.91767303 | G13: =(G12-B3)/B3 -> 1.023859 | H13: =(H12-B3)/B3 -> 1.0676238
A14: Total IRR (Annualized Return) | F14: =(F12/B3) ^ (1 / 1) - 1 -> 0.91767303 | G14: =(G12/B3) ^ (1 / 2) - 1 -> 0.42262397 | H14: =(H12/B3) ^ (1 / 3) - 1 -> 0.27396405
A16: --- FORECASTED SUMMARY --- | B16: BASE
A17: Realized At | B17: Dec '22 | C17: Dec '23 | D17: Dec '24 | E17: Dec '25 | F17: FY+1 (Estimate) | G17: FY+2 (Estimate) | H17: FY+3 (Estimate)
A18: Enterprise Value | B18: =B7 -> 305090.36 | C18: =C7 -> 463447.07 | D18: =D7 -> 397831.33 | E18: =E7 -> 243531.19 | F18: =F7 -> 188525.82 | J18: Cambiar múltiplo
A19: NTM EV/FCFF Multiple | B19: =B8 -> 32.367926 | C19: =C8 -> 37.103061 | D19: =D8 -> 32.195339 | E19: =E8 -> 27.348717 | F19: =IFERROR(IF(J19<>"",J19,MEDIAN('Trailing Valuation'!G24:K24)),"") -> 27.348717 | G19: =F19 -> 27.348717 | H19: =F19 -> 27.348717 | J19: =MIN(B19:E19) -> 27.348717
A20: FCFF | B20: =B18/B19 -> 9425.7 | C20: ='Financials Multiples'!B63 -> 12490.804 | D20: ='Financials Multiples'!C63 -> 12356.799 | E20: ='Financials Multiples'!D63 -> 8904.6661 | F20: ='Financials Multiples'!E63 -> 12569.321 | G20: ='Financials Multiples'!F63 -> 13137.977 | H20: ='Financials Multiples'!G63 -> 13398.899
A21: Implied Target Stock Price | F21: =F19*(F20/'Financials Multiples'!E70) -> 77.383909 | G21: =G19*(G20/'Financials Multiples'!F70) -> 81.31189 | H21: =H19*(H20/'Financials Multiples'!G70) -> 83.364542
A22: Cumulative Dividends/Share | F22: ='Financials Multiples'!E74 -> 1.8266 | G22: ='Financials Multiples'!F74 -> 1.9552514 | H22: ='Financials Multiples'!G74 -> 2.0839027
A23: Total Target Price + Dividends | F23: =F21+F22 -> 79.210509 | G23: =G21+G22 -> 83.267142 | H23: =H21+H22 -> 85.448445
A24: Total Return | F24: =(F23-B3)/B3 -> 1.010419 | G24: =(G23-B3)/B3 -> 1.1133792 | H24: =(H23-B3)/B3 -> 1.1687423
A25: Total IRR (Annualized Return) | F25: =(F23/B3) ^ (1 / 1) - 1 -> 1.010419 | G25: =(G23/B3) ^ (1 / 2) - 1 -> 0.45374662 | H25: =(H23/B3) ^ (1 / 3) - 1 -> 0.29440241
A27: --- FORECASTED SUMMARY --- | B27: OPTIMISTA
A28: Realized At | B28: Dec '22 | C28: Dec '23 | D28: Dec '24 | E28: Dec '25 | F28: FY+1 (Estimate) | G28: FY+2 (Estimate) | H28: FY+3 (Estimate)
A29: Enterprise Value | B29: =B7 -> 305090.36 | C29: =C7 -> 463447.07 | D29: =D7 -> 397831.33 | E29: =E7 -> 243531.19 | F29: =F7 -> 188525.82 | J29: Cambiar múltiplo
A30: NTM EV/FCFF Multiple | B30: =B8 -> 32.367926 | C30: =C8 -> 37.103061 | D30: =D8 -> 32.195339 | E30: =E8 -> 27.348717 | F30: =IFERROR(IF(J30<>"",J30,F19*1.1),"") -> 30.083588 | G30: =F30 -> 30.083588 | H30: =F30 -> 30.083588
A31: FCFF | B31: =B18/B19 -> 9425.7 | C31: ='Financials Multiples'!B103 -> 12490.804 | D31: ='Financials Multiples'!C103 -> 12356.799 | E31: ='Financials Multiples'!D103 -> 8904.6661 | F31: ='Financials Multiples'!E103 -> 12376.95 | G31: ='Financials Multiples'!F103 -> 12329.587 | H31: ='Financials Multiples'!G103 -> 11841.775
A32: Implied Target Stock Price | F32: =F30*(F31/'Financials Multiples'!E110) -> 83.819521 | G32: =G30*(G31/'Financials Multiples'!F110) -> 83.939578 | H32: =H30*(H31/'Financials Multiples'!G110) -> 81.044166
A33: Cumulative Dividends/Share | F33: ='Financials Multiples'!E114 -> 1.8266 | G33: ='Financials Multiples'!F114 -> 1.9552514 | H33: ='Financials Multiples'!G114 -> 2.0839027
A34: Total Target Price + Dividends | F34: =F32+F33 -> 85.646121 | G34: =G32+G33 -> 85.894829 | H34: =H32+H33 -> 83.128069
A35: Total Return | F35: =(F34-B3)/B3 -> 1.1737594 | G35: =(G34-B3)/B3 -> 1.1800718 | H35: =(H34-B3)/B3 -> 1.1098495
A36: Total IRR (Annualized Return) | F36: =(F34/B3) ^ (1 / 1) - 1 -> 1.1737594 | G36: =(G34/B3) ^ (1 / 2) - 1 -> 0.47650662 | H36: =(H34/B3) ^ (1 / 3) - 1 -> 0.28257811
A39: EV/FCFF Last 10Y | B39: =MEDIAN('Trailing Valuation'!B24:K24) -> 26.518564
A40: EV/FCFF Last 5Y | B40: =MEDIAN('Trailing Valuation'!G24:K24) -> 33.464422
A41: EV/FCFF Last 3Y | B41: =MEDIAN('Trailing Valuation'!I24:K24) -> 37.155843
A42: EV/FCFF TTM | B42: ='Trailing Valuation'!L24 -> 15.922654
A45: Matriz de Sensibilidad: Precio Objetivo Implícito (FY+3)
A46: EV/FCFF \ FCFF | B46: =$H$20*0.9 -> 12059.009 | C46: =$H$20*0.95 -> 12728.954 | D46: =$H$20 -> 13398.899 | E46: =$H$20*1.05 -> 14068.844 | F46: =$H$20*1.1 -> 14738.789
A47: =$F$19*0.9 -> 24.613845 | B47: =$A47*(B$46/'Financials Multiples'!$E$70) -> 66.817922 | C47: =$A47*(C$46/'Financials Multiples'!$E$70) -> 70.530028 | D47: =$A47*(D$46/'Financials Multiples'!$E$70) -> 74.242135 | E47: =$A47*(E$46/'Financials Multiples'!$E$70) -> 77.954242 | F47: =$A47*(F$46/'Financials Multiples'!$E$70) -> 81.666349
A48: =$F$19*0.95 -> 25.981281 | B48: =$A48*(B$46/'Financials Multiples'!$E$70) -> 70.530028 | C48: =$A48*(C$46/'Financials Multiples'!$E$70) -> 74.448363 | D48: =$A48*(D$46/'Financials Multiples'!$E$70) -> 78.366698 | E48: =$A48*(E$46/'Financials Multiples'!$E$70) -> 82.285033 | F48: =$A48*(F$46/'Financials Multiples'!$E$70) -> 86.203368
A49: =$F$19 -> 27.348717 | B49: =$A49*(B$46/'Financials Multiples'!$E$70) -> 74.242135 | C49: =$A49*(C$46/'Financials Multiples'!$E$70) -> 78.366698 | D49: =$A49*(D$46/'Financials Multiples'!$E$70) -> 82.491261 | E49: =$A49*(E$46/'Financials Multiples'!$E$70) -> 86.615824 | F49: =$A49*(F$46/'Financials Multiples'!$E$70) -> 90.740387
A50: =$F$19*1.05 -> 28.716152 | B50: =$A50*(B$46/'Financials Multiples'!$E$70) -> 77.954242 | C50: =$A50*(C$46/'Financials Multiples'!$E$70) -> 82.285033 | D50: =$A50*(D$46/'Financials Multiples'!$E$70) -> 86.615824 | E50: =$A50*(E$46/'Financials Multiples'!$E$70) -> 90.946616 | F50: =$A50*(F$46/'Financials Multiples'!$E$70) -> 95.277407
A51: =$F$19*1.1 -> 30.083588 | B51: =$A51*(B$46/'Financials Multiples'!$E$70) -> 81.666349 | C51: =$A51*(C$46/'Financials Multiples'!$E$70) -> 86.203368 | D51: =$A51*(D$46/'Financials Multiples'!$E$70) -> 90.740387 | E51: =$A51*(E$46/'Financials Multiples'!$E$70) -> 95.277407 | F51: =$A51*(F$46/'Financials Multiples'!$E$70) -> 99.814426

Sheet POCF
A1: ='Input sheet'!A1 -> Novo Nordisk (NYSE:NVO) | C1: Precio | D1: ='Input sheet'!D1 -> 39.4
A2: ⚠️ Advertencia: Las celdas en VERDE, AMARILLO y ROJO son para entrada manual de datos.
A3: Price today: | B3: ='Input sheet'!D1 -> 39.4
A5: --- FORECASTED SUMMARY --- | B5: CONSERVADOR
A6: Realized At | B6: ='Income Statement'!H2 -> Dec '22 | C6: ='Income Statement'!I2 -> Dec '23 | D6: ='Income Statement'!J2 -> Dec '24 | E6: ='Income Statement'!K2 -> Dec '25 | F6: FY+1 (Estimate) | G6: FY+2 (Estimate) | H6: FY+3 (Estimate)
A7: Market Cap | B7: ='Trailing Valuation'!H5 -> 304773.46 | C7: ='Trailing Valuation'!I5 -> 463924.97 | D7: ='Trailing Valuation'!J5 -> 387177.53 | E7: ='Trailing Valuation'!K5 -> 227170.59 | F7: ='Trailing Valuation'!L5 -> 174021.92 | J7: Cambiar múltiplo
A8: NTM P/OCF Multiple | B8: ='Trailing Valuation'!H15 -> 27.356024 | C8: =C7/C9 -> 28.15335 | D8: =D7/D9 -> 20.306265 | E8: =E7/E9 -> 12.390605 | F8: =IFERROR(IF(J8<>"",J8,F19*0.9),"") -> 11.151544 | G8: =F8 -> 11.151544 | H8: =F8 -> 11.151544
A9: OCF | B9: =B7/B8 -> 11141 | C9: ='Financials Multiples'!B26 -> 16478.5 | D9: ='Financials Multiples'!C26 -> 19066.9 | E9: ='Financials Multiples'!D26 -> 18334.1 | F9: ='Financials Multiples'!E26 -> 20831.215 | G9: ='Financials Multiples'!F26 -> 21528.883 | H9: ='Financials Multiples'!G26 -> 21778.544
A10: Implied Target Stock Price | F10: =F8*(F9/'Financials Multiples'!E31) -> 52.293958 | G10: =G8*(G9/'Financials Multiples'!F31) -> 54.330677 | H10: =H8*(H9/'Financials Multiples'!G31) -> 55.250879
A11: Cumulative Dividends/Share | F11: ='Financials Multiples'!E35 -> 1.8266 | G11: ='Financials Multiples'!F35 -> 1.9552514 | H11: ='Financials Multiples'!G35 -> 2.0839027
A12: Total Target Price + Dividends | F12: =F10+F11 -> 54.120558 | G12: =G10+G11 -> 56.285929 | H12: =H10+H11 -> 57.334781
A13: Total Return | F13: =(F12-B3)/B3 -> 0.37361822 | G13: =(G12-B3)/B3 -> 0.42857687 | H13: =(H12-B3)/B3 -> 0.45519749
A14: Total IRR (Annualized Return) | F14: =(F12/B3) ^ (1 / 1) - 1 -> 0.37361822 | G14: =(G12/B3) ^ (1 / 2) - 1 -> 0.19523089 | H14: =(H12/B3) ^ (1 / 3) - 1 -> 0.13320195
A16: --- FORECASTED SUMMARY --- | B16: BASE
A17: Realized At | B17: ='Income Statement'!H2 -> Dec '22 | C17: ='Income Statement'!I2 -> Dec '23 | D17: ='Income Statement'!J2 -> Dec '24 | E17: ='Income Statement'!K2 -> Dec '25 | F17: FY+1 (Estimate) | G17: FY+2 (Estimate) | H17: FY+3 (Estimate)
A18: Market Cap | B18: =B7 -> 304773.46 | C18: =C7 -> 463924.97 | D18: =D7 -> 387177.53 | E18: =E7 -> 227170.59 | F18: =F7 -> 174021.92 | J18: Cambiar múltiplo
A19: NTM P/OCF Multiple | B19: =B8 -> 27.356024 | C19: =C8 -> 28.15335 | D19: =D8 -> 20.306265 | E19: =E8 -> 12.390605 | F19: =IFERROR(IF(J19<>"",J19,MEDIAN('Trailing Valuation'!G15:K15)),"") -> 12.390605 | G19: =F19 -> 12.390605 | H19: =F19 -> 12.390605 | J19: =MIN(B19:E19) -> 12.390605
A20: OCF | B20: =B18/B19 -> 11141 | C20: ='Financials Multiples'!B65 -> 16478.5 | D20: ='Financials Multiples'!C65 -> 19066.9 | E20: ='Financials Multiples'!D65 -> 18334.1 | F20: ='Financials Multiples'!E65 -> 19758.616 | G20: ='Financials Multiples'!F65 -> 20574.681 | H20: ='Financials Multiples'!G65 -> 21093.706
A21: Implied Target Stock Price | F21: =F19*(F20/'Financials Multiples'!E70) -> 55.112603 | G21: =G19*(G20/'Financials Multiples'!F70) -> 57.691819 | H21: =H19*(H20/'Financials Multiples'!G70) -> 59.459426
A22: Cumulative Dividends/Share | F22: ='Financials Multiples'!E74 -> 1.8266 | G22: ='Financials Multiples'!F74 -> 1.9552514 | H22: ='Financials Multiples'!G74 -> 2.0839027
A23: Total Target Price + Dividends | F23: =F21+F22 -> 56.939203 | G23: =G21+G22 -> 59.647071 | H23: =H21+H22 -> 61.543329
A24: Total Return | F24: =(F23-B3)/B3 -> 0.44515743 | G24: =(G23-B3)/B3 -> 0.51388504 | H24: =(H23-B3)/B3 -> 0.56201342
A25: Total IRR (Annualized Return) | F25: =(F23/B3) ^ (1 / 1) - 1 -> 0.44515743 | G25: =(G23/B3) ^ (1 / 2) - 1 -> 0.23040036 | H25: =(H23/B3) ^ (1 / 3) - 1 -> 0.16027674
A27: --- FORECASTED SUMMARY --- | B27: OPTIMISTA
A28: Realized At | B28: ='Income Statement'!H2 -> Dec '22 | C28: ='Income Statement'!I2 -> Dec '23 | D28: ='Income Statement'!J2 -> Dec '24 | E28: ='Income Statement'!K2 -> Dec '25 | F28: FY+1 (Estimate) | G28: FY+2 (Estimate) | H28: FY+3 (Estimate)
A29: Market Cap | B29: =B7 -> 304773.46 | C29: =C7 -> 463924.97 | D29: =D7 -> 387177.53 | E29: =E7 -> 227170.59 | F29: =F7 -> 174021.92 | J29: Cambiar múltiplo
A30: NTM P/OCF Multiple | B30: =B8 -> 27.356024 | C30: =C8 -> 28.15335 | D30: =D8 -> 20.306265 | E30: =E8 -> 12.390605 | F30: =IFERROR(IF(J30<>"",J30,F19*1.1),"") -> 13.629665 | G30: =F30 -> 13.629665 | H30: =F30 -> 13.629665
A31: OCF | B31: =B29/B30 -> 11141 | C31: ='Financials Multiples'!B105 -> 16478.5 | D31: ='Financials Multiples'!C105 -> 19066.9 | E31: ='Financials Multiples'!D105 -> 18334.1 | F31: ='Financials Multiples'!E105 -> 19476.379 | G31: ='Financials Multiples'!F105 -> 19063.663 | H31: ='Financials Multiples'!G105 -> 18227.488
A32: Implied Target Stock Price | F32: =F30*(F31/'Financials Multiples'!E110) -> 59.757897 | G32: =G30*(G31/'Financials Multiples'!F110) -> 58.800382 | H32: =H30*(H31/'Financials Multiples'!G110) -> 56.51807
A33: Cumulative Dividends/Share | F33: ='Financials Multiples'!E114 -> 1.8266 | G33: ='Financials Multiples'!F114 -> 1.9552514 | H33: ='Financials Multiples'!G114 -> 2.0839027
A34: Total Target Price + Dividends | F34: =F32+F33 -> 61.584497 | G34: =G32+G33 -> 60.755633 | H34: =H32+H33 -> 58.601973
A35: Total Return | F35: =(F34-B3)/B3 -> 0.56305829 | G35: =(G34-B3)/B3 -> 0.54202114 | H35: =(H34-B3)/B3 -> 0.48735973
A36: Total IRR (Annualized Return) | F36: =(F34/B3) ^ (1 / 1) - 1 -> 0.56305829 | G36: =(G34/B3) ^ (1 / 2) - 1 -> 0.24178144 | H36: =(H34/B3) ^ (1 / 3) - 1 -> 0.14148972
A39: P/OCF Last 10Y | B39: =MEDIAN('Trailing Valuation'!B15:K15) -> 21.032127
A40: P/OCF Last 5Y | B40: =MEDIAN('Trailing Valuation'!G15:K15) -> 27.356024
A41: P/OCF Last 3Y | B41: =MEDIAN('Trailing Valuation'!I15:K15) -> 22.062152
A42: P/OCF TTM | B42: ='Trailing Valuation'!L15 -> 8.4518509
A45: Matriz de Sensibilidad: Precio Objetivo Implícito (FY+3)
A46: P/OCF \ OCF | B46: =$H$20*0.9 -> 18984.335 | C46: =$H$20*0.95 -> 20039.02 | D46: =$H$20 -> 21093.706 | E46: =$H$20*1.05 -> 22148.391 | F46: =$H$20*1.1 -> 23203.076
A47: =$F$19*0.9 -> 11.151544 | B47: =$A47*(B$46/'Financials Multiples'!$E$70) -> 47.657615 | C47: =$A47*(C$46/'Financials Multiples'!$E$70) -> 50.30526 | D47: =$A47*(D$46/'Financials Multiples'!$E$70) -> 52.952906 | E47: =$A47*(E$46/'Financials Multiples'!$E$70) -> 55.600551 | F47: =$A47*(F$46/'Financials Multiples'!$E$70) -> 58.248196
A48: =$F$19*0.95 -> 11.771075 | B48: =$A48*(B$46/'Financials Multiples'!$E$70) -> 50.30526 | C48: =$A48*(C$46/'Financials Multiples'!$E$70) -> 53.099997 | D48: =$A48*(D$46/'Financials Multiples'!$E$70) -> 55.894734 | E48: =$A48*(E$46/'Financials Multiples'!$E$70) -> 58.68947 | F48: =$A48*(F$46/'Financials Multiples'!$E$70) -> 61.484207
A49: =$F$19 -> 12.390605 | B49: =$A49*(B$46/'Financials Multiples'!$E$70) -> 52.952906 | C49: =$A49*(C$46/'Financials Multiples'!$E$70) -> 55.894734 | D49: =$A49*(D$46/'Financials Multiples'!$E$70) -> 58.836562 | E49: =$A49*(E$46/'Financials Multiples'!$E$70) -> 61.77839 | F49: =$A49*(F$46/'Financials Multiples'!$E$70) -> 64.720218
A50: =$F$19*1.05 -> 13.010135 | B50: =$A50*(B$46/'Financials Multiples'!$E$70) -> 55.600551 | C50: =$A50*(C$46/'Financials Multiples'!$E$70) -> 58.68947 | D50: =$A50*(D$46/'Financials Multiples'!$E$70) -> 61.77839 | E50: =$A50*(E$46/'Financials Multiples'!$E$70) -> 64.867309 | F50: =$A50*(F$46/'Financials Multiples'!$E$70) -> 67.956229
A51: =$F$19*1.1 -> 13.629665 | B51: =$A51*(B$46/'Financials Multiples'!$E$70) -> 58.248196 | C51: =$A51*(C$46/'Financials Multiples'!$E$70) -> 61.484207 | D51: =$A51*(D$46/'Financials Multiples'!$E$70) -> 64.720218 | E51: =$A51*(E$46/'Financials Multiples'!$E$70) -> 67.956229 | F51: =$A51*(F$46/'Financials Multiples'!$E$70) -> 71.19224

Sheet PE
A1: ='Input sheet'!A1 -> Novo Nordisk (NYSE:NVO) | C1: Precio | D1: ='Input sheet'!D1 -> 39.4
A2: ⚠️ Advertencia: Las celdas en VERDE, AMARILLO y ROJO son para entrada manual de datos.
A3: Price today: | B3: ='Input sheet'!D1 -> 39.4
A5: --- FORECASTED SUMMARY --- | B5: CONSERVADOR
A6: Realized At | B6: Dec '22 | C6: Dec '23 | D6: Dec '24 | E6: Dec '25 | F6: FY+1 (Estimate) | G6: FY+2 (Estimate) | H6: FY+3 (Estimate)
A7: Market Cap | B7: ='Trailing Valuation'!H5 -> 304773.46 | C7: ='Trailing Valuation'!I5 -> 463924.97 | D7: ='Trailing Valuation'!J5 -> 387177.53 | E7: ='Trailing Valuation'!K5 -> 227170.59 | F7: ='Trailing Valuation'!L5 -> 174021.92 | J7: Cambiar múltiplo
A8: NTM P/E Multiple | B8: ='Trailing Valuation'!H13 -> 38.974508 | C8: =C7/C9 -> 38.211115 | D8: =D7/D9 -> 26.426877 | E8: =E7/E9 -> 14.676335 | F8: =IFERROR(IF(J8<>"",J8,F19*0.9),"") -> 13.208702 | G8: =F8 -> 13.208702 | H8: =F8 -> 13.208702
A9: Net Income | B9: =B7/B8 -> 7819.8156 | C9: ='Financials Multiples'!B15 -> 12141.1 | D9: ='Financials Multiples'!C15 -> 14650.9 | E9: ='Financials Multiples'!D15 -> 15478.7 | F9: ='Financials Multiples'!E15 -> 18023.108 | G9: ='Financials Multiples'!F15 -> 18414.63 | H9: ='Financials Multiples'!G15 -> 18656.259
A10: Implied Target Stock Price | F10: =F8*(F9/'Financials Multiples'!E31) -> 53.59098 | G10: =G8*(G9/'Financials Multiples'!F31) -> 55.044223 | H10: =H8*(H9/'Financials Multiples'!G31) -> 56.060892
A11: Cumulative Dividends/Share | F11: ='Financials Multiples'!E35 -> 1.8266 | G11: ='Financials Multiples'!F35 -> 1.9552514 | H11: ='Financials Multiples'!G35 -> 2.0839027
A12: Total Target Price + Dividends | F12: =F10+F11 -> 55.41758 | G12: =G10+G11 -> 56.999474 | H12: =H10+H11 -> 58.144795
A13: Total Return | F13: =(F12-B3)/B3 -> 0.40653757 | G13: =(G12-B3)/B3 -> 0.44668716 | H13: =(H12-B3)/B3 -> 0.47575621
A14: Total IRR (Annualized Return) | F14: =(F12/B3) ^ (1 / 1) - 1 -> 0.40653757 | G14: =(G12/B3) ^ (1 / 2) - 1 -> 0.20278309 | H14: =(H12/B3) ^ (1 / 3) - 1 -> 0.13851356
A16: --- FORECASTED SUMMARY --- | B16: BASE
A17: Realized At | B17: Dec '22 | C17: Dec '23 | D17: Dec '24 | E17: Dec '25 | F17: FY+1 (Estimate) | G17: FY+2 (Estimate) | H17: FY+3 (Estimate)
A18: Market Cap | B18: =B7 -> 304773.46 | C18: =C7 -> 463924.97 | D18: =D7 -> 387177.53 | E18: =E7 -> 227170.59 | F18: =F7 -> 174021.92 | J18: Cambiar múltiplo
A19: NTM P/E Multiple | B19: =B8 -> 38.974508 | C19: =C8 -> 38.211115 | D19: =D8 -> 26.426877 | E19: =E8 -> 14.676335 | F19: =IFERROR(IF(J19<>"",J19,MEDIAN('Trailing Valuation'!G13:K13)),"") -> 14.676335 | G19: =F19 -> 14.676335 | H19: =F19 -> 14.676335 | J19: =MIN(B19:E19) -> 14.676335
A20: Net Income | B20: =B18/B19 -> 7819.8156 | C20: ='Financials Multiples'!B54 -> 12141.1 | D20: ='Financials Multiples'!C54 -> 14650.9 | E20: ='Financials Multiples'!D54 -> 15478.7 | F20: ='Financials Multiples'!E54 -> 17219.53 | G20: ='Financials Multiples'!F54 -> 17447.18 | H20: ='Financials Multiples'!G54 -> 17863.752
A21: Implied Target Stock Price | F21: =F19*(F20/'Financials Multiples'!E70) -> 56.890637 | G21: =G19*(G20/'Financials Multiples'!F70) -> 57.947068 | H21: =H19*(H20/'Financials Multiples'!G70) -> 59.643842
A22: Cumulative Dividends/Share | F22: ='Financials Multiples'!E74 -> 1.8266 | G22: ='Financials Multiples'!F74 -> 1.9552514 | H22: ='Financials Multiples'!G74 -> 2.0839027
A23: Total Target Price + Dividends | F23: =F21+F22 -> 58.717237 | G23: =G21+G22 -> 59.90232 | H23: =H21+H22 -> 61.727745
A24: Total Return | F24: =(F23-B3)/B3 -> 0.49028521 | G24: =(G23-B3)/B3 -> 0.52036345 | H24: =(H23-B3)/B3 -> 0.56669404
A25: Total IRR (Annualized Return) | F25: =(F23/B3) ^ (1 / 1) - 1 -> 0.49028521 | G25: =(G23/B3) ^ (1 / 2) - 1 -> 0.23303019 | H25: =(H23/B3) ^ (1 / 3) - 1 -> 0.16143452
A27: --- FORECASTED SUMMARY --- | B27: OPTIMISTA
A28: Realized At | B28: Dec '22 | C28: Dec '23 | D28: Dec '24 | E28: Dec '25 | F28: FY+1 (Estimate) | G28: FY+2 (Estimate) | H28: FY+3 (Estimate)
A29: Market Cap | B29: =B7 -> 304773.46 | C29: =C7 -> 463924.97 | D29: =D7 -> 387177.53 | E29: =E7 -> 227170.59 | F29: =F7 -> 174021.92 | J29: Cambiar múltiplo
A30: NTM P/E Multiple | B30: =B8 -> 38.974508 | C30: =C8 -> 38.211115 | D30: =D8 -> 26.426877 | E30: =E8 -> 14.676335 | F30: =IFERROR(IF(J30<>"",J30,F19*1.1),"") -> 16.143969 | G30: =F30 -> 16.143969 | H30: =F30 -> 16.143969
A31: Net Income | B31: =B29/B30 -> 7819.8156 | C31: ='Financials Multiples'!B94 -> 12141.1 | D31: ='Financials Multiples'!C94 -> 14650.9 | E31: ='Financials Multiples'!D94 -> 15478.7 | F31: ='Financials Multiples'!E94 -> 17004.285 | G31: ='Financials Multiples'!F94 -> 16459.605 | H31: ='Financials Multiples'!G94 -> 15764.648
A32: Implied Target Stock Price | F32: =F30*(F31/'Financials Multiples'!E110) -> 61.797455 | G32: =G30*(G31/'Financials Multiples'!F110) -> 60.133753 | H32: =H30*(H31/'Financials Multiples'!G110) -> 57.898846
A33: Cumulative Dividends/Share | F33: ='Financials Multiples'!E114 -> 1.8266 | G33: ='Financials Multiples'!F114 -> 1.9552514 | H33: ='Financials Multiples'!G114 -> 2.0839027
A34: Total Target Price + Dividends | F34: =F32+F33 -> 63.624055 | G34: =G32+G33 -> 62.089005 | H34: =H32+H33 -> 59.982748
A35: Total Return | F35: =(F34-B3)/B3 -> 0.61482372 | G35: =(G34-B3)/B3 -> 0.57586306 | H35: =(H34-B3)/B3 -> 0.52240478
A36: Total IRR (Annualized Return) | F36: =(F34/B3) ^ (1 / 1) - 1 -> 0.61482372 | G36: =(G34/B3) ^ (1 / 2) - 1 -> 0.25533384 | H36: =(H34/B3) ^ (1 / 3) - 1 -> 0.15038545
A39: P/E Last 10Y | B39: =MEDIAN('Trailing Valuation'!B13:K13) -> 24.620225
A40: P/E Last 5Y | B40: =MEDIAN('Trailing Valuation'!G13:K13) -> 34.010922
A41: P/E Last 3Y | B41: =MEDIAN('Trailing Valuation'!I13:K13) -> 26.47883
A42: P/E TTM | B42: ='Trailing Valuation'!L13 -> 11.161473
A45: Matriz de Sensibilidad: Precio Objetivo Implícito (FY+3)
A46: P/E \ Net Income | B46: =$H$20*0.9 -> 16077.376 | C46: =$H$20*0.95 -> 16970.564 | D46: =$H$20 -> 17863.752 | E46: =$H$20*1.05 -> 18756.939 | F46: =$H$20*1.1 -> 19650.127
A47: =$F$19*0.9 -> 13.208702 | B47: =$A47*(B$46/'Financials Multiples'!$E$70) -> 47.805427 | C47: =$A47*(C$46/'Financials Multiples'!$E$70) -> 50.461285 | D47: =$A47*(D$46/'Financials Multiples'!$E$70) -> 53.117142 | E47: =$A47*(E$46/'Financials Multiples'!$E$70) -> 55.772999 | F47: =$A47*(F$46/'Financials Multiples'!$E$70) -> 58.428856
A48: =$F$19*0.95 -> 13.942518 | B48: =$A48*(B$46/'Financials Multiples'!$E$70) -> 50.461285 | C48: =$A48*(C$46/'Financials Multiples'!$E$70) -> 53.264689 | D48: =$A48*(D$46/'Financials Multiples'!$E$70) -> 56.068094 | E48: =$A48*(E$46/'Financials Multiples'!$E$70) -> 58.871499 | F48: =$A48*(F$46/'Financials Multiples'!$E$70) -> 61.674903
A49: =$F$19 -> 14.676335 | B49: =$A49*(B$46/'Financials Multiples'!$E$70) -> 53.117142 | C49: =$A49*(C$46/'Financials Multiples'!$E$70) -> 56.068094 | D49: =$A49*(D$46/'Financials Multiples'!$E$70) -> 59.019046 | E49: =$A49*(E$46/'Financials Multiples'!$E$70) -> 61.969999 | F49: =$A49*(F$46/'Financials Multiples'!$E$70) -> 64.920951
A50: =$F$19*1.05 -> 15.410152 | B50: =$A50*(B$46/'Financials Multiples'!$E$70) -> 55.772999 | C50: =$A50*(C$46/'Financials Multiples'!$E$70) -> 58.871499 | D50: =$A50*(D$46/'Financials Multiples'!$E$70) -> 61.969999 | E50: =$A50*(E$46/'Financials Multiples'!$E$70) -> 65.068498 | F50: =$A50*(F$46/'Financials Multiples'!$E$70) -> 68.166998
A51: =$F$19*1.1 -> 16.143969 | B51: =$A51*(B$46/'Financials Multiples'!$E$70) -> 58.428856 | C51: =$A51*(C$46/'Financials Multiples'!$E$70) -> 61.674903 | D51: =$A51*(D$46/'Financials Multiples'!$E$70) -> 64.920951 | E51: =$A51*(E$46/'Financials Multiples'!$E$70) -> 68.166998 | F51: =$A51*(F$46/'Financials Multiples'!$E$70) -> 71.413046

Sheet PFCFE
A1: ='Input sheet'!A1 -> Novo Nordisk (NYSE:NVO) | C1: Precio | D1: ='Input sheet'!D1 -> 39.4
A2: ⚠️ Advertencia: Las celdas en VERDE, AMARILLO y ROJO son para entrada manual de datos.
A3: Price today: | B3: ='Input sheet'!D1 -> 39.4
A5: --- FORECASTED SUMMARY --- | B5: CONSERVADOR
A6: Realized At | B6: ='Income Statement'!H2 -> Dec '22 | C6: ='Income Statement'!I2 -> Dec '23 | D6: ='Income Statement'!J2 -> Dec '24 | E6: ='Income Statement'!K2 -> Dec '25 | F6: FY+1 (Estimate) | G6: FY+2 (Estimate) | H6: FY+3 (Estimate)
A7: Market Cap | B7: ='Trailing Valuation'!H5 -> 304773.46 | C7: ='Trailing Valuation'!I5 -> 463924.97 | D7: ='Trailing Valuation'!J5 -> 387177.53 | E7: ='Trailing Valuation'!K5 -> 227170.59 | F7: ='Trailing Valuation'!L5 -> 174021.92 | J7: Cambiar múltiplo
A8: NTM P/FCFE Multiple | B8: ='Trailing Valuation'!H16 -> 32.334305 | C8: =C7/C9 -> 37.049975 | D8: =D7/D9 -> 16.964209 | E8: =E7/E9 -> 17.494443 | F8: =IFERROR(IF(J8<>"",J8,F19*0.9),"") -> 15.267788 | G8: =F8 -> 15.267788 | H8: =F8 -> 15.267788
A9: FCFE | B9: =B7/B8 -> 9425.7 | C9: ='Financials Multiples'!B29 -> 12521.6 | D9: ='Financials Multiples'!C29 -> 22823.2 | E9: ='Financials Multiples'!D29 -> 12985.3 | F9: ='Financials Multiples'!E29 -> 18597.6 | G9: ='Financials Multiples'!F29 -> 19284.546 | H9: ='Financials Multiples'!G29 -> 19523.435
A10: Implied Target Stock Price | F10: =F8*(F9/'Financials Multiples'!E31) -> 63.919726 | G10: =G8*(G9/'Financials Multiples'!F31) -> 66.630665 | H10: =H8*(H9/'Financials Multiples'!G31) -> 67.812174
A11: Cumulative Dividends/Share | F11: ='Financials Multiples'!E35 -> 1.8266 | G11: ='Financials Multiples'!F35 -> 1.9552514 | H11: ='Financials Multiples'!G35 -> 2.0839027
A12: Total Target Price + Dividends | F12: =F10+F11 -> 65.746326 | G12: =G10+G11 -> 68.585916 | H12: =H10+H11 -> 69.896077
A13: Total Return | F13: =(F12-B3)/B3 -> 0.66868848 | G13: =(G12-B3)/B3 -> 0.7407593 | H13: =(H12-B3)/B3 -> 0.7740121
A14: Total IRR (Annualized Return) | F14: =(F12/B3) ^ (1 / 1) - 1 -> 0.66868848 | G14: =(G12/B3) ^ (1 / 2) - 1 -> 0.31937838 | H14: =(H12/B3) ^ (1 / 3) - 1 -> 0.21055779
A16: --- FORECASTED SUMMARY --- | B16: BASE
A17: Realized At | B17: ='Income Statement'!H2 -> Dec '22 | C17: ='Income Statement'!I2 -> Dec '23 | D17: ='Income Statement'!J2 -> Dec '24 | E17: ='Income Statement'!K2 -> Dec '25 | F17: FY+1 (Estimate) | G17: FY+2 (Estimate) | H17: FY+3 (Estimate)
A18: Market Cap | B18: =B7 -> 304773.46 | C18: =C7 -> 463924.97 | D18: =D7 -> 387177.53 | E18: =E7 -> 227170.59 | F18: =F7 -> 174021.92 | J18: Cambiar múltiplo
A19: NTM P/FCFE Multiple | B19: =B8 -> 32.334305 | C19: =C8 -> 37.049975 | D19: =D8 -> 16.964209 | E19: =E8 -> 17.494443 | F19: =IFERROR(IF(J19<>"",J19,MEDIAN('Trailing Valuation'!G16:K16)),"") -> 16.964209 | G19: =F19 -> 16.964209 | H19: =F19 -> 16.964209 | J19: =MIN(B19:E19) -> 16.964209
A20: FCFE | B20: =B18/B19 -> 9425.7 | C20: ='Financials Multiples'!B68 -> 12521.6 | D20: ='Financials Multiples'!C68 -> 22823.2 | E20: ='Financials Multiples'!D68 -> 12985.3 | F20: ='Financials Multiples'!E68 -> 17624.589 | G20: ='Financials Multiples'!F68 -> 18365.963 | H20: ='Financials Multiples'!G68 -> 18807.682
A21: Implied Target Stock Price | F21: =F19*(F20/'Financials Multiples'!E70) -> 67.30611 | G21: =G19*(G20/'Financials Multiples'!F70) -> 70.507598 | H21: =H19*(H20/'Financials Multiples'!G70) -> 72.584553
A22: Cumulative Dividends/Share | F22: ='Financials Multiples'!E74 -> 1.8266 | G22: ='Financials Multiples'!F74 -> 1.9552514 | H22: ='Financials Multiples'!G74 -> 2.0839027
A23: Total Target Price + Dividends | F23: =F21+F22 -> 69.13271 | G23: =G21+G22 -> 72.46285 | H23: =H21+H22 -> 74.668456
A24: Total Return | F24: =(F23-B3)/B3 -> 0.7546373 | G24: =(G23-B3)/B3 -> 0.83915862 | H24: =(H23-B3)/B3 -> 0.89513848
A25: Total IRR (Annualized Return) | F25: =(F23/B3) ^ (1 / 1) - 1 -> 0.7546373 | G25: =(G23/B3) ^ (1 / 2) - 1 -> 0.35615582 | H25: =(H23/B3) ^ (1 / 3) - 1 -> 0.23750506
A27: --- FORECASTED SUMMARY --- | B27: OPTIMISTA
A28: Realized At | B28: ='Income Statement'!H2 -> Dec '22 | C28: ='Income Statement'!I2 -> Dec '23 | D28: ='Income Statement'!J2 -> Dec '24 | E28: ='Income Statement'!K2 -> Dec '25 | F28: FY+1 (Estimate) | G28: FY+2 (Estimate) | H28: FY+3 (Estimate)
A29: Market Cap | B29: =B7 -> 304773.46 | C29: =C7 -> 463924.97 | D29: =D7 -> 387177.53 | E29: =E7 -> 227170.59 | F29: =F7 -> 174021.92 | J29: Cambiar múltiplo
A30: NTM P/FCFE Multiple | B30: =B8 -> 32.334305 | C30: =C8 -> 37.049975 | D30: =D8 -> 16.964209 | E30: =E8 -> 17.494443 | F30: =IFERROR(IF(J30<>"",J30,F19*1.1),"") -> 18.66063 | G30: =F30 -> 18.66063 | H30: =F30 -> 18.66063
A31: FCFE | B31: =B29/B30 -> 9425.7 | C31: ='Financials Multiples'!B108 -> 12521.6 | D31: ='Financials Multiples'!C108 -> 22823.2 | E31: ='Financials Multiples'!D108 -> 12985.3 | F31: ='Financials Multiples'!E108 -> 17369.027 | G31: ='Financials Multiples'!F108 -> 17065.893 | H31: ='Financials Multiples'!G108 -> 16333.602
A32: Implied Target Stock Price | F32: =F30*(F31/'Financials Multiples'!E110) -> 72.963167 | G32: =G30*(G31/'Financials Multiples'!F110) -> 72.06824 | H32: =H30*(H31/'Financials Multiples'!G110) -> 69.339959
A33: Cumulative Dividends/Share | F33: ='Financials Multiples'!E114 -> 1.8266 | G33: ='Financials Multiples'!F114 -> 1.9552514 | H33: ='Financials Multiples'!G114 -> 2.0839027
A34: Total Target Price + Dividends | F34: =F32+F33 -> 74.789767 | G34: =G32+G33 -> 74.023491 | H34: =H32+H33 -> 71.423862
A35: Total Return | F35: =(F34-B3)/B3 -> 0.89821743 | G35: =(G34-B3)/B3 -> 0.87876881 | H35: =(H34-B3)/B3 -> 0.81278837
A36: Total IRR (Annualized Return) | F36: =(F34/B3) ^ (1 / 1) - 1 -> 0.89821743 | G36: =(G34/B3) ^ (1 / 2) - 1 -> 0.37068188 | H36: =(H34/B3) ^ (1 / 3) - 1 -> 0.2193144
A39: P/FCFE Last 10Y | B39: =MEDIAN('Trailing Valuation'!B16:K16) -> 25.87229
A40: P/FCFE Last 5Y | B40: =MEDIAN('Trailing Valuation'!G16:K16) -> 33.284058
A41: P/FCFE Last 3Y | B41: =MEDIAN('Trailing Valuation'!I16:K16) -> 36.160821
A42: P/FCFE TTM | B42: ='Trailing Valuation'!L16 -> 14.697673
A45: Matriz de Sensibilidad: Precio Objetivo Implícito (FY+3)
A46: P/FCFE \ FCFE | B46: =$H$20*0.9 -> 16926.914 | C46: =$H$20*0.95 -> 17867.298 | D46: =$H$20 -> 18807.682 | E46: =$H$20*1.05 -> 19748.067 | F46: =$H$20*1.1 -> 20688.451
A47: =$F$19*0.9 -> 15.267788 | B47: =$A47*(B$46/'Financials Multiples'!$E$70) -> 58.1776 | C47: =$A47*(C$46/'Financials Multiples'!$E$70) -> 61.409689 | D47: =$A47*(D$46/'Financials Multiples'!$E$70) -> 64.641778 | E47: =$A47*(E$46/'Financials Multiples'!$E$70) -> 67.873867 | F47: =$A47*(F$46/'Financials Multiples'!$E$70) -> 71.105955
A48: =$F$19*0.95 -> 16.115998 | B48: =$A48*(B$46/'Financials Multiples'!$E$70) -> 61.409689 | C48: =$A48*(C$46/'Financials Multiples'!$E$70) -> 64.821338 | D48: =$A48*(D$46/'Financials Multiples'!$E$70) -> 68.232987 | E48: =$A48*(E$46/'Financials Multiples'!$E$70) -> 71.644637 | F48: =$A48*(F$46/'Financials Multiples'!$E$70) -> 75.056286
A49: =$F$19 -> 16.964209 | B49: =$A49*(B$46/'Financials Multiples'!$E$70) -> 64.641778 | C49: =$A49*(C$46/'Financials Multiples'!$E$70) -> 68.232987 | D49: =$A49*(D$46/'Financials Multiples'!$E$70) -> 71.824197 | E49: =$A49*(E$46/'Financials Multiples'!$E$70) -> 75.415407 | F49: =$A49*(F$46/'Financials Multiples'!$E$70) -> 79.006617
A50: =$F$19*1.05 -> 17.812419 | B50: =$A50*(B$46/'Financials Multiples'!$E$70) -> 67.873867 | C50: =$A50*(C$46/'Financials Multiples'!$E$70) -> 71.644637 | D50: =$A50*(D$46/'Financials Multiples'!$E$70) -> 75.415407 | E50: =$A50*(E$46/'Financials Multiples'!$E$70) -> 79.186178 | F50: =$A50*(F$46/'Financials Multiples'!$E$70) -> 82.956948
A51: =$F$19*1.1 -> 18.66063 | B51: =$A51*(B$46/'Financials Multiples'!$E$70) -> 71.105955 | C51: =$A51*(C$46/'Financials Multiples'!$E$70) -> 75.056286 | D51: =$A51*(D$46/'Financials Multiples'!$E$70) -> 79.006617 | E51: =$A51*(E$46/'Financials Multiples'!$E$70) -> 82.956948 | F51: =$A51*(F$46/'Financials Multiples'!$E$70) -> 86.907279

Sheet EVEBITDA
A1: ='Input sheet'!A1 -> Novo Nordisk (NYSE:NVO) | C1: Precio | D1: ='Input sheet'!D1 -> 39.4
A2: ⚠️ Advertencia: Las celdas en VERDE, AMARILLO y ROJO son para entrada manual de datos.
A3: Price today: | B3: ='Input sheet'!D1 -> 39.4
A5: --- FORECASTED SUMMARY --- | B5: CONSERVADOR
A6: Realized At | B6: Dec '22 | C6: Dec '23 | D6: Dec '24 | E6: Dec '25 | F6: FY+1 (Estimate) | G6: FY+2 (Estimate) | H6: FY+3 (Estimate)
A7: Enterprise Value | B7: ='Trailing Valuation'!H6 -> 305090.36 | C7: ='Trailing Valuation'!I6 -> 463447.07 | D7: ='Trailing Valuation'!J6 -> 397831.33 | E7: ='Trailing Valuation'!K6 -> 243531.19 | F7: ='Trailing Valuation'!L6 -> 188525.82 | J7: Cambiar múltiplo
A8: NTM EV/EBITDA Multiple | B8: ='Trailing Valuation'!H21 -> 26.290015 | C8: =C7/C9 -> 28.524033 | D8: =D7/D9 -> 18.598331 | E8: =E7/E9 -> 10.769998 | F8: =IFERROR(IF(J8<>"",J8,F19*0.9),"") -> 9.692998 | G8: =F8 -> 9.692998 | H8: =F8 -> 9.692998
A9: EBITDA | B9: =B7/B8 -> 11604.8 | C9: ='Financials Multiples'!B18 -> 16247.6 | D9: ='Financials Multiples'!C18 -> 21390.7 | E9: ='Financials Multiples'!D18 -> 22612 | F9: ='Financials Multiples'!E18 -> 25065.211 | G9: ='Financials Multiples'!F18 -> 25855.405 | H9: ='Financials Multiples'!G18 -> 26162.108
A10: Implied Target Stock Price | F10: =F8*(F9/'Financials Multiples'!E31) -> 54.692954 | G10: =G8*(G9/'Financials Multiples'!F31) -> 56.715018 | H10: =H8*(H9/'Financials Multiples'!G31) -> 57.69075
A11: Cumulative Dividends/Share | F11: ='Financials Multiples'!E35 -> 1.8266 | G11: ='Financials Multiples'!F35 -> 1.9552514 | H11: ='Financials Multiples'!G35 -> 2.0839027
A12: Total Target Price + Dividends | F12: =F10+F11 -> 56.519554 | G12: =G10+G11 -> 58.670269 | H12: =H10+H11 -> 59.774653
A13: Total Return | F13: =(F12-B3)/B3 -> 0.43450646 | G13: =(G12-B3)/B3 -> 0.48909313 | H13: =(H12-B3)/B3 -> 0.51712317
A14: Total IRR (Annualized Return) | F14: =(F12/B3) ^ (1 / 1) - 1 -> 0.43450646 | G14: =(G12/B3) ^ (1 / 2) - 1 -> 0.22028404 | H14: =(H12/B3) ^ (1 / 3) - 1 -> 0.14905358
A16: --- FORECASTED SUMMARY --- | B16: BASE
A17: Realized At | B17: Dec '22 | C17: Dec '23 | D17: Dec '24 | E17: Dec '25 | F17: FY+1 (Estimate) | G17: FY+2 (Estimate) | H17: FY+3 (Estimate)
A18: Enterprise Value | B18: =B7 -> 305090.36 | C18: =C7 -> 463447.07 | D18: =D7 -> 397831.33 | E18: =E7 -> 243531.19 | F18: =F7 -> 188525.82 | J18: Cambiar múltiplo
A19: NTM EV/EBITDA Multiple | B19: =B8 -> 26.290015 | C19: =C8 -> 28.524033 | D19: =D8 -> 18.598331 | E19: =E8 -> 10.769998 | F19: =IFERROR(IF(J19<>"",J19,MEDIAN('Trailing Valuation'!G21:K21)),"") -> 10.769998 | G19: =F19 -> 10.769998 | H19: =F19 -> 10.769998 | J19: =MIN(B19:E19) -> 10.769998
A20: EBITDA | B20: =B18/B19 -> 11604.8 | C20: ='Financials Multiples'!B57 -> 16247.6 | D20: ='Financials Multiples'!C57 -> 21390.7 | E20: ='Financials Multiples'!D57 -> 22612 | F20: ='Financials Multiples'!E57 -> 23947.654 | G20: ='Financials Multiples'!F57 -> 24610.032 | H20: ='Financials Multiples'!G57 -> 25224.351
A21: Implied Target Stock Price | F21: =F19*(F20/'Financials Multiples'!E70) -> 58.060461 | G21: =G19*(G20/'Financials Multiples'!F70) -> 59.981373 | H21: =H19*(H20/'Financials Multiples'!G70) -> 61.803196
A22: Cumulative Dividends/Share | F22: ='Financials Multiples'!E74 -> 1.8266 | G22: ='Financials Multiples'!F74 -> 1.9552514 | H22: ='Financials Multiples'!G74 -> 2.0839027
A23: Total Target Price + Dividends | F23: =F21+F22 -> 59.887061 | G23: =G21+G22 -> 61.936624 | H23: =H21+H22 -> 63.887099
A24: Total Return | F24: =(F23-B3)/B3 -> 0.51997617 | G24: =(G23-B3)/B3 -> 0.57199553 | H24: =(H23-B3)/B3 -> 0.62149997
A25: Total IRR (Annualized Return) | F25: =(F23/B3) ^ (1 / 1) - 1 -> 0.51997617 | G25: =(G23/B3) ^ (1 / 2) - 1 -> 0.25379246 | H25: =(H23/B3) ^ (1 / 3) - 1 -> 0.17482266
A27: --- FORECASTED SUMMARY --- | B27: OPTIMISTA
A28: Realized At | B28: Dec '22 | C28: Dec '23 | D28: Dec '24 | E28: Dec '25 | F28: FY+1 (Estimate) | G28: FY+2 (Estimate) | H28: FY+3 (Estimate)
A29: Enterprise Value | B29: =B7 -> 305090.36 | C29: =C7 -> 463447.07 | D29: =D7 -> 397831.33 | E29: =E7 -> 243531.19 | F29: =F7 -> 188525.82 | J29: Cambiar múltiplo
A30: NTM EV/EBITDA Multiple | B30: =B8 -> 26.290015 | C30: =C8 -> 28.524033 | D30: =D8 -> 18.598331 | E30: =E8 -> 10.769998 | F30: =IFERROR(IF(J30<>"",J30,F19*1.1),"") -> 11.846998 | G30: =F30 -> 11.846998 | H30: =F30 -> 11.846998
A31: EBITDA | B31: =B18/B19 -> 11604.8 | C31: ='Financials Multiples'!B97 -> 16247.6 | D31: ='Financials Multiples'!C97 -> 21390.7 | E31: ='Financials Multiples'!D97 -> 22612 | F31: ='Financials Multiples'!E97 -> 23648.308 | G31: ='Financials Multiples'!F97 -> 23099.028 | H31: ='Financials Multiples'!G97 -> 22091.113
A32: Implied Target Stock Price | F32: =F30*(F31/'Financials Multiples'!E110) -> 63.068176 | G32: =G30*(G31/'Financials Multiples'!F110) -> 61.928508 | H32: =H30*(H31/'Financials Multiples'!G110) -> 59.538956
A33: Cumulative Dividends/Share | F33: ='Financials Multiples'!E114 -> 1.8266 | G33: ='Financials Multiples'!F114 -> 1.9552514 | H33: ='Financials Multiples'!G114 -> 2.0839027
A34: Total Target Price + Dividends | F34: =F32+F33 -> 64.894776 | G34: =G32+G33 -> 63.883759 | H34: =H32+H33 -> 61.622859
A35: Total Return | F35: =(F34-B3)/B3 -> 0.64707553 | G35: =(G34-B3)/B3 -> 0.62141521 | H35: =(H34-B3)/B3 -> 0.56403194
A36: Total IRR (Annualized Return) | F36: =(F34/B3) ^ (1 / 1) - 1 -> 0.64707553 | G36: =(G34/B3) ^ (1 / 2) - 1 -> 0.27334803 | H36: =(H34/B3) ^ (1 / 3) - 1 -> 0.16077632
A39: EV/EBITDA Last 10Y | B39: =MEDIAN('Trailing Valuation'!B21:K21) -> 17.215173
A40: EV/EBITDA Last 5Y | B40: =MEDIAN('Trailing Valuation'!G21:K21) -> 25.182803
A41: EV/EBITDA Last 3Y | B41: =MEDIAN('Trailing Valuation'!I21:K21) -> 18.598331
A42: EV/EBITDA TTM | B42: ='Trailing Valuation'!L21 -> 8.4742132
A45: Matriz de Sensibilidad: Precio Objetivo Implícito (FY+3)
A46: EV/EBITDA \ EBITDA | B46: =$H$20*0.9 -> 22701.916 | C46: =$H$20*0.95 -> 23963.133 | D46: =$H$20 -> 25224.351 | E46: =$H$20*1.05 -> 26485.569 | F46: =$H$20*1.1 -> 27746.786
A47: =$F$19*0.9 -> 9.692998 | B47: =$A47*(B$46/'Financials Multiples'!$E$70) -> 49.536182 | C47: =$A47*(C$46/'Financials Multiples'!$E$70) -> 52.288192 | D47: =$A47*(D$46/'Financials Multiples'!$E$70) -> 55.040202 | E47: =$A47*(E$46/'Financials Multiples'!$E$70) -> 57.792212 | F47: =$A47*(F$46/'Financials Multiples'!$E$70) -> 60.544222
A48: =$F$19*0.95 -> 10.231498 | B48: =$A48*(B$46/'Financials Multiples'!$E$70) -> 52.288192 | C48: =$A48*(C$46/'Financials Multiples'!$E$70) -> 55.193091 | D48: =$A48*(D$46/'Financials Multiples'!$E$70) -> 58.097991 | E48: =$A48*(E$46/'Financials Multiples'!$E$70) -> 61.00289 | F48: =$A48*(F$46/'Financials Multiples'!$E$70) -> 63.90779
A49: =$F$19 -> 10.769998 | B49: =$A49*(B$46/'Financials Multiples'!$E$70) -> 55.040202 | C49: =$A49*(C$46/'Financials Multiples'!$E$70) -> 58.097991 | D49: =$A49*(D$46/'Financials Multiples'!$E$70) -> 61.15578 | E49: =$A49*(E$46/'Financials Multiples'!$E$70) -> 64.213569 | F49: =$A49*(F$46/'Financials Multiples'!$E$70) -> 67.271358
A50: =$F$19*1.05 -> 11.308498 | B50: =$A50*(B$46/'Financials Multiples'!$E$70) -> 57.792212 | C50: =$A50*(C$46/'Financials Multiples'!$E$70) -> 61.00289 | D50: =$A50*(D$46/'Financials Multiples'!$E$70) -> 64.213569 | E50: =$A50*(E$46/'Financials Multiples'!$E$70) -> 67.424247 | F50: =$A50*(F$46/'Financials Multiples'!$E$70) -> 70.634926
A51: =$F$19*1.1 -> 11.846998 | B51: =$A51*(B$46/'Financials Multiples'!$E$70) -> 60.544222 | C51: =$A51*(C$46/'Financials Multiples'!$E$70) -> 63.90779 | D51: =$A51*(D$46/'Financials Multiples'!$E$70) -> 67.271358 | E51: =$A51*(E$46/'Financials Multiples'!$E$70) -> 70.634926 | F51: =$A51*(F$46/'Financials Multiples'!$E$70) -> 73.998493

Sheet Financials Multiples
A1: ='Input sheet'!A1 -> Novo Nordisk (NYSE:NVO) | C1: Precio | D1: ='Input sheet'!D1 -> 39.4
A2: Conservador
A3: Operating Data | B3: ='Income Statement'!I$2 -> Dec '23 | C3: ='Income Statement'!J$2 -> Dec '24 | D3: ='Income Statement'!K$2 -> Dec '25 | E3: FY+1 (Estimate) | F3: FY+2 (Estimate) | G3: FY+3 (Estimate) | H3: FY+4 (Estimate)
A4: Revenues | B4: ='Income Statement'!$I$3 -> 33697.5 | C4: ='Income Statement'!$J$3 -> 42130.2 | D4: ='Income Statement'!$K$3 -> 46702.4 | E4: =D4+(D4*E5) -> 46926.572 | F4: =E4+(E4*F5) -> 47151.819 | G4: =F4+(F4*G5) -> 47378.148 | H4: =G4+(G4*H5) -> 47605.563 | J4: Cambiar crecimiento
A5: % Change YoY | B5: =('Income Statement'!$I$3-'Income Statement'!$H$3)/'Income Statement'!$H$3 -> 0.34839621 | C5: =(C4-B4)/B4 -> 0.25024705 | D5: =(D4-C4)/C4 -> 0.10852548 | E5: ='Valuation output'!C55 -> 0.0048 | F5: ='Valuation output'!D55 -> 0.0048 | G5: ='Valuation output'!E55 -> 0.0048 | H5: ='Valuation output'!F55 -> 0.0048
A6: EBIT | B6: ='Income Statement'!$I$12 -> 14881.9 | C6: ='Income Statement'!$J$12 -> 18618.8 | D6: ='Income Statement'!$K$12 -> 19290.3 | E6: =E4*E8 -> 22289.556 | F6: =F4*F8 -> 22773.76 | G6: =G4*G8 -> 23072.587 | H6: =H4*H8 -> 23373.758
A7: % Change YoY | B7: =(B6-'Income Statement'!$H$12)/'Income Statement'!$H$12 -> 0.40859055 | C7: =(C6-B6)/B6 -> 0.25110369 | D7: =(D6-C6)/C6 -> 0.036065697 | E7: =(E6-D6)/D6 -> 0.15548 | F7: =(F6-E6)/E6 -> 0.021723377 | G7: =(G6-F6)/F6 -> 0.013121533 | H7: =(H6-G6)/G6 -> 0.013053182 | J7: Cambiar EBIT margen
A8: % Margin | B8: =B6/B4 -> 0.44163217 | C8: =C6/C4 -> 0.44193476 | D8: =D6/D4 -> 0.4130473 | E8: =IFERROR(IF(J8<>"",J8,'Valuation output'!C57),"") -> 0.47498795 | F8: =IFERROR(IF(K8<>"",K8,'Valuation output'!D57),"") -> 0.48298795 | G8: =IFERROR(IF(L8<>"",L8,'Valuation output'!E57),"") -> 0.48698795 | H8: =IFERROR(IF(M8<>"",M8,'Valuation output'!F57),"") -> 0.49098795
A9: % Incremental Margin | B9: =((B6- 'Income Statement'!$H$12) / (B4 - 'Income Statement'!$H$3)) -> 0.49580208 | C9: =((C6-B6) / (C4 - B4)) -> 0.44314395 | D9: =((D6-C6) / (D4 - C4)) -> 0.14686584 | E9: =((E6-D6) / (E4 - D4)) -> 13.379291 | F9: =((F6-E6) / (F4 - E4)) -> 2.1496546 | G9: =((G6-F6) / (G4 - F4)) -> 1.3203213 | H9: =((H6-G6) / (H4 - G4)) -> 1.3243213
A10: Interest / Other | B10: ='Income Statement'!I$18 -> 304.7 | C10: ='Income Statement'!J$18 -> -166.5 | D10: ='Income Statement'!K$18 -> 435.5 | E10: =E6*E11 -> 253.41795 | F10: =F6*F11 -> 258.92304 | G10: =G6*G11 -> 262.32051 | H10: =H6*H11 -> 265.74463
A11: % of EBIT | B11: =B10/B6 -> 0.020474536 | C11: =C10/C6 -> -0.0089425742 | D11: =D10/D6 -> 0.022576113 | E11: =AVERAGE(B11:D11) -> 0.011369358 | F11: =E11 -> 0.011369358 | G11: =E11 -> 0.011369358 | H11: =E11 -> 0.011369358
A12: EBT | B12: =B6+B10 -> 15186.6 | C12: =C6+C10 -> 18452.3 | D12: =D6+D10 -> 19725.8 | E12: =E6+E10 -> 22542.974 | F12: =F6+F10 -> 23032.683 | G12: =G6+G10 -> 23334.907 | H12: =H6+H10 -> 23639.502
A13: Taxes / Other | B13: ='Income Statement'!I$20 -> 3045.5 | C13: ='Income Statement'!J$20 -> 3801.4 | D13: ='Income Statement'!K$20 -> 4247.1 | E13: =E12*E14 -> 4519.8663 | F13: =F12*F14 -> 4618.053 | G13: =G12*G14 -> 4678.649 | H13: =H12*H14 -> 4739.7202 | J13: Cambiar Tax rate
A14: % of EBT | B14: =B13/B12 -> 0.20053863 | C14: =C13/C12 -> 0.20601226 | D14: =D13/D12 -> 0.21530686 | E14: =IFERROR(IF(J14<>"",J14,'Valuation output'!C59),"") -> 0.2005 | F14: =IFERROR(IF(K14<>"",K14,'Valuation output'!D59),"") -> 0.2005 | G14: =IFERROR(IF(L14<>"",L14,'Valuation output'!E59),"") -> 0.2005 | H14: =IFERROR(IF(M14<>"",M14,'Valuation output'!F59),"") -> 0.2005
A15: Net Income Normalized | B15: =B12-B13 -> 12141.1 | C15: =C12-C13 -> 14650.9 | D15: =D12-D13 -> 15478.7 | E15: =E12-E13 -> 18023.108 | F15: =F12-F13 -> 18414.63 | G15: =G12-G13 -> 18656.259 | H15: =H12-H13 -> 18899.782
A16: % Change YoY | B16: =(B15/'Income Statement'!$H$21)-1 -> 0.54827397 | C16: =(C15/B15)-1 -> 0.20671933 | D16: =(D15/C15)-1 -> 0.056501648 | E16: =(E15/D15)-1 -> 0.16438122 | F16: =(F15/E15)-1 -> 0.021723377 | G16: =(G15/F15)-1 -> 0.013121533 | H16: =(H15/G15)-1 -> 0.013053182
A17: % Margin | B17: =B15/B4 -> 0.36029676 | C17: =C15/C4 -> 0.34775292 | D17: =D15/D4 -> 0.33143265 | E17: =E15/E4 -> 0.38407041 | F17: =F15/F4 -> 0.39053913 | G17: =G15/G4 -> 0.39377349 | H17: =H15/H4 -> 0.39700785
A18: EBITDA | B18: =B6+'Cash Flow Statement'!$I$4 -> 16247.6 | C18: =C6+'Cash Flow Statement'!$J$4 -> 21390.7 | D18: =D6+'Cash Flow Statement'!$K$4 -> 22612 | E18: =E6+E20 -> 25065.211 | F18: =F6+F20 -> 25855.405 | G18: =G6+G20 -> 26162.108 | H18: =H6+H20 -> 26384.247 | J18: Cambiar EBITDA margen
A19: % Margin | B19: =B18/B4 -> 0.4821604 | C19: =C18/C4 -> 0.50772842 | D19: =D18/D4 -> 0.48417212 | E19: =E18/E4 -> 0.53413685 | F19: =F18/F4 -> 0.54834374 | G19: =G18/G4 -> 0.55219779 | H19: =H18/H4 -> 0.55422613
A20: D&A | B20: =B18-B6 -> 1365.7 | C20: =C18-C6 -> 2771.9 | D20: =D18-D6 -> 3321.7 | E20: =AVERAGE((B20/B4),(C20/C4),(D20/D4))*E4 -> 2775.6553 | F20: =AVERAGE((C20/C4),(D20/D4),(E20/E4))*F4 -> 3081.6447 | G20: =AVERAGE((D20/D4),(E20/E4),(F20/F4))*G4 -> 3089.5215 | H20: =AVERAGE((E20/E4),(F20/F4),(G20/G4))*H4 -> 3010.4892
A21: CapEx | B21: ='Cash Flow Statement'!I$15 -> -3744.1 | C21: ='Cash Flow Statement'!J$15 -> -6842.3 | D21: ='Cash Flow Statement'!K$15 -> -9087.7 | E21: =AVERAGE((B21/B4),(C21/C4),(D21/D4))*E4 -> -7322.1876 | F21: =AVERAGE((B21/B4),(C21/C4),(D21/D4))*F4 -> -7357.3341 | G21: =AVERAGE((B21/B4),(C21/C4),(D21/D4))*G4 -> -7392.6493 | H21: =AVERAGE((B21/B4),(C21/C4),(D21/D4))*H4 -> -7428.134
A22: Change in NWC | B22: =(('Balance Sheet'!$I$10-'Balance Sheet'!$I$5) - ('Balance Sheet'!$I$24-'Balance Sheet'!$I$20-'Balance Sheet'!$I$21))-(('Balance Sheet'!$H$10-'Balance Sheet'!$H$5) - ('Balance Sheet'!$H$24-'Balance Sheet'!$H$20-'Balance Sheet'!$H$21)) -> -2971.7 | C22: =(('Balance Sheet'!$J$10-'Balance Sheet'!$J$5) - ('Balance Sheet'!$J$24-'Balance Sheet'!$J$20-'Balance Sheet'!$J$21))-(('Balance Sheet'!$I$10-'Balance Sheet'!$I$5) - ('Balance Sheet'!$I$24-'Balance Sheet'!$I$20-'Balance Sheet'!$I$21)) -> -1644.1 | D22: =(('Balance Sheet'!$K$10-'Balance Sheet'!$K$5) - ('Balance Sheet'!$K$24-'Balance Sheet'!$K$20-'Balance Sheet'!$K$21))-(('Balance Sheet'!$J$10-'Balance Sheet'!$J$5) - ('Balance Sheet'!$J$24-'Balance Sheet'!$J$20-'Balance Sheet'!$J$21)) -> 466.3 | E22: =AVERAGE(B22/(B4-'Income Statement'!H3),C22/(C4-$B4), D22/(D4-C4))*(E4-D4) -> -32.452053 | F22: =AVERAGE(B22/($B4-'Income Statement'!H3),$C22/($C4-$B4), $D22/($D4-$C4))*(F4-E4) -> -32.607822 | G22: =AVERAGE(B22/($B4-'Income Statement'!H3),$C22/($C4-$B4), $D22/($D4-$C4))*(G4-F4) -> -32.76434 | H22: =AVERAGE($C22/($C4-$B4), $D22/($D4-$C4))*(H4-G4) -> -10.572676
A23: Interest (Net of Tax) | B23: =-B10*(1-B14) -> -243.59588 | C23: =-C10*(1-C14) -> 132.19896 | D23: =-D10*(1-D14) -> -341.73386 | E23: =-E10*(1-E14) -> -202.60765 | F23: =-F10*(1-F14) -> -207.00897 | G23: =-G10*(1-G14) -> -209.72525 | H23: =-H10*(1-H14) -> -212.46283
A24: FCFF | B24: =(B6*(1-B14))+B20+B21-B22 -> 12490.804 | C24: =(C6*(1-C14))+C20+C21-C22 -> 12356.799 | D24: =(D6*(1-D14))+D20+D21-D22 -> 8904.6661 | E24: =(E6*(1-E14))+E20+E21-E22 -> 13306.42 | F24: =(F6*(1-F14))+F20+F21-F22 -> 13964.54 | G24: =(G6*(1-G14))+G20+G21-G22 -> 14176.17 | H24: =(H6*(1-H14))+H20+H21-H22 -> 14280.247
A25: FCFF per Share | B25: =B24/B31 -> 2.7789455 | C25: =C24/C31 -> 2.7687204 | D25: =D24/D31 -> 2.0020834 | E25: =E24/E31 -> 2.9954571 | F25: =F24/F31 -> 3.1602048 | G25: =G24/G31 -> 3.2250335 | H25: =H24/H31 -> 3.2658614
A26: OCF | B26: =B15+B20-B22 -> 16478.5 | C26: =C15+C20-C22 -> 19066.9 | D26: =D15+D20-D22 -> 18334.1 | E26: =E15+E20-E22 -> 20831.215 | F26: =F15+F20-F22 -> 21528.883 | G26: =G15+G20-G22 -> 21778.544 | H26: =H15+H20-H22 -> 21920.844
A27: OCF per Share | B27: =B26/B31 -> 3.6661253 | C27: =C26/C31 -> 4.272216 | D27: =D26/D31 -> 4.122153 | E27: =E26/E31 -> 4.6893915 | F27: =F26/F31 -> 4.8720316 | G27: =G26/G31 -> 4.9545495 | H27: =H26/H31 -> 5.0132493
A28: Net Borrowing | B28: ='Cash Flow Statement'!I$25 + 'Cash Flow Statement'!I$28 -> -212.8 | C28: ='Cash Flow Statement'!J$25 + 'Cash Flow Statement'!J$28 -> 10598.6 | D28: ='Cash Flow Statement'!K$25 + 'Cash Flow Statement'!K$28 -> 3738.9 | E28: =AVERAGE((B28/B4),(C28/C4),(D28/D4))*E4 -> 5088.5725 | F28: =AVERAGE((B28/B4),(C28/C4),(D28/D4))*F4 -> 5112.9976 | G28: =AVERAGE((B28/B4),(C28/C4),(D28/D4))*G4 -> 5137.54 | H28: =AVERAGE((B28/B4),(C28/C4),(D28/D4))*H4 -> 5162.2002
A29: FCFE | B29: =B15+B20+B21-B22+B28 -> 12521.6 | C29: =C15+C20+C21-C22+C28 -> 22823.2 | D29: =D15+D20+D21-D22+D28 -> 12985.3 | E29: =E15+E20+E21-E22+E28 -> 18597.6 | F29: =F15+F20+F21-F22+F28 -> 19284.546 | G29: =G15+G20+G21-G22+G28 -> 19523.435 | H29: =H15+H20+H21-H22+H28 -> 19654.91
A30: FCFE per Share | B30: =B29/B31 -> 2.7857969 | C30: =C29/C31 -> 5.1138696 | D30: =D29/D31 -> 2.9195539 | E30: =E29/E31 -> 4.1865742 | F30: =F29/F31 -> 4.3641336 | G30: =G29/G31 -> 4.4415193 | H30: =H29/H31 -> 4.4950352
A31: Diluted Shares Outstanding | B31: ='Income Statement'!$I$26 -> 4494.8 | C31: ='Income Statement'!$J$26 -> 4463 | D31: ='Income Statement'!$K$26 -> 4447.7 | E31: ='Income Statement'!$L$26 -> 4442.2 | F31: =E31+(E31*F32) -> 4418.8717 | G31: =F31+(F31*G32) -> 4395.666 | H31: =G31+(G31*H32) -> 4372.582
A32: % Change YoY | B32: =(B31/'Income Statement'!$H$26)-1 -> -0.01095806 | C32: =(C31/B31)-1 -> -0.007074842 | D32: =(D31/C31)-1 -> -0.0034281873 | E32: =(E31/D31)-1 -> -0.0012365942 | F32: =MEDIAN(B32:E32) -> -0.0052515147 | G32: =MEDIAN(B32:E32) -> -0.0052515147 | H32: =MEDIAN(B32:E32) -> -0.0052515147
A33: EPS Normalized | B33: =B15/B31 -> 2.7011435 | C33: =C15/C31 -> 3.282747 | D33: =D15/D31 -> 3.4801583 | E33: =E15/E31 -> 4.0572481 | F33: =F15/F31 -> 4.1672697 | G33: =G15/G31 -> 4.2442394 | H33: =H15/H31 -> 4.322339
A34: % Change YoY | B34: =(B33/'Income Statement'!$H$24)-1 -> 0.56497308 | C34: =(C33/B33)-1 -> 0.2153175 | D34: =(D33/C33)-1 -> 0.060135993 | E34: =(E33/D33)-1 -> 0.16582287 | F34: =(F33/E33)-1 -> 0.027117298 | G34: =(G33/F33)-1 -> 0.018470043 | H34: =(H33/G33)-1 -> 0.018401331
A35: Dividends Per Share | B35: =Dividendos!H$4 -> 1.3638 | C35: =Dividendos!I$4 -> 1.6539 | D35: =Dividendos!J$4 -> 1.768 | E35: =Dividendos!K$4 -> 1.8266 | F35: =E35+F36 -> 1.9552514 | G35: =F35+G36 -> 2.0839027 | H35: =G35+H36 -> 2.2125541
A36: % Change YoY | B36: =(B35/ Dividendos!G4)-1 -> 0.55756053 | C36: =(C35/ Dividendos!H4)-1 -> 0.21271447 | D36: =(D35/ Dividendos!I4)-1 -> 0.068988452 | E36: =(E35/ Dividendos!J4)-1 -> 0.033144796 | F36: =IFERROR((Dividendos!J4/Dividendos!B4)^(1/9)-1,"0") -> 0.12865136 | G36: =IFERROR((Dividendos!J4/Dividendos!B4)^(1/9)-1,"0") -> 0.12865136 | H36: =IFERROR((Dividendos!J4/Dividendos!B4)^(1/9)-1,"0") -> 0.12865136
A37: % Payout Ratio | B37: =B35/B33 -> 0.50489727 | C37: =C35/C33 -> 0.50381585 | D37: =D35/D33 -> 0.50802287 | E37: =E35/E33 -> 0.45020663 | F37: =F35/F33 -> 0.46919242 | G37: =G35/G33 -> 0.49099557 | H37: =H35/H33 -> 0.51188814
A41: Base
A42: Operating Data | B42: ='Income Statement'!I$2 -> Dec '23 | C42: ='Income Statement'!J$2 -> Dec '24 | D42: ='Income Statement'!K$2 -> Dec '25 | E42: FY+1 (Estimate) | F42: FY+2 (Estimate) | G42: FY+3 (Estimate) | H42: FY+4 (Estimate)
A43: Revenues | B43: ='Income Statement'!$I$3 -> 33697.5 | C43: ='Income Statement'!$J$3 -> 42130.2 | D43: ='Income Statement'!$K$3 -> 46702.4 | E43: =D43+(D43*E44) -> 44834.304 | F43: =E43+(E43*F44) -> 46403.505 | G43: =F43+(F43*G44) -> 48027.627 | H43: =G43+(G43*H44) -> 49708.594 | J43: Cambiar crecimiento
A44: % Change YoY | B44: =('Income Statement'!$I$3-'Income Statement'!$H$3)/'Income Statement'!$H$3 -> 0.34839621 | C44: =(C43-B43)/B43 -> 0.25024705 | D44: =(D43-C43)/C43 -> 0.10852548 | E44: ='Valuation output'!C4 -> -0.04 | F44: ='Valuation output'!D4 -> 0.035 | G44: ='Valuation output'!E4 -> 0.035 | H44: ='Valuation output'!F4 -> 0.035
A45: EBIT | B45: ='Income Statement'!$I$12 -> 14881.9 | C45: ='Income Statement'!$J$12 -> 18618.8 | D45: ='Income Statement'!$K$12 -> 19290.3 | E45: =E43*E47 -> 21295.754 | F45: =F43*F47 -> 21577.294 | G45: =G43*G47 -> 22092.477 | H45: =H43*H47 -> 22617.291
A46: % Change YoY | B46: =(B45-'Income Statement'!$H$12)/'Income Statement'!$H$12 -> 0.40859055 | C46: =(C45-B45)/B45 -> 0.25110369 | D46: =(D45-C45)/C45 -> 0.036065697 | E46: =(E45-D45)/D45 -> 0.10396179 | F46: =(F45-E45)/E45 -> 0.013220478 | G46: =(G45-F45)/F45 -> 0.02387616 | H46: =(H45-G45)/G45 -> 0.023755305 | J46: Cambiar EBIT margen
A47: % Margin | B47: =B45/B43 -> 0.44163217 | C47: =C45/C43 -> 0.44193476 | D47: =D45/D43 -> 0.4130473 | E47: =IFERROR(IF(J47<>"",J47,'Valuation output'!C6),"") -> 0.47498795 | F47: =IFERROR(IF(K47<>"",K47,'Valuation output'!D6),"") -> 0.46499277 | G47: =IFERROR(IF(L47<>"",L47,'Valuation output'!E6),"") -> 0.45999518 | H47: =IFERROR(IF(M47<>"",M47,'Valuation output'!F6),"") -> 0.45499759
A48: % Incremental Margin | B48: =((B45- 'Income Statement'!$H$12) / (B43 - 'Income Statement'!$H$3)) -> 0.49580208 | C48: =((C45-B45) / (C43 - B43)) -> 0.44314395 | D48: =((D45-C45) / (D43 - C43)) -> 0.14686584 | E48: =((E45-D45) / (E43 - D43)) -> -1.0735284 | F48: =((F45-E45) / (F43 - E43)) -> 0.17941622 | G48: =((G45-F45) / (G43 - F43)) -> 0.3172069 | H48: =((H45-G45) / (H43 - G43)) -> 0.31220931
A49: Interest / Other | B49: ='Income Statement'!I$18 -> 304.7 | C49: ='Income Statement'!J$18 -> -166.5 | D49: ='Income Statement'!K$18 -> 435.5 | E49: =E45*E50 -> 242.11906 | F49: =F45*F50 -> 245.31999 | G49: =G45*G50 -> 251.17729 | H49: =H45*H50 -> 257.14408
A50: % of EBIT | B50: =B49/B45 -> 0.020474536 | C50: =C49/C45 -> -0.0089425742 | D50: =D49/D45 -> 0.022576113 | E50: =AVERAGE(B50:D50) -> 0.011369358 | F50: =E50 -> 0.011369358 | G50: =F50 -> 0.011369358 | H50: =G50 -> 0.011369358
A51: EBT | B51: =B45+B49 -> 15186.6 | C51: =C45+C49 -> 18452.3 | D51: =D45+D49 -> 19725.8 | E51: =E45+E49 -> 21537.873 | F51: =F45+F49 -> 21822.614 | G51: =G45+G49 -> 22343.654 | H51: =H45+H49 -> 22874.435
A52: Taxes / Other | B52: ='Income Statement'!I$20 -> 3045.5 | C52: ='Income Statement'!J$20 -> 3801.4 | D52: ='Income Statement'!K$20 -> 4247.1 | E52: =E51*E53 -> 4318.3436 | F52: =F51*F53 -> 4375.4341 | G52: =G51*G53 -> 4479.9027 | H52: =H51*H53 -> 4586.3241 | J52: Cambiar Tax rate
A53: % of EBT | B53: =B52/B51 -> 0.20053863 | C53: =C52/C51 -> 0.20601226 | D53: =D52/D51 -> 0.21530686 | E53: =IFERROR(IF(J53<>"",J53,'Valuation output'!C8),"") -> 0.2005 | F53: =IFERROR(IF(K53<>"",K53,'Valuation output'!D8),"") -> 0.2005 | G53: =IFERROR(IF(L53<>"",L53,'Valuation output'!E8),"") -> 0.2005 | H53: =IFERROR(IF(M53<>"",M53,'Valuation output'!F8),"") -> 0.2005
A54: Net Income Normalized | B54: =B51-B52 -> 12141.1 | C54: =C51-C52 -> 14650.9 | D54: =D51-D52 -> 15478.7 | E54: =E51-E52 -> 17219.53 | F54: =F51-F52 -> 17447.18 | G54: =G51-G52 -> 17863.752 | H54: =H51-H52 -> 18288.111
A55: % Change YoY | B55: =(B54/'Income Statement'!$H$21)-1 -> 0.54827397 | C55: =(C54/B54)-1 -> 0.20671933 | D55: =(D54/C54)-1 -> 0.056501648 | E55: =(E54/D54)-1 -> 0.11246613 | F55: =(F54/E54)-1 -> 0.013220478 | G55: =(G54/F54)-1 -> 0.02387616 | H55: =(H54/G54)-1 -> 0.023755305
A56: % Margin | B56: =B54/B43 -> 0.36029676 | C56: =C54/C43 -> 0.34775292 | D56: =D54/D43 -> 0.33143265 | E56: =E54/E43 -> 0.38407041 | F56: =F54/F43 -> 0.37598841 | G56: =G54/G43 -> 0.37194741 | H56: =H54/H43 -> 0.36790641
A57: EBITDA | B57: =B45+'Cash Flow Statement'!$I$4 -> 16247.6 | C57: =C45+'Cash Flow Statement'!$J$4 -> 21390.7 | D57: =D45+'Cash Flow Statement'!$K$4 -> 22612 | E57: =$E$45+$E$59 -> 23947.654 | F57: =F45+F59 -> 24610.032 | G57: =G45+G59 -> 25224.351 | H57: =H45+H59 -> 25760.772 | J57: Cambiar EBITDA margen
A58: % Margin | B58: =B57/B43 -> 0.4821604 | C58: =C57/C43 -> 0.50772842 | D58: =D57/D43 -> 0.48417212 | E58: =E57/E43 -> 0.53413685 | F58: =F57/F43 -> 0.53034856 | G58: =G57/G43 -> 0.52520502 | H58: =H57/H43 -> 0.51823577
A59: D&A | B59: =B57-B45 -> 1365.7 | C59: =C57-C45 -> 2771.9 | D59: =D57-D45 -> 3321.7 | E59: =AVERAGE((B59/B43),(C59/C43),(D59/D43))*E43 -> 2651.8999 | F59: =AVERAGE((C59/C43),(D59/D43),(E59/E43))*F43 -> 3032.738 | G59: =AVERAGE((D59/D43),(E59/E43),(F59/F43))*G43 -> 3131.874 | H59: =AVERAGE((E59/E43),(F59/F43),(G59/G43))*H43 -> 3143.4811
A60: CapEx | B60: ='Cash Flow Statement'!I$15 -> -3744.1 | C60: ='Cash Flow Statement'!J$15 -> -6842.3 | D60: ='Cash Flow Statement'!K$15 -> -9087.7 | E60: =AVERAGE((B60/B43),(C60/C43),(D60/D43))*E43 -> -6995.7206 | F60: =AVERAGE((B60/B43),(C60/C43),(D60/D43))*F43 -> -7240.5709 | G60: =AVERAGE((B60/B43),(C60/C43),(D60/D43))*G43 -> -7493.9909 | H60: =AVERAGE((B60/B43),(C60/C43),(D60/D43))*H43 -> -7756.2805
A61: Change in NWC | B61: =(('Balance Sheet'!$I$10-'Balance Sheet'!$I$5) - ('Balance Sheet'!$I$24-'Balance Sheet'!$I$20-'Balance Sheet'!$I$21))-(('Balance Sheet'!$H$10-'Balance Sheet'!$H$5) - ('Balance Sheet'!$H$24-'Balance Sheet'!$H$20-'Balance Sheet'!$H$21)) -> -2971.7 | C61: =(('Balance Sheet'!$J$10-'Balance Sheet'!$J$5) - ('Balance Sheet'!$J$24-'Balance Sheet'!$J$20-'Balance Sheet'!$J$21))-(('Balance Sheet'!$I$10-'Balance Sheet'!$I$5) - ('Balance Sheet'!$I$24-'Balance Sheet'!$I$20-'Balance Sheet'!$I$21)) -> -1644.1 | D61: =(('Balance Sheet'!$K$10-'Balance Sheet'!$K$5) - ('Balance Sheet'!$K$24-'Balance Sheet'!$K$20-'Balance Sheet'!$K$21))-(('Balance Sheet'!$J$10-'Balance Sheet'!$J$5) - ('Balance Sheet'!$J$24-'Balance Sheet'!$J$20-'Balance Sheet'!$J$21)) -> 466.3 | E61: =AVERAGE(B61/(B43-'Income Statement'!H42),C61/(C43-$B43), D61/(D43-C43))*(E43-D43) -> 112.8136 | F61: =AVERAGE(B61/(B43-'Income Statement'!H42),C61/(C43-$B43), D61/(D43-C43))*(F43-E43) -> -94.763424 | G61: =AVERAGE(B61/(B43-'Income Statement'!H42),C61/(C43-$B43), D61/(D43-C43))*(G43-F43) -> -98.080143 | H61: =AVERAGE(B61/(B43-'Income Statement'!H42),C61/(C43-$B43), D61/(D43-C43))*(H43-G43) -> -101.51295
A62: Interest (Net of Tax) | B62: =-B49*(1-B53) -> -243.59588 | C62: =-C49*(1-C53) -> 132.19896 | D62: =-D49*(1-D53) -> -341.73386 | E62: =-E49*(1-E53) -> -193.57419 | F62: =-F49*(1-F53) -> -196.13333 | G62: =-G49*(1-G53) -> -200.81624 | H62: =-H49*(1-H53) -> -205.5867
A63: FCFF | B63: =(B45*(1-B53))+B59+B60-B61 -> 12490.804 | C63: =(C45*(1-C53))+C59+C60-C61 -> 12356.799 | D63: =(D45*(1-D53))+D59+D60-D61 -> 8904.6661 | E63: =(E45*(1-E53))+E59+E60-E61 -> 12569.321 | F63: =(F45*(1-F53))+F59+F60-F61 -> 13137.977 | G63: =(G45*(1-G53))+G59+G60-G61 -> 13398.899 | H63: =(H45*(1-H53))+H59+H60-H61 -> 13571.237
A64: FCFF per Share | B64: =B63/B70 -> 2.7789455 | C64: =C63/C70 -> 2.7687204 | D64: =D63/D70 -> 2.0020834 | E64: =E63/E70 -> 2.8295262 | F64: =F63/F70 -> 2.973152 | G64: =G63/G70 -> 3.0482068 | H64: =H63/H70 -> 3.1037124
A65: OCF | B65: =B54+B59-B61 -> 16478.5 | C65: =C54+C59-C61 -> 19066.9 | D65: =D54+D59-D61 -> 18334.1 | E65: =E54+E59-E61 -> 19758.616 | F65: =F54+F59-F61 -> 20574.681 | G65: =G54+G59-G61 -> 21093.706 | H65: =H54+H59-H61 -> 21533.105
A66: OCF per Share | B66: =B65/B70 -> 3.6661253 | C66: =C65/C70 -> 4.272216 | D66: =D65/D70 -> 4.122153 | E66: =E65/E70 -> 4.4479348 | F66: =F65/F70 -> 4.6560938 | G66: =G65/G70 -> 4.7987509 | H66: =H65/H70 -> 4.9245741
A67: Net Borrowing | B67: ='Cash Flow Statement'!I$25 + 'Cash Flow Statement'!I$28 -> -212.8 | C67: ='Cash Flow Statement'!J$25 + 'Cash Flow Statement'!J$28 -> 10598.6 | D67: ='Cash Flow Statement'!K$25 + 'Cash Flow Statement'!K$28 -> 3738.9 | E67: =AVERAGE((B67/B43),(C67/C43),(D67/D43))*E43 -> 4861.6935 | F67: =AVERAGE((B67/B43),(C67/C43),(D67/D43))*F43 -> 5031.8527 | G67: =AVERAGE((B67/B43),(C67/C43),(D67/D43))*G43 -> 5207.9676 | H67: =AVERAGE((B67/B43),(C67/C43),(D67/D43))*H43 -> 5390.2464
A68: FCFE | B68: =B54+B59+B60-B61+B67 -> 12521.6 | C68: =C54+C59+C60-C61+C67 -> 22823.2 | D68: =D54+D59+D60-D61+D67 -> 12985.3 | E68: =E54+E59+E60-E61+E67 -> 17624.589 | F68: =F54+F59+F60-F61+F67 -> 18365.963 | G68: =G54+G59+G60-G61+G67 -> 18807.682 | H68: =H54+H59+H60-H61+H67 -> 19167.07
A69: FCFE per Share | B69: =B68/B70 -> 2.7857969 | C69: =C68/C70 -> 5.1138696 | D69: =D68/D70 -> 2.9195539 | E69: =E68/E70 -> 3.9675361 | F69: =F68/F70 -> 4.1562563 | G69: =G68/G70 -> 4.2786878 | H69: =H68/H70 -> 4.3834673
A70: Diluted Shares Outstanding | B70: ='Income Statement'!$I$26 -> 4494.8 | C70: ='Income Statement'!$J$26 -> 4463 | D70: ='Income Statement'!$K$26 -> 4447.7 | E70: ='Income Statement'!L26 -> 4442.2 | F70: =E70+(E70*F71) -> 4418.8717 | G70: =F70+(F70*G71) -> 4395.666 | H70: =G70+(G70*H71) -> 4372.582
A71: % Change YoY | B71: =(B70/'Income Statement'!$H$26)-1 -> -0.01095806 | C71: =(C70/B70)-1 -> -0.007074842 | D71: =(D70/C70)-1 -> -0.0034281873 | E71: =(E70/ 'Income Statement'!K26)-1 -> -0.0012365942 | F71: =MEDIAN(B71:E71) -> -0.0052515147 | G71: =MEDIAN(B71:E71) -> -0.0052515147 | H71: =MEDIAN(B71:E71) -> -0.0052515147
A72: EPS Normalized | B72: =B54/B70 -> 2.7011435 | C72: =C54/C70 -> 3.282747 | D72: =D54/D70 -> 3.4801583 | E72: =E54/E70 -> 3.8763517 | F72: =F54/F70 -> 3.9483337 | G72: =G54/G70 -> 4.0639466 | H72: =H54/H70 -> 4.1824511
A73: % Change YoY | B73: =(B72/'Income Statement'!$H$24)-1 -> 0.56497308 | C73: =(C72/B72)-1 -> 0.2153175 | D73: =(D72/C72)-1 -> 0.060135993 | E73: =(E72/D72)-1 -> 0.11384351 | F73: =(F72/E72)-1 -> 0.018569511 | G73: =(G72/F72)-1 -> 0.029281446 | H73: =(H72/G72)-1 -> 0.029159954
A74: Dividends Per Share | B74: =Dividendos!H$4 -> 1.3638 | C74: =Dividendos!I$4 -> 1.6539 | D74: =Dividendos!J$4 -> 1.768 | E74: =Dividendos!K$4 -> 1.8266 | F74: =E74+F75 -> 1.9552514 | G74: =F74+G75 -> 2.0839027 | H74: =G74+H75 -> 2.2125541
A75: % Change YoY | B75: =(B74/ Dividendos!G4)-1 -> 0.55756053 | C75: =(C74/ Dividendos!H4)-1 -> 0.21271447 | D75: =(D74/ Dividendos!I4)-1 -> 0.068988452 | E75: =(E74/ Dividendos!J4)-1 -> 0.033144796 | F75: =IFERROR((Dividendos!J4/Dividendos!B4)^(1/9)-1,"0") -> 0.12865136 | G75: =IFERROR((Dividendos!J4/Dividendos!B4)^(1/9)-1,"0") -> 0.12865136 | H75: =IFERROR((Dividendos!J4/Dividendos!B4)^(1/9)-1,"0") -> 0.12865136
A76: % Payout Ratio | B76: =B74/B72 -> 0.50489727 | C76: =C74/C72 -> 0.50381585 | D76: =D74/D72 -> 0.50802287 | E76: =E74/E72 -> 0.47121627 | F76: =F74/F72 -> 0.49520925 | G76: =G74/G72 -> 0.51277808 | H76: =H74/H72 -> 0.52900896
A81: Optimista
A82: Operating Data | B82: ='Income Statement'!I$2 -> Dec '23 | C82: ='Income Statement'!J$2 -> Dec '24 | D82: ='Income Statement'!K$2 -> Dec '25 | E82: FY+1 (Estimate) | F82: FY+2 (Estimate) | G82: FY+3 (Estimate) | H82: FY+4 (Estimate)
A83: Revenues | B83: ='Income Statement'!$I$3 -> 33697.5 | C83: ='Income Statement'!$J$3 -> 42130.2 | D83: ='Income Statement'!$K$3 -> 46702.4 | E83: =D83+(D83*E84) -> 44273.875 | F83: =E83+(E83*F84) -> 41971.634 | G83: =F83+(F83*G84) -> 39789.109 | H83: =G83+(G83*H84) -> 37720.075 | J83: Cambiar crecimiento
A84: % Change YoY | B84: =('Income Statement'!$I$3-'Income Statement'!$H$3)/'Income Statement'!$H$3 -> 0.34839621 | C84: =(C83-B83)/B83 -> 0.25024705 | D84: =(D83-C83)/C83 -> 0.10852548 | E84: ='Valuation output'!C106 -> -0.052 | F84: ='Valuation output'!D106 -> -0.052 | G84: ='Valuation output'!E106 -> -0.052 | H84: ='Valuation output'!F106 -> -0.052
A85: EBIT | B85: ='Income Statement'!$I$12 -> 14881.9 | C85: ='Income Statement'!$J$12 -> 18618.8 | D85: ='Income Statement'!$K$12 -> 19290.3 | E85: =E83*E87 -> 21029.557 | F85: =F83*F87 -> 20355.939 | G85: =G83*G87 -> 19496.471 | H85: =H83*H87 -> 18671.346
A86: % Change YoY | B86: =(B85-'Income Statement'!$H$12)/'Income Statement'!$H$12 -> 0.40859055 | C86: =(C85-B85)/B85 -> 0.25110369 | D86: =(D85-C85)/C85 -> 0.036065697 | E86: =(E85-D85)/D85 -> 0.090162265 | F86: =(F85-E85)/E85 -> -0.032031977 | G86: =(G85-F85)/F85 -> -0.042221947 | H86: =(H85-G85)/G85 -> -0.042321772 | J86: Cambiar EBIT margen
A87: % Margin | B87: =B85/B83 -> 0.44163217 | C87: =C85/C83 -> 0.44193476 | D87: =D85/D83 -> 0.4130473 | E87: =IFERROR(IF(J87<>"",J87,'Valuation output'!C108),"") -> 0.47498795 | F87: =IFERROR(IF(K87<>"",K87,'Valuation output'!D108),"") -> 0.48499277 | G87: =IFERROR(IF(L87<>"",L87,'Valuation output'!E108),"") -> 0.48999518 | H87: =IFERROR(IF(M87<>"",M87,'Valuation output'!F108),"") -> 0.49499759
A88: % Incremental Margin | B88: =((B85- 'Income Statement'!$H$12) / (B83 - 'Income Statement'!$H$3)) -> 0.49580208 | C88: =((C85-B85) / (C83 - B83)) -> 0.44314395 | D88: =((D85-C85) / (D83 - C83)) -> 0.14686584 | E88: =((E85-D85) / (E83 - D83)) -> -0.71617845 | F88: =((F85-E85) / (F83 - E83)) -> 0.29259237 | G88: =((G85-F85) / (G83 - F83)) -> 0.39379498 | H88: =((H85-G85) / (H83 - G83)) -> 0.39879739
A89: Interest / Other | B89: ='Income Statement'!I$18 -> 304.7 | C89: ='Income Statement'!J$18 -> -166.5 | D89: ='Income Statement'!K$18 -> 435.5 | E89: =E85*E90 -> 239.09257 | F89: =F85*F90 -> 231.43397 | G89: =G85*G90 -> 221.66237 | H89: =H85*H90 -> 212.28123
A90: % of EBIT | B90: =B89/B85 -> 0.020474536 | C90: =C89/C85 -> -0.0089425742 | D90: =D89/D85 -> 0.022576113 | E90: =AVERAGE(B90:D90) -> 0.011369358 | F90: =E90 -> 0.011369358 | G90: =F90 -> 0.011369358 | H90: =G90 -> 0.011369358
A91: EBT | B91: =B85+B89 -> 15186.6 | C91: =C85+C89 -> 18452.3 | D91: =D85+D89 -> 19725.8 | E91: =E85+E89 -> 21268.65 | F91: =F85+F89 -> 20587.373 | G91: =G85+G89 -> 19718.134 | H91: =H85+H89 -> 18883.627
A92: Taxes / Other | B92: ='Income Statement'!I$20 -> 3045.5 | C92: ='Income Statement'!J$20 -> 3801.4 | D92: ='Income Statement'!K$20 -> 4247.1 | E92: =E91*E93 -> 4264.3643 | F92: =F91*F93 -> 4127.7682 | G92: =G91*G93 -> 3953.4858 | H92: =H91*H93 -> 3786.1673 | J92: Cambiar Tax rate
A93: % of EBT | B93: =B92/B91 -> 0.20053863 | C93: =C92/C91 -> 0.20601226 | D93: =D92/D91 -> 0.21530686 | E93: =IFERROR(IF(J93<>"",J93,'Valuation output'!C110),"") -> 0.2005 | F93: =IFERROR(IF(K93<>"",K93,'Valuation output'!D110),"") -> 0.2005 | G93: =IFERROR(IF(L93<>"",L93,'Valuation output'!E110),"") -> 0.2005 | H93: =IFERROR(IF(M93<>"",M93,'Valuation output'!F110),"") -> 0.2005
A94: Net Income Normalized | B94: =B91-B92 -> 12141.1 | C94: =C91-C92 -> 14650.9 | D94: =D91-D92 -> 15478.7 | E94: =E91-E92 -> 17004.285 | F94: =F91-F92 -> 16459.605 | G94: =G91-G92 -> 15764.648 | H94: =H91-H92 -> 15097.46
A95: % Change YoY | B95: =(B94/'Income Statement'!$H$21)-1 -> 0.54827397 | C95: =(C94/B94)-1 -> 0.20671933 | D95: =(D94/C94)-1 -> 0.056501648 | E95: =(E94/D94)-1 -> 0.098560308 | F95: =(F94/E94)-1 -> -0.032031977 | G95: =(G94/F94)-1 -> -0.042221947 | H95: =(H94/G94)-1 -> -0.042321772
A96: % Margin | B96: =B94/B83 -> 0.36029676 | C96: =C94/C83 -> 0.34775292 | D96: =D94/D83 -> 0.33143265 | E96: =E94/E83 -> 0.38407041 | F96: =F94/F83 -> 0.39216021 | G96: =G94/G83 -> 0.39620511 | H96: =H94/H83 -> 0.40025
A97: EBITDA | B97: =B85+'Cash Flow Statement'!$I$4 -> 16247.6 | C97: =C85+'Cash Flow Statement'!$J$4 -> 21390.7 | D97: =D85+'Cash Flow Statement'!$K$4 -> 22612 | E97: =E85+E99 -> 23648.308 | F97: =F85+F99 -> 23099.028 | G97: =G85+G99 -> 22091.113 | H97: =H85+H99 -> 21056.695 | J97: Cambiar EBITDA margen
A98: % Margin | B98: =B97/B83 -> 0.4821604 | C98: =C97/C83 -> 0.50772842 | D98: =D97/D83 -> 0.48417212 | E98: =E97/E83 -> 0.53413685 | F98: =F97/F83 -> 0.55034856 | G98: =G97/G83 -> 0.55520502 | H98: =H97/H83 -> 0.55823577
A99: D&A | B99: =B97-B85 -> 1365.7 | C99: =C97-C85 -> 2771.9 | D99: =D97-D85 -> 3321.7 | E99: =AVERAGE((B99/B83),(C99/C83),(D99/D83))*E83 -> 2618.7512 | F99: =AVERAGE((C99/C83),(D99/D83),(E99/E83))*F83 -> 2743.0895 | G99: =AVERAGE((D99/D83),(E99/E83),(F99/F83))*G83 -> 2594.6415 | H99: =AVERAGE((E99/E83),(F99/F83),(G99/G83))*H83 -> 2385.3489
A100: CapEx | B100: ='Cash Flow Statement'!I$15 -> -3744.1 | C100: ='Cash Flow Statement'!J$15 -> -6842.3 | D100: ='Cash Flow Statement'!K$15 -> -9087.7 | E100: =AVERAGE((B100/B83),(C100/C83),(D100/D83))*E83 -> -6908.2741 | F100: =AVERAGE((B100/B83),(C100/C83),(D100/D83))*F83 -> -6549.0439 | G100: =AVERAGE((B100/B83),(C100/C83),(D100/D83))*G83 -> -6208.4936 | H100: =AVERAGE((B100/B83),(C100/C83),(D100/D83))*H83 -> -5885.6519
A101: Change in NWC | B101: =(('Balance Sheet'!$I$10-'Balance Sheet'!$I$5) - ('Balance Sheet'!$I$24-'Balance Sheet'!$I$20-'Balance Sheet'!$I$21))-(('Balance Sheet'!$H$10-'Balance Sheet'!$H$5) - ('Balance Sheet'!$H$24-'Balance Sheet'!$H$20-'Balance Sheet'!$H$21)) -> -2971.7 | C101: =(('Balance Sheet'!$J$10-'Balance Sheet'!$J$5) - ('Balance Sheet'!$J$24-'Balance Sheet'!$J$20-'Balance Sheet'!$J$21))-(('Balance Sheet'!$I$10-'Balance Sheet'!$I$5) - ('Balance Sheet'!$I$24-'Balance Sheet'!$I$20-'Balance Sheet'!$I$21)) -> -1644.1 | D101: =(('Balance Sheet'!$K$10-'Balance Sheet'!$K$5) - ('Balance Sheet'!$K$24-'Balance Sheet'!$K$20-'Balance Sheet'!$K$21))-(('Balance Sheet'!$J$10-'Balance Sheet'!$J$5) - ('Balance Sheet'!$J$24-'Balance Sheet'!$J$20-'Balance Sheet'!$J$21)) -> 466.3 | E101: =AVERAGE(B101/(B83-'Income Statement'!H82),C101/(C83-$B83), D101/(D83-C83))*(E83-D83) -> 146.65768 | F101: =AVERAGE(B101/(B83-'Income Statement'!H82),C101/(C83-$B83), D101/(D83-C83))*(F83-E83) -> 139.03148 | G101: =AVERAGE(B101/(B83-'Income Statement'!H82),C101/(C83-$B83), D101/(D83-C83))*(G83-F83) -> 131.80184 | H101: =AVERAGE(B101/(B83-'Income Statement'!H82),C101/(C83-$B83), D101/(D83-C83))*(H83-G83) -> 124.94815
A102: Interest (Net of Tax) | B102: =-B89*(1-B93) -> -243.59588 | C102: =-C89*(1-C93) -> 132.19896 | D102: =-D89*(1-D93) -> -341.73386 | E102: =-E89*(1-E93) -> -191.15451 | F102: =-F89*(1-F93) -> -185.03146 | G102: =-G89*(1-G93) -> -177.21907 | H102: =-H89*(1-H93) -> -169.71884
A103: FCFF | B103: =(B85*(1-B93))+B99+B100-B101 -> 12490.804 | C103: =(C85*(1-C93))+C99+C100-C101 -> 12356.799 | D103: =(D85*(1-D93))+D99+D100-D101 -> 8904.6661 | E103: =(E85*(1-E93))+E99+E100-E101 -> 12376.95 | F103: =(F85*(1-F93))+F99+F100-F101 -> 12329.587 | G103: =(G85*(1-G93))+G99+G100-G101 -> 11841.775 | H103: =(H85*(1-H93))+H99+H100-H101 -> 11302.49
A104: FCFF per Share | B104: =B103/B110 -> 2.7789455 | C104: =C103/C110 -> 2.7687204 | D104: =D103/D110 -> 2.0020834 | E104: =E103/E110 -> 2.7862209 | F104: =F103/F110 -> 2.7902116 | G104: =G103/G110 -> 2.6939661 | H104: =H103/H110 -> 2.5848549
A105: OCF | B105: =B94+B99-B101 -> 16478.5 | C105: =C94+C99-C101 -> 19066.9 | D105: =D94+D99-D101 -> 18334.1 | E105: =E94+E99-E101 -> 19476.379 | F105: =F94+F99-F101 -> 19063.663 | G105: =G94+G99-G101 -> 18227.488 | H105: =H94+H99-H101 -> 17357.861
A106: OCF per Share | B106: =B105/B110 -> 3.6661253 | C106: =C105/C110 -> 4.272216 | D106: =D105/D110 -> 4.122153 | E106: =E105/E110 -> 4.3843994 | F106: =F105/F110 -> 4.3141471 | G106: =G105/G110 -> 4.1466954 | H106: =H105/H110 -> 3.969705
A107: Net Borrowing | B107: ='Cash Flow Statement'!I$25 + 'Cash Flow Statement'!I$28 -> -212.8 | C107: ='Cash Flow Statement'!J$25 + 'Cash Flow Statement'!J$28 -> 10598.6 | D107: ='Cash Flow Statement'!K$25 + 'Cash Flow Statement'!K$28 -> 3738.9 | E107: =AVERAGE((B107/B83),(C107/C83),(D107/D83))*E83 -> 4800.9223 | F107: =AVERAGE((B107/B83),(C107/C83),(D107/D83))*F83 -> 4551.2743 | G107: =AVERAGE((B107/B83),(C107/C83),(D107/D83))*G83 -> 4314.6081 | H107: =AVERAGE((B107/B83),(C107/C83),(D107/D83))*H83 -> 4090.2484
...

Sheet Input sheet
A1: Novo Nordisk (NYSE:NVO) | C1: Precio | D1: =IFERROR(__xludf.DUMMYFUNCTION("IF(A1="""","""",GOOGLEFINANCE(REGEXEXTRACT(A1,""\(.*?:(.*?)\)""),""price""))")," ") -> 39.4
C2: Input cell | E2: Calculated cell
A4: Date of valuation | B4: 46288 | C4: Important: Before you run this spreadsheet, go into preferences in Excel and check under Calculation options
A5: Company name | B5: Novo Nordisk A/S (ADR NYSE: NVO; 1 ADR = 1 acción B). Cifras en USD millones convertidas desde DKK | C5: There should be a check against the iteration box. If there is not, you will get circular reasoning errors.
A6: Numbers from your base year below ( in consistent units, i.e., if you enter numbers in millions, stay with millions all the way through, including on share count.
A7: If you don't understand an input, turn on comemnts and you should see my suggestions on that input.
A8: Country of incorporation | B8: Denmark | F8: If you want a guide through this spreadsheet, try this YouTube video that takes you through each input cell: https://youtu.be/kyKfJ_7-mdg?si=FIeHhnLH2_2brag3
A9: Industry (US) | B9: Drugs (Pharmaceutical)
A10: Industry (Global) | B10: Drugs (Pharmaceutical)
B11: Most Recent 12 months | C11: Last 10K before LTM | D11: Years since last 10K
A12: Revenues | B12: ='Income Statement'!L3 -> 47254.1 | C12: =IF('Income Statement'!L3='Income Statement'!K3,'Income Statement'!J3,'Income Statement'!K3) -> 46702.4 | D12: =IF('Income Statement'!L3='Income Statement'!K3,1,0.5) -> 0.5
A13: Operating income or EBIT | B13: ='Income Statement'!L12 -> 18994.8 | C13: =IF('Income Statement'!L12='Income Statement'!K12,'Income Statement'!J12,'Income Statement'!K12) -> 19290.3
A14: Interest expense | B14: ='Income Statement'!L16 -> -659.9 | C14: =IF('Income Statement'!L16='Income Statement'!K16,'Income Statement'!J16,'Income Statement'!K16) -> -443.9
A15: Book value of equity | B15: ='Balance Sheet'!L35 -> 33731.5 | C15: =IF('Balance Sheet'!L35='Balance Sheet'!K35,'Balance Sheet'!J35,'Balance Sheet'!K35) -> 30527.3
A16: Book value of debt | B16: ='Balance Sheet'!L20+'Balance Sheet'!L21+'Balance Sheet'!L25+'Balance Sheet'!L26 -> 21361 | C16: =IF('Balance Sheet'!L20+'Balance Sheet'!L21+'Balance Sheet'!L25+'Balance Sheet'!L26='Balance Sheet'!K20+'Balance Sheet'!K21+'Balance Sheet'!K25+'Balance Sheet'!K26,'Balance Sheet'!J20+'Balance Sheet'!J21+'Balance Sheet'!J25+'Balance Sheet'!J26,'Balance Sheet'!K20+'Balance Sheet'!K21+'Balance Sheet'!K25+'Balance Sheet'!K26) -> 20602.2
A17: Do you have R&D expenses to capitalize? | B17: Yes | C17: If you want to capitalize R&D, you have to input the numbers into the R&D worksheet.
A18: Do you have operating lease commitments? | B18: No | C18: If you lease or other contractual commitments that have not been converteed to debt already, say yes to this option and do the conversion.
A19: Cash and Marketable Securities | B19: ='Balance Sheet'!L5 -> 6857.1 | C19: =IF('Balance Sheet'!L5='Balance Sheet'!K5,'Balance Sheet'!J5,'Balance Sheet'!K5) -> 4241.6
A20: Cross holdings and other non-operating assets | B20: ='Balance Sheet'!L14+'Balance Sheet'!L15 -> 4943.7 | C20: =IF('Balance Sheet'!L14+'Balance Sheet'!L15='Balance Sheet'!K14+'Balance Sheet'!K15,'Balance Sheet'!J14+'Balance Sheet'!J15,'Balance Sheet'!K14+'Balance Sheet'!K15) -> 5037
A21: Minority interests | B21: 0 | C21: 0
A22: Number of shares outstanding = | B22: ='Income Statement'!L27 -> 4416.8 | E22: Computed numbers: Here is what your company's numbers look like, relative to industry.
A23: Current stock price = | B23: ='Input sheet'!D1 -> 39.4 | E23: If you are not working in US dollars, you should add the inflation differential to the industry averages.
A24: Effective tax rate = | B24: ='Income Statement'!I29 -> 0.2005 | J24: Industry (US) | K24: Industry (Global) | L24: Global Distribution Stats
A25: Marginal tax rate = | B25: 0.22 | I25: Company | J25: Average | K25: Average | L25: 1st Quartile | M25: Median | N25: 3rd Quartile
A26: The value drivers below: | E26: Revenue growth in the most recent year = | I26: =IF(C12>0,(B12/C12)^(1/D12)-1, "NA") -> 0.023765744 | J26: =VLOOKUP(B9,'Industry Averages(US)'!A3:S96,3) -> 0.18446775 | K26: =VLOOKUP(B10,'Industry Averages (Global)'!A3:N96,3) -> 0.14050235 | L26: =VLOOKUP($B$10,'Input Stat Distributioons'!$A$4:$T$97,3,FALSE) -> 0.039 | M26: =VLOOKUP($B$10,'Input Stat Distributioons'!$A$4:$T$97,4,FALSE) -> 0.104 | N26: =VLOOKUP($B$10,'Input Stat Distributioons'!$A$4:$T$97,5,FALSE) -> 0.189
A27: Revenue growth rate for next year | B27: -0.04 | C27: Growth Lever - Next year | E27: Pre-tax operating margin in the most recent year = | I27: ='Valuation output'!B6 -> 0.49498795 | J27: =VLOOKUP(B9,'Industry Averages(US)'!A3:AA96,4) -> 0.295397 | K27: =VLOOKUP(B10,'Industry Averages (Global)'!A3:N96,4) -> 0.2307006 | L27: =VLOOKUP($B$10,'Input Stat Distributioons'!$A$4:$T$97,6,FALSE) -> -0.14144737 | M27: =VLOOKUP($B$10,'Input Stat Distributioons'!$A$4:$T$97,7,FALSE) -> 0.058879847 | N27: =VLOOKUP($B$10,'Input Stat Distributioons'!$A$4:$T$97,8,FALSE) -> 0.15482761
A28: Operating Margin for next year | B28: ='Valuation output'!B6-0.02 -> 0.47498795 | C28: Profitability Lever - Next year | E28: Sales to capital ratio in most recent year = | I28: =B12/'Valuation output'!B41 -> 0.60592115 | J28: =VLOOKUP(B9,'Industry Averages(US)'!A3:S96,14) -> 1.1116586 | K28: =VLOOKUP(B10,'Industry Averages (Global)'!A3:N96,14) -> 1.0697899 | L28: =VLOOKUP($B$10,'Input Stat Distributioons'!$A$4:$T$97,9,FALSE) -> 0.40617589 | M28: =VLOOKUP($B$10,'Input Stat Distributioons'!$A$4:$T$97,10,FALSE) -> 0.82019584 | N28: =VLOOKUP($B$10,'Input Stat Distributioons'!$A$4:$T$97,11,FALSE) -> 1.3765042
A29: Compounded annual revenue growth rate - years 2-5 = | B29: 0.035 | C29: Growth Lever - Long term | E29: Marginal sales to capital ratio = | I29: =IF(('Input sheet'!B12-'Input sheet'!C12)/(('Input sheet'!B15+'Input sheet'!B16-'Input sheet'!B19)-('Input sheet'!C15+'Input sheet'!C16-'Input sheet'!C19))>0,('Input sheet'!B12-'Input sheet'!C12)/(('Input sheet'!B15+'Input sheet'!B16-'Input sheet'!B19)-('Input sheet'!C15+'Input sheet'!C16-'Input sheet'!C19)),"NA") -> 0.40942486
A30: Target pre-tax operating margin = | B30: 0.45 | C30: Profitability Lever - Long term | E30: Return on invested capital in most recent year= | I30: ='Valuation output'!B9/'Valuation output'!B41 -> 0.23978897 | J30: =VLOOKUP(B9,'Industry Averages(US)'!A3:S96,5) -> 0.16949548 | K30: =VLOOKUP(B10,'Industry Averages (Global)'!A3:N96,5) -> 0.14737283
A31: Year of convergence for margin | B31: 5 | C31: Speed of convergence level | E31: Standard deviation in stock prices = | J31: =VLOOKUP(B9,'Industry Averages(US)'!A3:S96,10) -> 0.76644924 | K31: =VLOOKUP(B9,'Industry Averages (Global)'!A3:Z96,10) -> 0.47485789
A32: Sales to capital ratio (for years 1-5) | B32: 0.8 | C32: Efficency of Growth Lever (first 5 years) | E32: Cost of capital = | I32: =B36 -> 0.10042099 | J32: =VLOOKUP(B9,'Industry Averages(US)'!A3:S96,13) -> 0.078487512 | K32: =VLOOKUP(B9,'Industry Averages (Global)'!A3:Z96,13) -> 0.092235289 | L32: =VLOOKUP($B$10,'Input Stat Distributioons'!$A$4:$T$97,12,FALSE) -> 0.083851835 | M32: =VLOOKUP($B$10,'Input Stat Distributioons'!$A$4:$T$97,13,FALSE) -> 0.089041973 | N32: =VLOOKUP($B$10,'Input Stat Distributioons'!$A$4:$T$97,14,FALSE) -> 0.10157621
A33: Sales to capital ratio (for years 6-10) | B33: =K28 -> 1.0697899 | C33: Efficency of Growth Lever (years 6-10)
A34: Market numbers | E34: Valuation Output Feedback (for you to use to fine tune your inputs, if you want)
A35: Riskfree rate | B35: 0.0496 | E35: Revenues in year 10, based on your revenue growth = | J35: ='Valuation output'!M5 -> 67683.405
A36: Initial cost of capital = | B36: ='Cost of capital worksheet'!B14 -> 0.10042099 | C36: Do not input. Go to cost of capital sheet. | E36: Pre-tax Operating Income in year 10, based on your operating margin = | J36: ='Valuation output'!M7 -> 30457.532
A37: Other inputs | E37: Return on invested capital in year 10, based on your sales/capital ratio = | J37: ='Valuation output'!L42 -> 0.22957288
A38: Do you have employee options outstanding? | B38: No | E38: Check the Diagnostics worksheet for more details.
A39: Number of options outstanding =
A40: Average strike price =
A41: Average maturity = | B41: 7
A42: Standard deviation on stock price = | B42: 0.45
A44: Default assumptions.
A45: In stable growth, I will assume that your firm will have a cost of capital similar to that of typical mature companies (riskfree rate + 4.5%)
A46: Do you want to override this assumption = | B46: No | C46: Mature companies generally see their risk levels approach the average
A47: If yes, enter the cost of capital after year 10 = | B47: =B36 -> 0.10042099 | C47: Though some sectors, even in stable growth, may have higher risk. If you change your risk free rate after year 10 (see cell B57 & 58), you should incorporate the change into your stable cost of capital estimate.
A48: I will assume that your firm will earn a return on capital equal to its cost of capital after year 10. I am assuming that whatever competitive advantages you have today will fade over time.
A49: Do you want to override this assumption = | B49: No | C49: Mature companies find it difficult to generate returns that exceed the cost of capital
A50: If yes, enter the return on capital you expect after year 10 | B50: 0.2 | C50: But there are significant exceptions among companies with long-lasting competitive advantages.
A51: I will assume that your firm has no chance of failure over the foreseeable future.
A52: Do you want to override this assumption = | B52: No | C52: Many young, growth companies fail, especially if they have trouble raising cash. Many distressed companies fail, because they have trouble making debt payments.
A53: If yes, enter the probability of failure = | B53: 0.12 | C53: Tough to estimate but a key input. Use the failure rate worksheet, if necessary.
A54: What do you want to tie your proceeds in failure to? | B54: V | C54: B: Book value of capital, V= Estimated fair value for the company
A55: Enter the distress proceeds as percentage of book or fair value | B55: 0.5 | C55: This can be zero, if the assets will be worth nothing if the firm fails.
A56: I assume that reinvestment in a year translates into growth in the next year, i.e., there is a one year lag between reinvesting and generating growth from that reinvestment.
A57: Do you want override this assumption = | B57: No
A58: If yes, enter a different lag (0 = no lag to 3 = lag of 3 years) | B58: 1
A59: I will assume that your effective tax rate will adjust to your marginal tax rate by your terminal year. If you override this assumption, I will leave the tax rate at your effective tax rate.
A60: Do you want to override this assumption = | B60: No
A61: I will assume that you have no losses carried forward from prior years ( NOL) coming into the valuation. If you have a money losing company, you may want to override tis.
A62: Do you want to override this assumption = | B62: No | C62: Check the financial statements.
A63: If yes, enter the NOL that you are carrying over into year 1 | B63: 0 | C63: An NOL will shield your income from taxes, even after you start making money.
A64: I will asssume that today's risk free rate will prevail in perpetuity. If you override this assumption, I will change the riskfree rate after year 10.
A65: Do you want to override this assumption = | B65: No | C65: If yes, you will be asked to enter a normal risk free rate and your growth in perpetuity will be adjusted accordingly.
A66: If yes, enter the riskfree rate after year 10 | B66: 0.02 | C66: Enter your estimate of what the riskfree rate (in your currency of choice) will be after year 10
A67: I will assume that the growth rate in perpetuity will be equal to the risk free rate. This allows for both valuation consistency and prevents "impossible" growth rates.
A68: Do you want to override this assumption = | B68: No | C68: This is an option to let you use a negative growth rate in perpetuity or to even liquidate the firm.
A69: If yes, enter the growth rate in perpetuity | B69: -0.05 | C69: This can be negative, if you feel the company will decline (and disappear) after growth is done. If you let it exceed the risk free rate, you are on your own in uncharted territory.
A70: I have assumed that none of the cash is trapped (in foreign countries) and that there is no additional tax liability coming due and that cash is a neutral asset.
A71: Do you want to override this assumption | B71: No
A72: If yes, enter trapped cash (if taxes) or entire balance (if mistrust) | B72: 140000 | C72: Cash that is trapped in foreign markets (and subject to additoinal tax) or cash that is being discounted by the market (because of management mistrust)
A73: & Average tax rate of the foreign markets where the cash is trapped | B73: 0.15 | C73: Additional tax rate due on trapped cash or discount being applied to cash balance because of mistrust.

Sheet Valuation output
A1: ='Input sheet'!A1 -> Novo Nordisk (NYSE:NVO) | C1: Precio | D1: ='Input sheet'!D1 -> 39.4
A2: Modelo Base | B2: Base
B3: Base year | C3: 1 | D3: 2 | E3: 3 | F3: 4 | G3: 5 | H3: 6 | I3: 7 | J3: 8 | K3: 9 | L3: 10 | M3: Terminal year
A4: Revenue growth rate | B4: ='Input sheet'!B27 -> -0.04 | C4: ='Input sheet'!B27 -> -0.04 | D4: ='Input sheet'!B29 -> 0.035 | E4: =D4 -> 0.035 | F4: =E4 -> 0.035 | G4: =F4 -> 0.035 | H4: =G4-((G4-$M$4)/5) -> 0.03792 | I4: =G4-((G4-$M$4)/5)*2 -> 0.04084 | J4: =G4-((G4-$M$4)/5)*3 -> 0.04376 | K4: =G4-((G4-$M$4)/5)*4 -> 0.04668 | L4: =G4-((G4-$M$4)/5)*5 -> 0.0496 | M4: =IF('Input sheet'!B68="Yes",'Input sheet'!B69,IF('Input sheet'!B65="Yes",'Input sheet'!B66,'Input sheet'!B35)) -> 0.0496
A5: Revenues | B5: ='Input sheet'!$B$12 -> 47254.1 | C5: =B5*(1+C4) -> 45363.936 | D5: =C5*(1+D4) -> 46951.674 | E5: =D5*(1+E4) -> 48594.982 | F5: =E5*(1+F4) -> 50295.807 | G5: =F5*(1+G4) -> 52056.16 | H5: =G5*(1+H4) -> 54030.13 | I5: =H5*(1+I4) -> 56236.72 | J5: =I5*(1+J4) -> 58697.639 | ... M5: =L5*(1+M4) -> 67683.405
A6: EBIT (Operating) margin | B6: =B7/B5 -> 0.49498795 | C6: ='Input sheet'!B28 -> 0.47498795 | D6: =IF(D3>'Input sheet'!$B$31,$C$46,$C$46-(($C$46-$C$6)/'Input sheet'!$B$31)*('Input sheet'!$B$31-D3)) -> 0.46499277 | E6: =IF(E3>'Input sheet'!$B$31,$C$46,$C$46-(($C$46-$C$6)/'Input sheet'!$B$31)*('Input sheet'!$B$31-E3)) -> 0.45999518 | F6: =IF(F3>'Input sheet'!$B$31,$C$46,$C$46-(($C$46-$C$6)/'Input sheet'!$B$31)*('Input sheet'!$B$31-F3)) -> 0.45499759 | G6: =IF(G3>'Input sheet'!$B$31,$C$46,$C$46-(($C$46-$C$6)/'Input sheet'!$B$31)*('Input sheet'!$B$31-G3)) -> 0.45 | H6: =IF(H3>'Input sheet'!$B$31,$C$46,$C$46-(($C$46-$C$6)/'Input sheet'!$B$31)*('Input sheet'!$B$31-H3)) -> 0.45 | I6: =IF(I3>'Input sheet'!$B$31,$C$46,$C$46-(($C$46-$C$6)/'Input sheet'!$B$31)*('Input sheet'!$B$31-I3)) -> 0.45 | J6: =IF(J3>'Input sheet'!$B$31,$C$46,$C$46-(($C$46-$C$6)/'Input sheet'!$B$31)*('Input sheet'!$B$31-J3)) -> 0.45 | K6: =IF(K3>'Input sheet'!$B$31,$C$46,$C$46-(($C$46-$C$6)/'Input sheet'!$B$31)*('Input sheet'!$B$31-K3)) -> 0.45 | L6: =IF(L3>'Input sheet'!$B$31,$C$46,$C$46-(($C$46-$C$6)/'Input sheet'!$B$31)*('Input sheet'!$B$31-L3)) -> 0.45 | M6: =L6 -> 0.45
A7: EBIT (Operating income) | B7: =IF('Input sheet'!$B$18="Yes",IF('Input sheet'!$B$17="Yes",'Input sheet'!$B$13+'Operating lease converter'!$F$33+'R& D converter'!$D$40,'Input sheet'!$B$13+'Operating lease converter'!$F$33),IF('Input sheet'!$B$17="Yes",'Input sheet'!$B$13+'R& D converter'!$D$40,'Input sheet'!$B$13)) -> 23390.21 | C7: =C6*C5 -> 21547.323 | D7: =D6*D5 -> 21832.189 | E7: =E6*E5 -> 22353.458 | F7: =F6*F5 -> 22884.471 | G7: =G6*G5 -> 23425.272 | H7: =H6*H5 -> 24313.558 | I7: =I6*I5 -> 25306.524 | J7: =J6*J5 -> 26413.938 | ... M7: =M6*M5 -> 30457.532 | N7: =M7-B7 -> 7067.3225
A8: Tax rate | B8: ='Input sheet'!$B$24 -> 0.2005 | C8: =B8 -> 0.2005 | D8: =C8 -> 0.2005 | E8: =D8 -> 0.2005 | F8: =E8 -> 0.2005 | G8: =F8 -> 0.2005 | H8: =G8+($M8-$G8)/5 -> 0.2044 | I8: =H8+($M8-$G8)/5 -> 0.2083 | J8: =I8+($M8-$G8)/5 -> 0.2122 | K8: =J8+($M8-$G8)/5 -> 0.2161 | L8: =K8+($M8-$G8)/5 -> 0.22 | M8: =IF('Input sheet'!$B$60="Yes",'Input sheet'!$B$24,'Input sheet'!$B$25) -> 0.22
A9: EBIT(1-t) | B9: =IF(B7>0,B7*(1-B8),B7) -> 18700.473 | C9: =IF(C7>0,IF(C7<B12,C7,C7-(C7-B12)*C8),C7) -> 17227.085 | D9: =IF(D7>0,IF(D7<C12,D7,D7-(D7-C12)*D8),D7) -> 17454.835 | E9: =IF(E7>0,IF(E7<D12,E7,E7-(E7-D12)*E8),E7) -> 17871.589 | F9: =IF(F7>0,IF(F7<E12,F7,F7-(F7-E12)*F8),F7) -> 18296.134 | G9: =IF(G7>0,IF(G7<F12,G7,G7-(G7-F12)*G8),G7) -> 18728.505 | H9: =IF(H7>0,IF(H7<G12,H7,H7-(H7-G12)*H8),H7) -> 19343.867 | I9: =IF(I7>0,IF(I7<H12,I7,I7-(I7-H12)*I8),I7) -> 20035.175 | J9: =IF(J7>0,IF(J7<I12,J7,J7-(J7-I12)*J8),J7) -> 20808.9 | ... L9: =IF(L7>0,IF(L7<K12,L7,L7-(L7-K12)*L8),L7) -> 22634.218 | M9: =M7*(1-M8) -> 23756.875
A10: - Reinvestment | C10: =IF('Input sheet'!$B$57="No",(D5-C5)/C40,IF('Input sheet'!$B$58=0,(C5-B5)/C40,IF('Input sheet'!$B$58=2,(E5-D5)/C40,IF('Input sheet'!$B$58=3,(F5-E5)/C40,(D5-C5)/C40)))) -> 1984.6722 | D10: =IF('Input sheet'!$B$57="No",(E5-D5)/D40,IF('Input sheet'!$B$58=0,(D5-C5)/D40,IF('Input sheet'!$B$58=2,(F5-E5)/D40,IF('Input sheet'!$B$58=3,(G5-F5)/D40,(E5-D5)/D40)))) -> 2054.1357 | E10: =IF('Input sheet'!$B$57="No",(F5-E5)/E40,IF('Input sheet'!$B$58=0,(E5-D5)/E40,IF('Input sheet'!$B$58=2,(G5-F5)/E40,IF('Input sheet'!$B$58=3,(H5-G5)/E40,(F5-E5)/E40)))) -> 2126.0305 | F10: =IF('Input sheet'!$B$57="No",(G5-F5)/F40,IF('Input sheet'!$B$58=0,(F5-E5)/F40,IF('Input sheet'!$B$58=2,(H5-G5)/F40,IF('Input sheet'!$B$58=3,(I5-H5)/F40,(G5-F5)/F40)))) -> 2200.4415 | G10: =IF('Input sheet'!$B$57="No",(H5-G5)/G40,IF('Input sheet'!$B$58=0,(G5-F5)/G40,IF('Input sheet'!$B$58=2,(I5-H5)/G40,IF('Input sheet'!$B$58=3,(J5-I5)/G40,(H5-G5)/G40)))) -> 2467.462 | H10: =IF('Input sheet'!$B$57="No",(I5-H5)/H40,IF('Input sheet'!$B$58=0,(H5-G5)/H40,IF('Input sheet'!$B$58=2,(J5-I5)/H40,IF('Input sheet'!$B$58=3,(K5-J5)/H40,(I5-H5)/H40)))) -> 2062.6392 | I10: =IF('Input sheet'!$B$57="No",(J5-I5)/I40,IF('Input sheet'!$B$58=0,(I5-H5)/I40,IF('Input sheet'!$B$58=2,(K5-J5)/I40,IF('Input sheet'!$B$58=3,(L5-K5)/I40,(J5-I5)/I40)))) -> 2300.376 | J10: =IF('Input sheet'!$B$57="No",(K5-J5)/J40,IF('Input sheet'!$B$58=0,(J5-I5)/J40,IF('Input sheet'!$B$58=2,(L5-K5)/J40,IF('Input sheet'!$B$58=3,(M5-L5)/J40,(K5-J5)/J40)))) -> 2561.2561 | K10: =IF('Input sheet'!$B$57="No",(L5-K5)/K40,IF('Input sheet'!$B$58=0,(K5-J5)/K40,IF('Input sheet'!$B$58=2,L5*L4/K40,IF('Input sheet'!$B$58=3,M5*M4/K40,(L5-K5)/K40)))) -> 2848.5101 | L10: =IF('Input sheet'!$B$57="No",(M5-L5)/L40,IF('Input sheet'!$B$58=0,(L5-K5)/L40,IF('Input sheet'!$B$58=2,M5*M4/L40,IF('Input sheet'!$B$58=3,K10*(1+M4),(M5-L5)/L40)))) -> 2989.7962 | M10: =M9*(M4/M42) -> 12821.991 | N10: =SUM(C10:M10) -> 36417.311
A11: FCFF | C11: =C9-C10 -> 15242.412 | D11: =D9-D10 -> 15400.699 | E11: =E9-E10 -> 15745.559 | F11: =F9-F10 -> 16095.693 | G11: =G9-G10 -> 16261.043 | H11: =H9-H10 -> 17281.228 | I11: =I9-I10 -> 17734.799 | J11: =J9-J10 -> 18247.644 | ... M11: =M9-M10 -> 10934.884
A12: NOL | B12: =IF('Input sheet'!$B$62="Yes",'Input sheet'!$B$63,0) -> 0 | C12: =IF(C7<0,B12-C7,IF(B12>C7,B12-C7,0)) -> 0 | D12: =IF(D7<0,C12-D7,IF(C12>D7,C12-D7,0)) -> 0 | E12: =IF(E7<0,D12-E7,IF(D12>E7,D12-E7,0)) -> 0 | F12: =IF(F7<0,E12-F7,IF(E12>F7,E12-F7,0)) -> 0 | G12: =IF(G7<0,F12-G7,IF(F12>G7,F12-G7,0)) -> 0 | H12: =IF(H7<0,G12-H7,IF(G12>H7,G12-H7,0)) -> 0 | I12: =IF(I7<0,H12-I7,IF(H12>I7,H12-I7,0)) -> 0 | J12: =IF(J7<0,I12-J7,IF(I12>J7,I12-J7,0)) -> 0 | ... M12: =IF(M7<0,L12-M7,IF(L12>M7,L12-M7,0)) -> 0
A14: Cost of capital | C14: ='Input sheet'!$B$36 -> 0.10042099 | D14: =C14 -> 0.10042099 | E14: =D14 -> 0.10042099 | F14: =E14 -> 0.10042099 | G14: =F14 -> 0.10042099 | H14: =G14-($G14-$M14)/5 -> 0.098716792 | I14: =H14-($G14-$M14)/5 -> 0.097012594 | J14: =I14-($G14-$M14)/5 -> 0.095308396 | K14: =J14-($G14-$M14)/5 -> 0.093604198 | L14: =K14-($G14-$M14)/5 -> 0.0919 | M14: =IF('Input sheet'!$B$46="Yes",'Input sheet'!$B$47,IF('Input sheet'!$B$65="Yes",'Input sheet'!$B$66+'Country equity risk premiums'!$B$2,'Input sheet'!$B$35+'Country equity risk premiums'!$B$2)) -> 0.0919
A15: Cumulated discount factor | C15: =1/(1+C14) -> 0.90874312 | D15: =C15*(1/(1+D14)) -> 0.82581405 | E15: =D15*(1/(1+E14)) -> 0.75045284 | F15: =E15*(1/(1+F14)) -> 0.68196885 | G15: =F15*(1/(1+G14)) -> 0.6197345 | H15: =G15*(1/(1+H14)) -> 0.56405299 | I15: =H15*(1/(1+I14)) -> 0.51417185 | J15: =I15*(1/(1+J14)) -> 0.46943112 | K15: =J15*(1/(1+K14)) -> 0.42925139 | L15: =K15*(1/(1+L14)) -> 0.39312335
A16: PV(FCFF) | C16: =C11*C15 -> 13851.437 | D16: =D11*D15 -> 12718.114 | E16: =E11*E15 -> 11816.299 | F16: =F11*F15 -> 10976.761 | G16: =G11*G15 -> 10077.529 | H16: =H11*H15 -> 9747.5283 | I16: =I11*I15 -> 9118.7345 | J16: =J11*J15 -> 8566.0119 | ... L16: =L11*L15 -> 7722.681
A18: Terminal cash flow | B18: =M11 -> 10934.884
A19: Terminal cost of capital | B19: =M14 -> 0.0919
A20: Terminal value | B20: =B18/(B19-M4) -> 258507.89
A21: PV(Terminal value) | B21: =B20*L15 -> 101625.49
A22: PV (CF over next 10 years) | B22: =SUM(C16:L16) -> 102675.29
A23: Sum of PV | B23: =B21+B22 -> 204300.78
A24: Probability of failure = | B24: =IF('Input sheet'!$B$52="Yes",'Input sheet'!$B$53,0) -> 0
A25: Proceeds if firm fails = | B25: =IF('Input sheet'!$B$54="B",('Input sheet'!$B$15+'Input sheet'!$B$16)*'Input sheet'!$B$55,'Valuation output'!B23*'Input sheet'!$B$55) -> 102150.39
A26: Value of operating assets = | B26: =B23*(1-B24)+B25*B24 -> 204300.78
A27: - Debt | B27: =IF('Input sheet'!$B$18="Yes",'Input sheet'!$B$16+'Operating lease converter'!$C$29,'Input sheet'!$B$16) -> 21361
A28: - Minority interests | B28: ='Input sheet'!$B$21 -> 0
A29: + Cash | B29: =IF('Input sheet'!$B$71="YES",'Input sheet'!$B$19-'Input sheet'!$B$72*('Input sheet'!$B$25-'Input sheet'!$B$73),'Input sheet'!$B$19) -> 6857.1 | D29: If you get Value Errors all over, it is usually because your option worksheet has gone haywire. The fix is very low tech. Go into the option value worksheet, and in cell B17 of that worksheet (adjusted S), enter any number (say 5) and then undo what you did. Voila!
A30: + Non-operating assets | B30: ='Input sheet'!$B$20 -> 4943.7
A31: Value of equity | B31: =B26-B27-B28+B29+B30 -> 194740.58
A32: - Value of options | B32: =IF('Input sheet'!$B$38="No",0,'Option value'!$B$30) -> 0
A33: Value of equity in common stock | B33: =B31-B32 -> 194740.58
A34: Number of shares | B34: ='Input sheet'!$B$22 -> 4416.8
A35: Estimated value /share | B35: =B33/B34 -> 44.090876
A36: Price | B36: ='Input sheet'!$B$23 -> 39.4
A37: Price as % of value | B37: =B36/B35 -> 0.89360891
A39: Implied variables | M39: After year 10
A40: Sales to capital ratio | C40: ='Input sheet'!$B$32 -> 0.8 | D40: ='Input sheet'!$B$32 -> 0.8 | E40: =D40 -> 0.8 | F40: =E40 -> 0.8 | G40: =F40 -> 0.8 | H40: ='Input sheet'!$B$33 -> 1.0697899 | I40: =H40 -> 1.0697899 | J40: =I40 -> 1.0697899 | K40: =J40 -> 1.0697899 | L40: =K40 -> 1.0697899
A41: Invested capital | B41: =IF('Input sheet'!$B$18="Yes",IF('Input sheet'!$B$17="Yes",'Input sheet'!$B$15+'Input sheet'!$B$16-'Input sheet'!$B$19+'Operating lease converter'!$F$34+'R& D converter'!$D$36,'Input sheet'!$B$15+'Input sheet'!$B$16-'Input sheet'!$B$19+'Operating lease converter'!$F$34),IF('Input sheet'!$B$17="Yes",'Input sheet'!$B$15+'Input sheet'!$B$16-'Input sheet'!$B$19+'R& D converter'!$D$36,'Input sheet'!$B$15+'Input sheet'!$B$16-'Input sheet'!$B$19)) -> 77987.21 | C41: =B41+C10 -> 79971.882 | D41: =C41+D10 -> 82026.018 | E41: =D41+E10 -> 84152.048 | F41: =E41+F10 -> 86352.49 | G41: =F41+G10 -> 88819.952 | H41: =G41+H10 -> 90882.591 | I41: =H41+I10 -> 93182.967 | J41: =I41+J10 -> 95744.223 | ... L41: =K41+L10 -> 101582.53
A42: ROIC | B42: =B9/B41 -> 0.23978897 | C42: =C9/B41 -> 0.22089628 | D42: =D9/C41 -> 0.21826215 | E42: =E9/D41 -> 0.21787708 | F42: =F9/E41 -> 0.21741758 | G42: =G9/F41 -> 0.21688437 | H42: =H9/G41 -> 0.21778741 | I42: =I9/H41 -> 0.22045119 | J42: =J9/I41 -> 0.22331227 | ... L42: =L9/K41 -> 0.22957288 | M42: =IF('Input sheet'!$B$49="Yes",'Input sheet'!$B$50,'Valuation output'!L14) -> 0.0919
B44: Growth | C44: EBIT margin
A45: Conservador | B45: ='Input sheet'!B35 -> 0.0496 | C45: =B6 -> 0.49498795
A46: Base | B46: ='Input sheet'!J26 -> 0.18446775 | C46: ='Input sheet'!B30 -> 0.45
A47: Optimista | B47: =B50 -> 0.1149289 | C47: ='Input sheet'!B30+0.05 -> 0.5
A49: LTM | B49: ='Income Statement'!L4 -> 0.0487 | C49: ='Income Statement'!$L$13 -> 0.402
A50: Promedio 3Y | B50: =('Income Statement'!K3/'Income Statement'!I3)^(1/3)-1 -> 0.1149289 | C50: =AVERAGE('Income Statement'!$I$13:$K$13) -> 0.43216667
A51: Promedio de 5Y | B51: =('Income Statement'!K3/'Income Statement'!G3)^(1/5)-1 -> 0.15850875 | C51: =AVERAGE('Income Statement'!$G$13:$K$13) -> 0.42716
A52: CAGR 10Y | B52: =('Income Statement'!K3/'Income Statement'!B3)^(1/10)-1 -> 0.10891101 | C52: =AVERAGE('Income Statement'!$B$13:$K$13) -> 0.42865
A53: Modelo Conservador | B53: Conservador
B54: Base year | C54: 1 | D54: 2 | E54: 3 | F54: 4 | G54: 5 | H54: 6 | I54: 7 | J54: 8 | K54: 9 | L54: 10 | M54: Terminal year
A55: Revenue growth rate | B55: ='Input sheet'!B29 -> 0.035 | C55: =AVERAGE('Input sheet'!B27,'Input sheet'!B35) -> 0.0048 | D55: =C55 -> 0.0048 | E55: =D55 -> 0.0048 | F55: =E55 -> 0.0048 | G55: =F55 -> 0.0048 | H55: =G55-((G55-$M$4)/5) -> 0.01376 | I55: =G55-((G55-$M$4)/5)*2 -> 0.02272 | J55: =G55-((G55-$M$4)/5)*3 -> 0.03168 | K55: =G55-((G55-$M$4)/5)*4 -> 0.04064 | L55: =G55-((G55-$M$4)/5)*5 -> 0.0496 | M55: =IF('Input sheet'!B68="Yes",'Input sheet'!B69,IF('Input sheet'!B65="Yes",'Input sheet'!B66,'Input sheet'!B35)) -> 0.0496
A56: Revenues | B56: ='Input sheet'!$B$12 -> 47254.1 | C56: =B56*(1+C55) -> 47480.92 | D56: =C56*(1+D55) -> 47708.828 | E56: =D56*(1+E55) -> 47937.83 | F56: =E56*(1+F55) -> 48167.932 | G56: =F56*(1+G55) -> 48399.138 | H56: =G56*(1+H55) -> 49065.11 | I56: =H56*(1+I55) -> 50179.87 | J56: =I56*(1+J55) -> 51769.568 | ... M56: =L56*(1+M55) -> 59350.27
A57: EBIT (Operating) margin | B57: =B58/B56 -> 0.49498795 | C57: ='Input sheet'!B28 -> 0.47498795 | D57: =IF(D3>'Input sheet'!$B$31,$C$45,$C$45-(($C$45-$C$6)/'Input sheet'!$B$31)*('Input sheet'!$B$31-D3)) -> 0.48298795 | E57: =IF(E3>'Input sheet'!$B$31,$C$45,$C$45-(($C$45-$C$6)/'Input sheet'!$B$31)*('Input sheet'!$B$31-E3)) -> 0.48698795 | F57: =IF(F3>'Input sheet'!$B$31,$C$45,$C$45-(($C$45-$C$6)/'Input sheet'!$B$31)*('Input sheet'!$B$31-F3)) -> 0.49098795 | G57: =IF(G3>'Input sheet'!$B$31,$C$45,$C$45-(($C$45-$C$6)/'Input sheet'!$B$31)*('Input sheet'!$B$31-G3)) -> 0.49498795 | H57: =IF(H3>'Input sheet'!$B$31,$C$45,$C$45-(($C$45-$C$6)/'Input sheet'!$B$31)*('Input sheet'!$B$31-H3)) -> 0.49498795 | I57: =IF(I3>'Input sheet'!$B$31,$C$45,$C$45-(($C$45-$C$6)/'Input sheet'!$B$31)*('Input sheet'!$B$31-I3)) -> 0.49498795 | J57: =IF(J3>'Input sheet'!$B$31,$C$45,$C$45-(($C$45-$C$6)/'Input sheet'!$B$31)*('Input sheet'!$B$31-J3)) -> 0.49498795 | K57: =IF(K3>'Input sheet'!$B$31,$C$45,$C$45-(($C$45-$C$6)/'Input sheet'!$B$31)*('Input sheet'!$B$31-K3)) -> 0.49498795 | L57: =IF(L3>'Input sheet'!$B$31,$C$45,$C$45-(($C$45-$C$6)/'Input sheet'!$B$31)*('Input sheet'!$B$31-L3)) -> 0.49498795 | M57: =L57 -> 0.49498795
A58: EBIT (Operating income) | B58: =IF('Input sheet'!$B$18="Yes",IF('Input sheet'!$B$17="Yes",'Input sheet'!$B$13+'Operating lease converter'!$F$33+'R& D converter'!$D$40,'Input sheet'!$B$13+'Operating lease converter'!$F$33),IF('Input sheet'!$B$17="Yes",'Input sheet'!$B$13+'R& D converter'!$D$40,'Input sheet'!$B$13)) -> 23390.21 | C58: =C57*C56 -> 22552.865 | D58: =D57*D56 -> 23042.789 | E58: =E57*E56 -> 23345.146 | F58: =F57*F56 -> 23649.874 | G58: =G57*G56 -> 23956.99 | H58: =H57*H56 -> 24286.638 | I58: =I57*I56 -> 24838.431 | J58: =J57*J56 -> 25625.312 | ... M58: =M57*M56 -> 29377.668 | N58: =M58-B58 -> 5987.4584
A59: Tax rate | B59: ='Input sheet'!$B$24 -> 0.2005 | C59: =B59 -> 0.2005 | D59: =C59 -> 0.2005 | E59: =D59 -> 0.2005 | F59: =E59 -> 0.2005 | G59: =F59 -> 0.2005 | H59: =G59+($M59-$G59)/5 -> 0.2044 | I59: =H59+($M59-$G59)/5 -> 0.2083 | J59: =I59+($M59-$G59)/5 -> 0.2122 | K59: =J59+($M59-$G59)/5 -> 0.2161 | L59: =K59+($M59-$G59)/5 -> 0.22 | M59: =IF('Input sheet'!$B$60="Yes",'Input sheet'!$B$24,'Input sheet'!$B$25) -> 0.22
A60: EBIT(1-t) | B60: =IF(B58>0,B58*(1-B59),B58) -> 18700.473 | C60: =IF(C58>0,IF(C58<B63,C58,C58-(C58-B63)*C59),C58) -> 18031.015 | D60: =IF(D58>0,IF(D58<C63,D58,D58-(D58-C63)*D59),D58) -> 18422.71 | E60: =IF(E58>0,IF(E58<D63,E58,E58-(E58-D63)*E59),E58) -> 18664.444 | F60: =IF(F58>0,IF(F58<E63,F58,F58-(F58-E63)*F59),F58) -> 18908.074 | G60: =IF(G58>0,IF(G58<F63,G58,G58-(G58-F63)*G59),G58) -> 19153.614 | H60: =IF(H58>0,IF(H58<G63,H58,H58-(H58-G63)*H59),H58) -> 19322.449 | I60: =IF(I58>0,IF(I58<H63,I58,I58-(I58-H63)*I59),I58) -> 19664.586 | J60: =IF(J58>0,IF(J58<I63,J58,J58-(J58-I63)*J59),J58) -> 20187.621 | ... L60: =IF(L58>0,IF(L58<K63,L58,L58-(L58-K63)*L59),L58) -> 21831.728 | M60: =M58*(1-M59) -> 22914.581
A61: - Reinvestment | C61: =IF('Input sheet'!$B$57="No",(D56-C56)/C91,IF('Input sheet'!$B$58=0,(C56-B56)/C91,IF('Input sheet'!$B$58=2,(E56-D56)/C91,IF('Input sheet'!$B$58=3,(F56-E56)/C91,(D56-C56)/C91)))) -> 284.88552 | D61: =IF('Input sheet'!$B$57="No",(E56-D56)/D91,IF('Input sheet'!$B$58=0,(D56-C56)/D91,IF('Input sheet'!$B$58=2,(F56-E56)/D91,IF('Input sheet'!$B$58=3,(G56-F56)/D91,(E56-D56)/D91)))) -> 286.25297 | E61: =IF('Input sheet'!$B$57="No",(F56-E56)/E91,IF('Input sheet'!$B$58=0,(E56-D56)/E91,IF('Input sheet'!$B$58=2,(G56-F56)/E91,IF('Input sheet'!$B$58=3,(H56-G56)/E91,(F56-E56)/E91)))) -> 287.62698 | F61: =IF('Input sheet'!$B$57="No",(G56-F56)/F91,IF('Input sheet'!$B$58=0,(F56-E56)/F91,IF('Input sheet'!$B$58=2,(H56-G56)/F91,IF('Input sheet'!$B$58=3,(I56-H56)/F91,(G56-F56)/F91)))) -> 289.00759 | G61: =IF('Input sheet'!$B$57="No",(H56-G56)/G91,IF('Input sheet'!$B$58=0,(G56-F56)/G91,IF('Input sheet'!$B$58=2,(I56-H56)/G91,IF('Input sheet'!$B$58=3,(J56-I56)/G91,(H56-G56)/G91)))) -> 832.46518 | H61: =IF('Input sheet'!$B$57="No",(I56-H56)/H91,IF('Input sheet'!$B$58=0,(H56-G56)/H91,IF('Input sheet'!$B$58=2,(J56-I56)/H91,IF('Input sheet'!$B$58=3,(K56-J56)/H91,(I56-H56)/H91)))) -> 1042.0358 | I61: =IF('Input sheet'!$B$57="No",(J56-I56)/I91,IF('Input sheet'!$B$58=0,(I56-H56)/I91,IF('Input sheet'!$B$58=2,(K56-J56)/I91,IF('Input sheet'!$B$58=3,(L56-K56)/I91,(J56-I56)/I91)))) -> 1485.9912 | J61: =IF('Input sheet'!$B$57="No",(K56-J56)/J91,IF('Input sheet'!$B$58=0,(J56-I56)/J91,IF('Input sheet'!$B$58=2,(L56-K56)/J91,IF('Input sheet'!$B$58=3,(M56-L56)/J91,(K56-J56)/J91)))) -> 1966.6622 | K61: =IF('Input sheet'!$B$57="No",(L56-K56)/K91,IF('Input sheet'!$B$58=0,(K56-J56)/K91,IF('Input sheet'!$B$58=2,L56*L55/K91,IF('Input sheet'!$B$58=3,M56*M55/K91,(L56-K56)/K91)))) -> 2497.8034 | L61: =IF('Input sheet'!$B$57="No",(M56-L56)/L91,IF('Input sheet'!$B$58=0,(L56-K56)/L91,IF('Input sheet'!$B$58=2,M56*M55/L91,IF('Input sheet'!$B$58=3,K61*(1+M55),(M56-L56)/L91)))) -> 2621.6945 | M61: =M60*(M55/M93) -> 12367.391 | N61: =SUM(C61:M61) -> 23961.816
A62: FCFF | C62: =C60-C61 -> 17746.13 | D62: =D60-D61 -> 18136.457 | E62: =E60-E61 -> 18376.817 | F62: =F60-F61 -> 18619.067 | G62: =G60-G61 -> 18321.148 | H62: =H60-H61 -> 18280.414 | I62: =I60-I61 -> 18178.594 | J62: =J60-J61 -> 18220.959 | ... M62: =M60-M61 -> 10547.19
A63: NOL | B63: =IF('Input sheet'!$B$62="Yes",'Input sheet'!$B$63,0) -> 0 | C63: =IF(C58<0,B63-C58,IF(B63>C58,B63-C58,0)) -> 0 | D63: =IF(D58<0,C63-D58,IF(C63>D58,C63-D58,0)) -> 0 | E63: =IF(E58<0,D63-E58,IF(D63>E58,D63-E58,0)) -> 0 | F63: =IF(F58<0,E63-F58,IF(E63>F58,E63-F58,0)) -> 0 | G63: =IF(G58<0,F63-G58,IF(F63>G58,F63-G58,0)) -> 0 | H63: =IF(H58<0,G63-H58,IF(G63>H58,G63-H58,0)) -> 0 | I63: =IF(I58<0,H63-I58,IF(H63>I58,H63-I58,0)) -> 0 | J63: =IF(J58<0,I63-J58,IF(I63>J58,I63-J58,0)) -> 0 | ... M63: =IF(M58<0,L63-M58,IF(L63>M58,L63-M58,0)) -> 0
A65: Cost of capital | C65: ='Input sheet'!$B$36 -> 0.10042099 | D65: =C65 -> 0.10042099 | E65: =D65 -> 0.10042099 | F65: =E65 -> 0.10042099 | G65: =F65 -> 0.10042099 | H65: =G65-($G65-$M65)/5 -> 0.098716792 | I65: =H65-($G65-$M65)/5 -> 0.097012594 | J65: =I65-($G65-$M65)/5 -> 0.095308396 | K65: =J65-($G65-$M65)/5 -> 0.093604198 | L65: =K65-($G65-$M65)/5 -> 0.0919 | M65: =IF('Input sheet'!$B$46="Yes",'Input sheet'!$B$47,IF('Input sheet'!$B$65="Yes",'Input sheet'!$B$66+'Country equity risk premiums'!$B$2,'Input sheet'!$B$35+'Country equity risk premiums'!$B$2)) -> 0.0919
A66: Cumulated discount factor | C66: =1/(1+C65) -> 0.90874312 | D66: =C66*(1/(1+D65)) -> 0.82581405 | E66: =D66*(1/(1+E65)) -> 0.75045284 | F66: =E66*(1/(1+F65)) -> 0.68196885 | G66: =F66*(1/(1+G65)) -> 0.6197345 | H66: =G66*(1/(1+H65)) -> 0.56405299 | I66: =H66*(1/(1+I65)) -> 0.51417185 | J66: =I66*(1/(1+J65)) -> 0.46943112 | K66: =J66*(1/(1+K65)) -> 0.42925139 | L66: =K66*(1/(1+L65)) -> 0.39312335
A67: PV(FCFF) | C67: =C62*C66 -> 16126.673 | D67: =D62*D66 -> 14977.341 | E67: =E62*E66 -> 13790.934 | F67: =F62*F66 -> 12697.624 | G67: =G62*G66 -> 11354.248 | H67: =H62*H66 -> 10311.122 | I67: =I62*I66 -> 9346.9215 | J67: =J62*J66 -> 8553.4851 | ... L67: =L62*L66 -> 7551.9127
A69: Terminal cash flow | B69: =M62 -> 10547.19
A70: Terminal cost of capital | B70: =M65 -> 0.0919
A71: Terminal value | B71: =B69/(B70-M55) -> 249342.56
A72: PV(Terminal value) | B72: =B71*L66 -> 98022.384
A73: PV (CF over next 10 years) | B73: =SUM(C67:L67) -> 112611.17
A74: Sum of PV | B74: =B72+B73 -> 210633.55
A75: Probability of failure = | B75: =IF('Input sheet'!$B$52="Yes",'Input sheet'!$B$53,0) -> 0
A76: Proceeds if firm fails = | B76: =IF('Input sheet'!$B$54="B",('Input sheet'!$B$15+'Input sheet'!$B$16)*'Input sheet'!$B$55,'Valuation output'!B74*'Input sheet'!$B$55) -> 105316.77
A77: Value of operating assets = | B77: =B74*(1-B75)+B76*B75 -> 210633.55
A78: - Debt | B78: =IF('Input sheet'!$B$18="Yes",'Input sheet'!$B$16+'Operating lease converter'!$C$29,'Input sheet'!$B$16) -> 21361
A79: - Minority interests | B79: ='Input sheet'!$B$21 -> 0
A80: + Cash | B80: =IF('Input sheet'!$B$71="YES",'Input sheet'!$B$19-'Input sheet'!$B$72*('Input sheet'!$B$25-'Input sheet'!$B$73),'Input sheet'!$B$19) -> 6857.1 | D80: If you get Value Errors all over, it is usually because your option worksheet has gone haywire. The fix is very low tech. Go into the option value worksheet, and in cell B17 of that worksheet (adjusted S), enter any number (say 5) and then undo what you did. Voila!
A81: + Non-operating assets | B81: ='Input sheet'!$B$20 -> 4943.7
A82: Value of equity | B82: =B77-B78-B79+B80+B81 -> 201073.35
A83: - Value of options | B83: =IF('Input sheet'!$B$38="No",0,'Option value'!$B$30) -> 0
A84: Value of equity in common stock | B84: =B82-B83 -> 201073.35
A85: Number of shares | B85: ='Input sheet'!$B$22 -> 4416.8
A86: Estimated value /share | B86: =B84/B85 -> 45.524667
A87: Price | B87: ='Input sheet'!$B$23 -> 39.4
A88: Price as % of value | B88: =B87/B86 -> 0.86546487
A90: Implied variables | M90: After year 10
A91: Sales to capital ratio | C91: ='Input sheet'!$B$32 -> 0.8 | D91: ='Input sheet'!$B$32 -> 0.8 | E91: =D91 -> 0.8 | F91: =E91 -> 0.8 | G91: =F91 -> 0.8 | H91: ='Input sheet'!$B$33 -> 1.0697899 | I91: =H91 -> 1.0697899 | J91: =I91 -> 1.0697899 | K91: =J91 -> 1.0697899 | L91: =K91 -> 1.0697899
A92: Invested capital | B92: =IF('Input sheet'!$B$18="Yes",IF('Input sheet'!$B$17="Yes",'Input sheet'!$B$15+'Input sheet'!$B$16-'Input sheet'!$B$19+'Operating lease converter'!$F$34+'R& D converter'!$D$36,'Input sheet'!$B$15+'Input sheet'!$B$16-'Input sheet'!$B$19+'Operating lease converter'!$F$34),IF('Input sheet'!$B$17="Yes",'Input sheet'!$B$15+'Input sheet'!$B$16-'Input sheet'!$B$19+'R& D converter'!$D$36,'Input sheet'!$B$15+'Input sheet'!$B$16-'Input sheet'!$B$19)) -> 77987.21 | C92: =B92+C61 -> 78272.096 | D92: =C92+D61 -> 78558.348 | E92: =D92+E61 -> 78845.975 | F92: =E92+F61 -> 79134.983 | G92: =F92+G61 -> 79967.448 | H92: =G92+H61 -> 81009.484 | I92: =H92+I61 -> 82495.475 | J92: =I92+J61 -> 84462.137 | ... L92: =K92+L61 -> 89581.635
A93: ROIC | B93: =B60/B92 -> 0.23978897 | C93: =C60/B92 -> 0.23120477 | D93: =D60/C92 -> 0.23536753 | E93: =E60/D92 -> 0.23758702 | F93: =F60/E92 -> 0.23981027 | G93: =G60/F92 -> 0.24203725 | H93: =H60/G92 -> 0.24162894 | I93: =I60/H92 -> 0.24274424 | J93: =J60/I92 -> 0.24471186 | ... L93: =L60/K92 -> 0.251055 | M93: =IF('Input sheet'!$B$49="Yes",'Input sheet'!$B$50,'Valuation output'!L65) -> 0.0919
B95: Growth | C95: EBIT margin
A96: Conservador | B96: =MIN(B100:B102) -> 0.0487 | C96: =MIN(C100:C102) -> 0.402
A97: Base | B97: =MEDIAN(B100:B102) -> 0.19522 | C97: =MEDIAN(C100:C102) -> 0.42716
A98: Optimista | B98: =MAX(B100:B102) -> 0.2357 | C98: =MAX(C100:C102) -> 0.43216667
A100: LTM | B100: ='Income Statement'!$L$4 -> 0.0487 | C100: ='Income Statement'!$L$13 -> 0.402
A101: Promedio 3Y | B101: =AVERAGE('Income Statement'!$I$4:$K$4) -> 0.2357 | C101: =AVERAGE('Income Statement'!$I$13:$K$13) -> 0.43216667
A102: Promedio de 5Y | B102: =AVERAGE('Income Statement'!$G$4:$K$4) -> 0.19522 | C102: =AVERAGE('Income Statement'!$G$13:$K$13) -> 0.42716
A104: Modelo Optimista | B104: Optimista
B105: Base year | C105: 1 | D105: 2 | E105: 3 | F105: 4 | G105: 5 | H105: 6 | I105: 7 | J105: 8 | K105: 9 | L105: 10 | M105: Terminal year
A106: Revenue growth rate | B106: ='Input sheet'!B27 -> -0.04 | C106: ='Input sheet'!B27*1.3 -> -0.052 | D106: =C106 -> -0.052 | E106: =D106 -> -0.052 | F106: =E106 -> -0.052 | G106: =F106 -> -0.052 | H106: =G106-((G106-$M$4)/5) -> -0.03168 | I106: =G106-((G106-$M$4)/5)*2 -> -0.01136 | J106: =G106-((G106-$M$4)/5)*3 -> 0.00896 | K106: =G106-((G106-$M$4)/5)*4 -> 0.02928 | L106: =G106-((G106-$M$4)/5)*5 -> 0.0496 | M106: =IF('Input sheet'!B68="Yes",'Input sheet'!B69,IF('Input sheet'!B65="Yes",'Input sheet'!B66,'Input sheet'!B35)) -> 0.0496
A107: Revenues | B107: ='Input sheet'!$B$12 -> 47254.1 | C107: =B107*(1+C106) -> 44796.887 | D107: =C107*(1+D106) -> 42467.449 | E107: =D107*(1+E106) -> 40259.141 | F107: =E107*(1+F106) -> 38165.666 | G107: =F107*(1+G106) -> 36181.051 | H107: =G107*(1+H106) -> 35034.836 | I107: =H107*(1+I106) -> 34636.84 | J107: =I107*(1+J106) -> 34947.186 | ... M107: =L107*(1+M106) -> 39627.2
A108: EBIT (Operating) margin | B108: =B109/B107 -> 0.49498795 | C108: ='Input sheet'!B28 -> 0.47498795 | D108: =IF(D3>'Input sheet'!$B$31,$C$47,$C$47-(($C$47-$C$6)/'Input sheet'!$B$31)*('Input sheet'!$B$31-D3)) -> 0.48499277 | E108: =IF(E3>'Input sheet'!$B$31,$C$47,$C$47-(($C$47-$C$6)/'Input sheet'!$B$31)*('Input sheet'!$B$31-E3)) -> 0.48999518 | F108: =IF(F3>'Input sheet'!$B$31,$C$47,$C$47-(($C$47-$C$6)/'Input sheet'!$B$31)*('Input sheet'!$B$31-F3)) -> 0.49499759 | G108: =IF(G3>'Input sheet'!$B$31,$C$47,$C$47-(($C$47-$C$6)/'Input sheet'!$B$31)*('Input sheet'!$B$31-G3)) -> 0.5 | H108: =IF(H3>'Input sheet'!$B$31,$C$47,$C$47-(($C$47-$C$6)/'Input sheet'!$B$31)*('Input sheet'!$B$31-H3)) -> 0.5 | I108: =IF(I3>'Input sheet'!$B$31,$C$47,$C$47-(($C$47-$C$6)/'Input sheet'!$B$31)*('Input sheet'!$B$31-I3)) -> 0.5 | J108: =IF(J3>'Input sheet'!$B$31,$C$47,$C$47-(($C$47-$C$6)/'Input sheet'!$B$31)*('Input sheet'!$B$31-J3)) -> 0.5 | K108: =IF(K3>'Input sheet'!$B$31,$C$47,$C$47-(($C$47-$C$6)/'Input sheet'!$B$31)*('Input sheet'!$B$31-K3)) -> 0.5 | ... M108: =IF(M3>'Input sheet'!$B$31,$C$47,$C$47-(($C$47-$C$6)/'Input sheet'!$B$31)*('Input sheet'!$B$31-M3)) -> 0.5
A109: EBIT (Operating income) | B109: =IF('Input sheet'!$B$18="Yes",IF('Input sheet'!$B$17="Yes",'Input sheet'!$B$13+'Operating lease converter'!$F$33+'R& D converter'!$D$40,'Input sheet'!$B$13+'Operating lease converter'!$F$33),IF('Input sheet'!$B$17="Yes",'Input sheet'!$B$13+'R& D converter'!$D$40,'Input sheet'!$B$13)) -> 23390.21 | C109: =C108*C107 -> 21277.981 | D109: =D108*D107 -> 20596.406 | E109: =E108*E107 -> 19726.785 | F109: =F108*F107 -> 18891.913 | G109: =G108*G107 -> 18090.526 | H109: =H108*H107 -> 17517.418 | I109: =I108*I107 -> 17318.42 | J109: =J108*J107 -> 17473.593 | ... M109: =M108*M107 -> 19813.6 | N109: =M109-B109 -> -3576.6099
A110: Tax rate | B110: ='Input sheet'!$B$24 -> 0.2005 | C110: =B110 -> 0.2005 | D110: =C110 -> 0.2005 | E110: =D110 -> 0.2005 | F110: =E110 -> 0.2005 | G110: =F110 -> 0.2005 | H110: =G110+($M110-$G110)/5 -> 0.2044 | I110: =H110+($M110-$G110)/5 -> 0.2083 | J110: =I110+($M110-$G110)/5 -> 0.2122 | K110: =J110+($M110-$G110)/5 -> 0.2161 | L110: =K110+($M110-$G110)/5 -> 0.22 | M110: =IF('Input sheet'!$B$60="Yes",'Input sheet'!$B$24,'Input sheet'!$B$25) -> 0.22
A111: EBIT(1-t) | B111: =IF(B109>0,B109*(1-B110),B109) -> 18700.473 | C111: =IF(C109>0,IF(C109<B114,C109,C109-(C109-B114)*C110),C109) -> 17011.746 | D111: =IF(D109>0,IF(D109<C114,D109,D109-(D109-C114)*D110),D109) -> 16466.826 | E111: =IF(E109>0,IF(E109<D114,E109,E109-(E109-D114)*E110),E109) -> 15771.565 | F111: =IF(F109>0,IF(F109<E114,F109,F109-(F109-E114)*F110),F109) -> 15104.084 | G111: =IF(G109>0,IF(G109<F114,G109,G109-(G109-F114)*G110),G109) -> 14463.375 | H111: =IF(H109>0,IF(H109<G114,H109,H109-(H109-G114)*H110),H109) -> 13936.858 | I111: =IF(I109>0,IF(I109<H114,I109,I109-(I109-H114)*I110),I109) -> 13710.993 | J111: =IF(J109>0,IF(J109<I114,J109,J109-(J109-I114)*J110),J109) -> 13765.697 | ... L111: =IF(L109>0,IF(L109<K114,L109,L109-(L109-K114)*L110),L109) -> 14724.284 | M111: =M109*(1-M110) -> 15454.608
...

Sheet Cualitativo
A2: PERFIL CORPORATIVO & RESUMEN DE NEGOCIO
A4: 1. DATOS GENERALES DE LA EMPRESA
A5: Nombre de la Empresa | B5: Novo Nordisk A/S (CVR 24256790), Bagsværd, Dinamarca. Controlada por la Novo Nordisk Foundation vía Novo Holdings A/S (100% acciones A; 76,02% + 1,26% de los votos al 31-dic-2025).
A6: Director Ejecutivo (CEO) | B6: Maziar Mike Doustdar (presidente y CEO desde el 7-ago-2025). CFO: Karsten Munk Knudsen. Presidente del Consejo: Lars Rebien Sørensen (desde el 14-nov-2025).
A7: Sector Industrial | B7: Salud – Farmacéutica (diabetes, obesidad y enfermedades raras). Damodaran: Drugs (Pharmaceutical).
A8: Sitio Web Oficial | B8: https://www.novonordisk.com
A9: Ticker | B9: ='Input sheet'!A1 -> Novo Nordisk (NYSE:NVO) | C9: ='Input sheet'!D1 -> 39.4
A10: 2. DESCRIPCIÓN OPERATIVA Y SEGMENTOS DE NEGOCIO
A11: Segmento / Área | B11: Descripción (fuente: informe H1 2026 del 4-ago-2026 y 20-F 2025)
A12: Visión General de la Empresa | B12: Empresa farmacéutica fundada en 1923, líder en GLP-1 (semaglutida: Ozempic®, Wegovy®, Rybelsus®/Ozempic® pill) e insulinas. Ventas IFRS 2025: DKK 309.064 M (+6,4% DKK); margen operativo 41,3%; ~66.700 empleados y ventas en ~170 países. Reporta dos segmentos: Obesity & Diabetes care (94% de ventas ajustadas H1 2026) y Rare disease (6%).
A13: Obesity care (Wegovy®, Wegovy® pill, Saxenda®) | B13: Ventas ajustadas H1 2026 DKK 44.064 M (+19% TCC; 30% del total). Wegovy® inyectable 37.719 M (+7%), Wegovy® pill 5.474 M (lanzado en EE. UU. el 5-ene-2026). EE. UU. +6% TCC con precios a la baja; International Operations +40% TCC. Pacientes con productos de obesidad: 4,9 M (+69%).
A14: Diabetes care (GLP-1 e insulinas) | B14: Ventas ajustadas H1 2026 DKK 95.365 M (-5% TCC; 64% del total). GLP-1 diabetes 69.515 M (-5%; Ozempic® 59.200 M, -2%); insulinas 24.586 M (-7%) con pérdida de cuota en EE. UU. Patente de compuesto de semaglutida en EE. UU. hasta 2032; ANDAs de genéricos presentadas y litigadas.
A15: Rare disease (hemofilia, hormona de crecimiento) | B15: Ventas ajustadas H1 2026 DKK 9.122 M (+2% TCC). NovoSeven®, Alhemo®, Norditropin®, Sogroya®. Margen operativo del segmento H1 2026: 3,1% (afectado por deterioros de pipeline). Catalizadores: CHMP positivo para FREHEMGO® (denecimig) el 17-sep-2026; decisiones EE. UU./UE de denecimig en Q4 2026.
A16: Estrategia de Distribución y Comercialización | B16: Dos unidades: US Operations (51% de ventas ajustadas H1 2026) e International Operations (EUCAN, Emerging Markets, APAC, Region China). En EE. UU. amplía el canal de autopago (NovoCare® Pharmacy, telemedicina), Medicare Part D vía programa Bridge (desde 1-jul-2026) y acuerdo MFN con la Administración; precio de lista de Wegovy®/Ozempic® a USD 675 desde 1-ene-2027.
A18: ANÁLISIS DE PERSPECTIVAS: BULLS VS. BEARS
A20: PERSPECTIVA ALCISTA (BULLS SAY) - ARGUMENTOS A FAVOR
A21: Pilar / Tema
A22: Liderazgo en volumen de GLP-1 y nuevo formato oral | B22: Wegovy® sigue siendo líder en nuevos pacientes entre medicamentos de marca para obesidad en EE. UU.; Wegovy® pill superó 265.000 recetas semanales y 5 M de recetas acumuladas; aprobado por la EMA en julio de 2026 y lanzado en Reino Unido y EAU (informe H1 2026).
A23: Escala de manufactura, balance y caja | B23: Capacidad de API y llenado ampliada (capex 2025 DKK 60,1 mil M; plantas de Catalent); FCF H1 2026 DKK 55,3 mil M y guía 2026 DKK 45-55 mil M; ratings Aa3/AA; deuda neta DKK 86,5 mil M (≈0,6x EBITDA LTM ajustado).
A24: Opcionalidad de pipeline y mercado subpenetrado | B24: Mercado global de obesidad de marca creció 81% en volumen (MAT mayo-2026, IQVIA citado por la compañía). Pipeline: CagriSema (decisión EE. UU. Q4 2026), zenagamtide (fase 3), Wegovy® HD; objetivo CMD de >5 multi-blockbusters a 2030 y >DKK 150 mil M de ventas de pipeline en 2035 (ajustado por riesgo).
A26: PERSPECTIVA BAJISTA (BEARS SAY) - RIESGOS Y DESAFÍOS
A27: Pilar de Riesgo
A28: Precio neto en EE. UU. en caída estructural | B28: Ventas ajustadas en EE. UU. -4% TCC en H1 2026 por menores precios realizados; acuerdo MFN, cobertura Medicaid reducida y precio de lista de USD 675 desde 2027 (≈-50% Wegovy®, -35% Ozempic®).
A29: Competencia de Eli Lilly y ejecución del pipeline | B29: Tirzepatida superó a CagriSema en HbA1c (REIMAGINE 4); ZEUS falló su objetivo primario (31-jul-2026); monlunabant terminado (deterioro DKK 4,0 mil M). Novo demandó a Lilly por publicidad comparativa (21-jul-2026).
A30: Genéricos de semaglutida y retornos decrecientes sobre capital | B30: Expiración de la patente de semaglutida en algunos mercados de International Operations desde 2026 y en EE. UU. en 2032; demanda de Sandoz en el UPC contra la patente de la dosis de 1 mg (30-jun-2026). ROIC reportado 88,5% (2023) → 39,3% (2025) por capex y adquisiciones.
A32: Fuente: elaboración propia con documentos primarios de Novo Nordisk (informe H1 2026 del 4-ago-2026, 20-F 2025, Five-year overview AR2025, anuncios 6-K jul-sep 2026). No se usó informe de terceros para esta tabla.
A34: ACONTECIMIENTOS Y NOTICIAS RECIENTES
A35: Periodo del Reporte: 25 de junio de 2026 – 23 de septiembre de 2026 (90 días previos al corte)
A37: 1. RESUMEN DE TITULARES Y NOTICIAS CLAVE
A38: Categoría / Tema | B38: Titular | D38: Detalle Corto
A39: I+D / Pipeline | B39: ZEUS (ziltivekimab) no cumple el objetivo primario de MACE — 31-jul-2026 | D39: Posible deterioro no monetario en Q3 2026; reduce opcionalidad cardiovascular.
A40: Resultados | B40: Resultados H1 2026 y guía elevada — 4-ago-2026 | D40: Ventas ajustadas 2026: 0% a -6% TCC (antes -4% a -12%); FCF DKK 45-55 mil M.
A41: Regulatorio | B41: Aprobaciones EMA de Wegovy® pill y Wegovy® 7,2 mg — julio 2026 | D41: Amplía el formato oral y la dosis alta fuera de EE. UU.
A42: Estrategia | B42: Capital Markets Day: objetivos 2030 — 21-sep-2026 | D42: TCAC 2026-30 "en línea con pares", margen estable; el ADR cayó 7,96% ese día (USD 43,24 → 39,80).
A43: Legal / Patentes | B43: Litigios: Sandoz (UPC, 30-jun), demanda contra Lilly (21-jul), ANDA de Cipla | D43: Defensa de exclusividad de semaglutida y disputa comercial con Lilly.
A45: 2. ANÁLISIS Y DESARROLLO DETALLADO DE LOS EVENTOS
A46: Evento / Noticia
A47: ZEUS y terminación de monlunabant | B47: Ziltivekimab no redujo MACE vs placebo en >6.300 pacientes con ASCVD, ERC e inflamación (anuncio 31-jul-2026). En Q2 2026 se registraron deterioros de DKK 6,3 mil M en activos de pipeline, incluido monlunabant (DKK 4,0 mil M). Impacto negativo: reduce la diversificación fuera de GLP-1.
A48: Guía 2026 elevada (H1 2026) | B48: Ventas ajustadas Q2 2026 +7% TCC y beneficio operativo ajustado +11% TCC. Guía de ventas y beneficio operativo ajustados elevada a 0% a -6% TCC; FCF DKK 45-55 mil M; capex ~DKK 55 mil M; tasa fiscal 21-23%. Dividendo interino DKK 3,75. Impacto positivo moderado.
A49: Capital Markets Day 2026 | B49: Metas: >5 multi-blockbusters a 2030, >DKK 150 mil M en ventas de pipeline en 2035 (ajustado por riesgo), atender >60 M de pacientes en 2030, TCAC de ingresos 2026-30 en línea con pares y margen operativo ampliamente estable (GlobeNewswire, 21-sep-2026). El ADR cayó 7,96% ese día (stockanalysis). Impacto: aclara que no se espera expansión de margen.
A50: Recompra de acciones en curso | B50: Programa de hasta DKK 15 mil M (4-feb-2026 a 3-feb-2027): 34,17 M de acciones B recompradas a un promedio de DKK 281,79 hasta el 18-sep-2026; autocartera 48,2 M; 4.465 M de acciones totales (anuncio 21-sep-2026). Reducción neta de acciones ~1% anual.

Sheet Estadísticas
A1: =UPPER('Input sheet'!A1)&" | ESTADÍSTICAS Y MÉTRICAS FINANCIERAS (USD)" -> NOVO NORDISK (NYSE:NVO) | ESTADÍSTICAS Y MÉTRICAS FINANCIERAS (USD)
A3: PERFIL DE LA EMPRESA (PROFILE) | D3: VALORACIÓN TTM (VALUATION TTM) | G3: TASAS DE CRECIMIENTO ANUALIZADO (CAGR)
A4: Capitalización de Mercado (Market Cap) | B4: ='Trailing Valuation'!L5 -> 174021.92 | D4: P/E (Precio / Utilidad TTM) | E4: ='Trailing Valuation'!L13 -> 11.161473 | G4: Crec. Ingresos 3 Años (Rev 3Yr) | H4: 0.2317
A5: Valor de Empresa (EV) | B5: ='Trailing Valuation'!L6 -> 188525.82 | D5: P/B (Precio / Valor en Libros) | E5: ='Trailing Valuation'!L18 -> 5.159033 | G5: Crec. Ingresos 5 Años (Rev 5Yr) | H5: 0.1918
A6: Acciones en Circulación (Shares Out) | B6: ='Income Statement'!L27 -> 4416.8 | D6: EV/Sales (EV / Ventas TTM) | E6: ='Trailing Valuation'!L19 -> 3.9896183 | G6: Crec. Ingresos 10 Años (Rev 10Yr) | H6: 0.1128
A7: Ingresos Totales (Revenue TTM) | B7: ='Income Statement'!L3 -> 47254.1 | D7: EV/EBITDA TTM | E7: ='Trailing Valuation'!L21 -> 8.4742132 | G7: Crec. LPA Diluido 3 Años (Dil EPS 3Yr) | H7: 0.2634
A8: Número de Empleados | B8: 66700 | D8: P/FCF (Precio / Flujo de Caja Libre) | E8: ='Trailing Valuation'!L16 -> 14.697673 | G8: Crec. LPA Diluido 5 Años (Dil EPS 5Yr) | H8: 0.2036
D9: EV/Gross Profit (EV / Utilidad Bruta) | E9: ='Trailing Valuation'!L20 -> 5.0541489 | G9: Crec. LPA Diluido 10 Años (Dil EPS 10Yr) | H9: 0.1323
A10: MÁRGENES DE RENTABILIDAD (MARGINS) | G10: Crec. FCF 5 Años (FCF 5Yr) | H10: 0.0477
A11: Margen Bruto (Gross) | B11: ='Income Statement'!L7 -> 0.7894 | D11: VALORACIÓN PROYECTADA (VALUATION NTM) | G11: Crec. Acciones 5 Años (Shares 5Yr) | H11: -0.0101
A12: Margen EBITDA | B12: ='Income Statement'!L30 -> 0.47079513 | D12: Precio Objetivo (Price Target) | E12: ='Resumen de Valoración'!D12 -> 58.164425 | G12: Crec. Ingresos Proyectado 2 Años (Rev Fwd 2Yr) | H12: -0.0086
A13: Margen Operativo (Operating) | B13: ='Income Statement'!L13 -> 0.402 | D13: P/E Estimado (NTM) | E13: ='Input sheet'!D1/'Financials Multiples'!E72 -> 10.164196 | G13: Crec. EBITDA Proyectado 2 Años (EBITDA Fwd 2Yr) | H13: n.d.
A14: Margen Antes de Impuestos (Pre-Tax) | B14: ='Income Statement'!L19/'Income Statement'!L3 -> 0.4239484 | D14: PEG Ratio (P/E a Crecimiento) | E14: n.d. (crecimiento de BPA proyectado negativo) | G14: Crec. LPA Proyectado 2 Años (EPS Fwd 2Yr) | H14: -0.0269
A15: Margen Neto (Net) | B15: ='Income Statement'!L21/'Income Statement'!L3 -> 0.33187385 | D15: EV/Sales Estimado (NTM) | E15: =IFERROR('Trailing Valuation'!L6/'Financials Multiples'!E43,"") -> 4.2049458 | G15: Est. Crec. LPA a Largo Plazo (EPS LT Growth Est) | H15: n.d.
A16: Margen Flujo de Caja Libre (FCF) | B16: ='Cash Flow Statement'!L36/'Income Statement'!L3 -> 0.25056239 | D16: EV/EBITDA Estimado (NTM) | E16: ='Trailing Valuation'!L6/'Financials Multiples'!E57 -> 7.8724129
D17: P/FCF Estimado (NTM) | E17: =IFERROR('Trailing Valuation'!L5/('Financials Multiples'!E65-'Financials Multiples'!E60),"") -> 6.5044379 | G17: DIVIDENDOS (DIVIDENDS)
A18: RETORNOS PROMEDIO 5 AÑOS (RETURNS) | G18: Rendimiento por Dividendo (Yield) | H18: =Dividendos!K3 -> 0.046360406
A19: Retorno s/ Activos (ROA) | B19: ='Eficiencia de capital'!L4 -> 0.17810607 | D19: SALUD FINANCIERA (FINANCIAL HEALTH) | G19: Razón de Pago (Payout) | H19: =Dividendos!K5 -> 0.5174
A20: Retorno s/ Activos Totales (ROTA) | B20: =IFERROR(('Income Statement'!L12*(1-'Income Statement'!L29))/(('Balance Sheet'!L16+'Balance Sheet'!K16)/2),"") -> 0.1688697 | D20: Efectivo y Equivalentes (Cash) | E20: ='Balance Sheet'!L5 -> 6857.1 | G20: Dividendo por Acción (DPS) | H20: =Dividendos!K4 -> 1.8266
A21: Retorno s/ Patrimonio (ROE) | B21: ='Income Statement'!L22/AVERAGE('Balance Sheet'!L35,'Balance Sheet'!K35) -> 0.48810124 | D21: Deuda Neta (Net Debt) | E21: ='Balance Sheet'!L20+'Balance Sheet'!L21+'Balance Sheet'!L25+'Balance Sheet'!L26-'Balance Sheet'!L5 -> 14503.9 | G21: Crec. DPS 3 Años | H21: 0.2639
A22: Retorno s/ Capital Empleado (ROCE) | B22: ='Eficiencia de capital'!L7 -> 0.35931345 | D22: Deuda / Patrimonio (Debt/Equity) | E22: =IFERROR(('Balance Sheet'!L20+'Balance Sheet'!L21+'Balance Sheet'!L25+'Balance Sheet'!L26)/'Balance Sheet'!L35,"") -> 0.63326564 | G22: Crec. DPS 5 Años | H22: 0.2049
A23: Retorno s/ Capital Invertido (ROIC) | B23: ='Cash Flow Statement'!L37/('Balance Sheet'!L35+'Balance Sheet'!L20+'Balance Sheet'!L21+'Balance Sheet'!L25+'Balance Sheet'!L26-'Balance Sheet'!L5) -> 0.30826737 | D23: Cobertura de Intereses (EBIT/Interest) | E23: ='Income Statement'!L12/'Income Statement'!L15 -> 24.265202 | G23: Crec. DPS 10 Años | H23: 0.1403
G24: Crec. DPS Proyectado 2 Años (DPS Growth Fwd 2Yr) | H24: -0.0343
A26: Notas: LTM jun-26 ajustado (excluye reversión 340B y deterioros mayores). Empleados ≈66.700 (informe H1 2026). Tasas H: USD; 10 años = 2015-2025. Proyecciones = consenso stockanalysis (23-sep-2026) en DKK; n.d. = no disponible en la fuente.

Sheet Income Statement
A1: ='Input sheet'!A1 -> Novo Nordisk (NYSE:NVO) | C1: Precio | D1: ='Input sheet'!D1 -> 39.4
A2: Income Statement | B2: Dec '16 | C2: Dec '17 | D2: Dec '18 | E2: Dec '19 | F2: Dec '20 | G2: Dec '21 | H2: Dec '22 | I2: Dec '23 | J2: Dec '24 | K2: Dec '25 | L2: LTM jun-26 (aj.) | M2: Dec '26 (E)
A3: Total Revenues | B3: 16610.1 | C3: 16928.1 | D3: 17702.3 | E3: 18293.3 | F3: 19421.4 | G3: 22379.1 | H3: 24990.8 | I3: 33697.5 | J3: 42130.2 | K3: 46702.4 | L3: 47254.1
A4: Total Revenues %Chg | B4: 0.0354 | C4: 0.0191 | D4: 0.0457 | E4: 0.0334 | F4: 0.0617 | G4: 0.1523 | H4: 0.1167 | I4: 0.3484 | J4: 0.2502 | K4: 0.1085 | L4: 0.0487
A5: Cost of Sales | B5: 2553.3 | C5: 2672.2 | D5: 2788.7 | E5: 3011.6 | F5: 3202.4 | G5: 3760.3 | H5: 4017.6 | I5: 5189 | J5: 6459 | K5: 8883.4 | L5: 9952.9
A6: Gross Profit | B6: 14056.8 | C6: 14255.9 | D6: 14913.6 | E6: 15281.7 | F6: 16219 | G6: 18618.8 | H6: 20973.2 | I6: 28508.6 | J6: 35671.2 | K6: 37819 | L6: 37301.2
A7: Gross Profit Margin | B7: 0.8463 | C7: 0.8421 | D7: 0.8425 | E7: 0.8354 | F7: 0.8351 | G7: 0.832 | H7: 0.8392 | I7: 0.846 | J7: 0.8467 | K7: 0.8098 | L7: 0.7894
A8: Selling, General & Administrative Expenses | B8: 4805.5 | C8: 4868.6 | D8: 5273.3 | E8: 5371.6 | F8: 5643.2 | G8: 6525.8 | H8: 7158 | I8: 8936.9 | J8: 9774.7 | K8: 10619.8 | L8: 10123.2
A9: Depreciation & Amortization Expenses | B9: 0 | C9: 0 | D9: 0 | E9: 0 | F9: 0 | G9: 0 | H9: 0 | I9: 0 | J9: 0 | K9: 0 | L9: 0
A10: Research & Development Expenses | B10: 2164 | C10: 2123.9 | D10: 2343.6 | E10: 2131.9 | F10: 2365.5 | G10: 2824.7 | H10: 3396.1 | I10: 4707 | J10: 6972.6 | K10: 7863.6 | L10: 8084.7
A11: Other Operating Expenses | B11: -109.5 | C11: -157.8 | D11: -182.4 | E11: -90 | F11: -70.4 | G11: -52.8 | H11: -146 | I11: -17.3 | J11: 305.1 | K11: 45.3 | L11: 98.5
A12: Operating Profit | B12: 7196.8 | C12: 7421.2 | D12: 7479.1 | E12: 7868.2 | F12: 8280.7 | G12: 9321 | H12: 10565.1 | I12: 14881.9 | J12: 18618.8 | K12: 19290.3 | L12: 18994.8
A13: Operating Margin | B13: 0.4333 | C13: 0.4384 | D13: 0.4225 | E13: 0.4301 | F13: 0.4264 | G13: 0.4165 | H13: 0.4228 | I13: 0.4416 | J13: 0.4419 | K13: 0.413 | L13: 0.402
A14: Interest and Investment Income | B14: 16.9 | C14: 15.3 | D14: 8.1 | E14: 9.7 | F14: 51.6 | G14: 36.7 | H14: 33.8 | I14: 155.1 | J14: 266.6 | K14: 191.8 | L14: 122.9
A15: Interest Expense | B15: 9.8 | C15: 13.2 | D15: 14.1 | E15: 33 | F15: 59.7 | G15: 45.9 | H15: 53.4 | I15: 78.6 | J15: 237.9 | K15: 635.7 | L15: 782.8
A16: Interest Expense, Net | B16: =B14-B15 -> 7.1 | C16: =C14-C15 -> 2.1 | D16: =D14-D15 -> -6 | E16: =E14-E15 -> -23.3 | F16: =F14-F15 -> -8.1 | G16: =G14-G15 -> -9.2 | H16: =H14-H15 -> -19.6 | I16: =I14-I15 -> 76.5 | ... M16: =M14-M15 -> 0
A17: Non-Operating Income | B17: -101.3 | C17: -45.6 | D17: 64.1 | E17: -565.9 | F17: -144.3 | G17: 78.5 | H17: -792 | I17: 228.2 | J17: -195.3 | K17: 879.5 | L17: 1698.5
A18: Total Non-Operating Income | B18: -94.2 | C18: -43.5 | D18: 58.1 | E18: -589.2 | F18: -152.4 | G18: 69.3 | H18: -811.6 | I18: 304.7 | J18: -166.5 | K18: 435.5 | L18: 1038.5
A19: Income Before Provision for Income Taxes | B19: 7102.6 | C19: 7377.7 | D19: 7537.2 | E19: 7279 | F19: 8128.3 | G19: 9390.3 | H19: 9753.5 | I19: 15186.6 | J19: 18452.2 | K19: 19725.8 | L19: 20033.3
A20: Provision for Income Taxes | B20: 1467.1 | C20: 1598.9 | D20: 1422.6 | E20: 1439.5 | F20: 1681.7 | G20: 1799.7 | H20: 1911.8 | I20: 3045.5 | J20: 3801.4 | K20: 4247.1 | L20: 4350.9
A21: Consolidated Net Income | B21: 5635.5 | C21: 5778.8 | D21: 6114.6 | E21: 5839.5 | F21: 6446.7 | G21: 7590.6 | H21: 7841.7 | I21: 12141.1 | J21: 14650.8 | K21: 15478.7 | L21: 15682.4
A22: Net Income Attributable to Common Shareholders | B22: 5635.5 | C22: 5778.8 | D22: 6114.6 | E22: 5839.5 | F22: 6446.7 | G22: 7590.6 | H22: 7841.7 | I22: 12141.1 | J22: 14650.8 | K22: 15478.7 | L22: 15682.4
A23: Basic EPS | B23: 1.114 | C23: 1.168 | D23: 1.263 | E23: 1.23 | F23: 1.381 | G23: 1.653 | H23: 1.731 | I23: 2.709 | J23: 3.289 | K23: 3.485 | L23: 3.534
A24: Diluted EPS | B24: 1.112 | C24: 1.166 | D24: 1.261 | E24: 1.228 | F24: 1.378 | G24: 1.648 | H24: 1.726 | I24: 2.701 | J24: 3.283 | K24: 3.48 | L24: 3.53
A25: Basic Weighted Average Shares Outstanding | B25: 5060 | C25: 4945.5 | D25: 4840.6 | E25: 4748.6 | F25: 4667.8 | G25: 4593.2 | H25: 4530.6 | I25: 4482.8 | J25: 4453.9 | K25: 4443 | L25: 4438.2
A26: Diluted Weighted Average Shares Outstanding | B26: 5070.2 | C26: 4955.2 | D26: 4849.7 | E26: 4757.4 | F26: 4680 | G26: 4606.2 | H26: 4544.6 | I26: 4494.8 | J26: 4463 | K26: 4447.7 | L26: 4442.2
A27: Shares Outstanding | B27: 5060 | C27: 4945.5 | D27: 4840.6 | E27: 4748.6 | F27: 4667.8 | G27: 4593.2 | H27: 4530.6 | I27: 4482.8 | J27: 4453.9 | K27: 4443 | L27: 4416.8
A28: EBITDA | B28: 7671.3 | C28: 7903.4 | D28: 8100.4 | E28: 8716.9 | F28: 9160.9 | G28: 10278.6 | H28: 11604.8 | I28: 16247.6 | J28: 21390.7 | K28: 22612 | L28: 22247
A29: Effective Tax Rate | B29: 0.2066 | C29: 0.2167 | D29: 0.1887 | E29: 0.1978 | F29: 0.2069 | G29: 0.1917 | H29: 0.196 | I29: 0.2005 | J29: 0.206 | K29: 0.2153 | L29: 0.2172
A30: EBITDA Margin | B30: =B28/B3 -> 0.4618455 | C30: =C28/C3 -> 0.46688051 | D30: =D28/D3 -> 0.45759026 | E30: =E28/E3 -> 0.47650779 | F30: =F28/F3 -> 0.47169102 | G30: =G28/G3 -> 0.45929461 | H30: =H28/H3 -> 0.46436289 | I30: =I28/I3 -> 0.4821604 | ... L30: =L28/L3 -> 0.47079513

Sheet Balance Sheet
A1: ='Input sheet'!A1 -> Novo Nordisk (NYSE:NVO) | C1: Precio | D1: ='Input sheet'!D1 -> 39.4
A2: Assets | B2: Dec '16 | C2: Dec '17 | D2: Dec '18 | E2: Dec '19 | F2: Dec '20 | G2: Dec '21 | H2: Dec '22 | I2: Dec '23 | J2: Dec '24 | K2: Dec '25 | L2: LTM jun-26 (aj.) | M2: Dec '26 (E)
A3: Cash and Cash Equivalents | B3: 2650 | C3: 3036.9 | D3: 2397.9 | E3: 2326.8 | F3: 2103.8 | G3: 1632.7 | H3: 1814.8 | I3: 2133.8 | J3: 2180.8 | K3: 4163.3 | L3: 6780.9
A4: Short-Term Investments | B4: 284.8 | C4: 0 | D4: 0 | E4: 0 | F4: 0 | G4: 1030.3 | H4: 1566.4 | I4: 2348.2 | J4: 1484 | K4: 78.3 | L4: 76.2
A5: Total Cash and Cash Equivalents | B5: 2934.8 | C5: 3036.9 | D5: 2397.9 | E5: 2326.8 | F5: 2103.8 | G5: 2663.1 | H5: 3381.2 | I5: 4482 | J5: 3664.8 | K5: 4241.6 | L5: 6857.1
A6: Accounts Receivable | B6: 2868.9 | C6: 3248.4 | D6: 3493.9 | E6: 3745.7 | F6: 4573.7 | G6: 6190.1 | H6: 7251.7 | I6: 9603.1 | J6: 10022.8 | K6: 11147 | L6: 13559.4
A7: Other Receivables | B7: 561.9 | C7: 545.5 | D7: 629.1 | E7: 637.5 | F7: 733.9 | G7: 937.6 | H7: 996.1 | I7: 1555.4 | J7: 2278.5 | K7: 2883.7 | L7: 2982.2
A8: Total Trade Receivables | B8: 3430.8 | C8: 3793.8 | D8: 4123 | E8: 4383.2 | F8: 5307.6 | G8: 7127.7 | H8: 8247.8 | I8: 11158.5 | J8: 12301.2 | K8: 14030.7 | L8: 16541.6
A9: Other Current Assets | B9: 2108.4 | C9: 2847.6 | D9: 2536.2 | E9: 2680.7 | F9: 3441.4 | G9: 3245.8 | H9: 3889 | I9: 5064 | J9: 6571.7 | K9: 8857.8 | L9: 8415
A10: Total Current Assets | B10: 8474 | C10: 9678.3 | D10: 9057.1 | E10: 9390.8 | F10: 10852.7 | G10: 13036.5 | H10: 15518 | I10: 20704.5 | J10: 22537.7 | K10: 27130.1 | L10: 31813.7
A11: Net Property, Plant & Equipment | B11: 4279 | C11: 5677.9 | D11: 6423.4 | E11: 7600.7 | F11: 8290 | G11: 8431.9 | H11: 9562.5 | I11: 13486.3 | J11: 22522.6 | K11: 32781.8 | L11: 35329.3
A12: Net Intangible Assets | B12: 384.8 | C12: 535.6 | D12: 788.9 | E12: 877.3 | F12: 3406.6 | G12: 5913.2 | H12: 6644.1 | I12: 8294.2 | J12: 12649.3 | K12: 17337.8 | L12: 15574.4
A13: Goodwill | B13: 0 | C13: 0 | D13: 0 | E13: 0 | F13: 0 | G13: 661.9 | H13: 661.9 | I13: 661.9 | J13: 2788.4 | K13: 3122 | L13: 3032
A14: Long-Term Investments | B14: 311.5 | C14: 283.8 | D14: 271.9 | E14: 271.8 | F14: 271.8 | G14: 219.5 | H14: 192.6 | I14: 246.6 | J14: 372.9 | K14: 394.4 | L14: 355.2
... A16: Total Assets | B16: 13829.7 | C16: 16488.4 | D16: 16984.8 | E16: 18886.8 | F16: 23899.5 | G16: 29624.5 | H16: 34602.9 | I16: 46627.1 | J16: 64864 | K16: 85408.8 | L16: 90693
A17: Liabilities | M17: Dec '26 (E)
A18: Accounts Payable | B18: 852.3 | C18: 903.7 | D18: 1035.9 | E18: 956 | F18: 942.8 | G18: 1350.9 | H18: 2235.6 | I18: 3796.5 | J18: 2387.7 | K18: 3108.3 | L18: 2224.3
A19: Accrued Expenses | B19: 2010.7 | C19: 2327.1 | D19: 2161.7 | E19: 2268.2 | F19: 2804.3 | G19: 2985.2 | H19: 3385.8 | I19: 4255.9 | J19: 4927.5 | K19: 6248.9 | L19: 5850.1
A20: Short-Term Debt | B20: 32.5 | C20: 272.9 | D20: 79 | E20: 221.6 | F20: 1102.3 | G20: 1958.9 | H20: 68.8 | I20: 786.4 | J20: 1640.3 | K20: 1680.3 | L20: 2591
A21: Current Portion of Leases | B21: 0 | C21: 0 | D21: 0 | E21: 0 | F21: 127.8 | G21: 125.2 | H21: 141.4 | I21: 174.1 | J21: 186.4 | K21: 210.2 | L21: 203.7
A22: Unearned Revenue | B22: 0 | C22: 0 | D22: 0 | E22: 0 | F22: 0 | G22: 0 | H22: 0 | I22: 0 | J22: 0 | K22: 0 | L22: 0
A23: Other Current Liabilities | B23: 3830.4 | C23: 4076.5 | D23: 5028.6 | E23: 5422.8 | F23: 6611.7 | G23: 8736.5 | H23: 11514.5 | I23: 16141 | J23: 21172.6 | K23: 22679.9 | L23: 25576.9
A24: Total Current Liabilities | B24: 6725.8 | C24: 7580.3 | D24: 8305.2 | E24: 8868.6 | F24: 11588.9 | G24: 15156.8 | H24: 17346.1 | I24: 25153.8 | J24: 30314.5 | K24: 33927.6 | L24: 36445.9
A25: Long-Term Debt | B25: 0 | C25: 0 | D25: 0 | E25: 0 | F25: 0 | G25: 1470.4 | H25: 2979.7 | I25: 2368.7 | J25: 11735.8 | K25: 17573.3 | L25: 17455.6
A26: Leases | B26: 0 | C26: 0 | D26: 0 | E26: 452.4 | F26: 477.8 | G26: 503.7 | H26: 508.2 | I26: 674.9 | J26: 756.1 | K26: 1138.4 | L26: 1110.7
A27: Other Long-Term Liabilities | B27: 685.4 | C27: 883.4 | D27: 730.8 | E27: 906.2 | F27: 1389.7 | G27: 1718.8 | H27: 1794.7 | I27: 2630.5 | J27: 2069.5 | K27: 2242.3 | L27: 1949.3
A28: Total Long-Term Liabilities | B28: 685.4 | C28: 883.4 | D28: 730.8 | E28: 1358.6 | F28: 1867.5 | G28: 3692.8 | H28: 5282.6 | I28: 5674.1 | J28: 14561.4 | K28: 20953.9 | L28: 20515.6
A29: Total Liabilities | B29: 7411.2 | C29: 8463.7 | D29: 9036 | E29: 10227.2 | F29: 13456.4 | G29: 18849.6 | H29: 22628.7 | I29: 30827.9 | J29: 44875.9 | K29: 54881.5 | L29: 56961.5
A30: Equity | M30: Dec '26 (E)
A31: Additional Paid-in Capital | B31: 71 | C31: 78.8 | D31: 73.4 | E31: 70.7 | F31: 76.2 | G31: 69.5 | H31: 64.5 | I31: 66.1 | J31: 61.9 | K31: 69.8 | L31: 67.4
A32: Accumulated Other Comprehensive Income | B32: -190.4 | C32: 56.2 | D32: -313.7 | E32: -104.3 | F32: -150.2 | G32: -261.1 | H32: 351.3 | I32: 189.2 | J32: -195.9 | K32: -266.7 | L32: -507.5
A33: Retained Earnings | B33: 6537.9 | C33: 7889.7 | D33: 8189 | E33: 8693.3 | F33: 10517.2 | G33: 10966.6 | H33: 11558.4 | I33: 15543.9 | J33: 20122.2 | K33: 30724.1 | L33: 34171.6
A34: Total Common Shareholders' Equity | B34: 6418.5 | C34: 8024.7 | D34: 7948.7 | E34: 8659.6 | F34: 10443.1 | G34: 10775 | H34: 11974.2 | I34: 15799.2 | J34: 19988.1 | K34: 30527.3 | L34: 33731.5
A35: Total Shareholders' Equity | B35: 6418.5 | C35: 8024.7 | D35: 7948.7 | E35: 8659.6 | F35: 10443.1 | G35: 10775 | H35: 11974.2 | I35: 15799.2 | J35: 19988.1 | K35: 30527.3 | L35: 33731.5
A36: Total Liabilities and Shareholders' Equity | B36: 13829.7 | C36: 16488.4 | D36: 16984.8 | E36: 18886.8 | F36: 23899.5 | G36: 29624.5 | H36: 34602.9 | I36: 46627.1 | J36: 64864 | K36: 85408.8 | L36: 90693

Sheet Cash Flow Statement
A1: ='Input sheet'!A1 -> Novo Nordisk (NYSE:NVO) | C1: Precio | D1: ='Input sheet'!D1 -> 39.4
A2: Operating Activities | B2: Dec '16 | C2: Dec '17 | D2: Dec '18 | E2: Dec '19 | F2: Dec '20 | G2: Dec '21 | H2: Dec '22 | I2: Dec '23 | J2: Dec '24 | K2: Dec '25 | L2: LTM jun-26 (aj.) | M2: Dec '26 (E)
A3: Net Income | B3: 5635.5 | C3: 5778.8 | D3: 6114.6 | E3: 5839.5 | F3: 6446.7 | G3: 7590.6 | H3: 7841.7 | I3: 12141.1 | J3: 14650.8 | K3: 15478.7 | L3: 18179.5
A4: Depreciation & Amortization | B4: 474.5 | C4: 482.2 | D4: 621.3 | E4: 848.7 | F4: 880.1 | G4: 957.6 | H4: 1039.7 | I4: 1365.7 | J4: 2771.9 | K4: 3321.7 | L4: 3252.2
A5: Share-Based Compensation Expense | E5: 54.4 | F5: 125.9 | G5: 165.3 | H5: 217.3 | I5: 311.8 | J5: 332.1 | K5: 216.8 | L5: 151.8
A6: Other Adjustments | B6: 33 | C6: -241.4 | D6: 425.8 | E6: 669.1 | F6: 694.6 | G6: 1661.6 | H6: 2066.6 | I6: 2874.7 | J6: -736.8 | K6: -1647.2 | L6: -1210.7
A7: Changes in Trade Receivables | E7: -318.7 | F7: -431.7 | G7: -2051.8 | H7: -1400.6 | I7: -2061.7 | J7: -1041.5 | K7: 165.2
A8: Changes in Accounts Payable | E8: -59.7 | F8: -98.1 | G8: 501.1 | H8: 948.6 | I8: 1092.3 | J8: 727 | K8: 395.6
A9: Changes in Accrued Expenses | E9: 180.2 | F9: 194.9 | G9: 412.5 | H9: 565.8 | I9: 788.7 | J9: 1344 | K9: 657.2
A10: Changes in Income Taxes Payable | B10: 1036.3 | C10: 219.6 | D10: -99.3 | E10: -200 | F10: 135.5 | G10: -495.1 | H10: -138.1 | I10: -711.8 | J10: -498 | K10: -590.5 | L10: 217
A11: Changes in Unearned Revenue | B11: 0 | C11: 0 | D11: 0 | E11: 0 | F11: 0 | G11: 0 | H11: 0 | I11: 0 | J11: 0 | K11: 0 | L11: 0
A12: Changes in Other Operating Activities | B12: 0 | C12: 0 | D12: 0 | E12: 0 | F12: 0 | G12: 0 | H12: 0 | I12: 0 | J12: 0 | K12: 0 | L12: 0
A13: Cash from Operating Activities | B13: 7179.3 | C13: 6239.2 | D13: 7062.5 | E13: 7013.5 | F13: 7948 | G13: 8741.8 | H13: 11141 | I13: 15800.9 | J13: 17549.4 | K13: 17997.4 | L13: 20589.8
A14: Investing Activities | M14: Dec '26 (E)
A15: Capital Expenditure | B15: -1050.3 | C15: -1155.8 | D15: -1525.3 | E15: -1339.1 | F15: -891.2 | G15: -1006.9 | H15: -1715.4 | I15: -3744.1 | J15: -6842.3 | K15: -9087.7 | L15: -8749.6
A16: Proceeds from Sale of Property, Plant & Equipment | B16: 1 | C16: 1.4 | D16: 2.1 | E16: 0.6 | F16: 1.1 | G16: 0 | H16: 0 | I16: 0 | J16: 0 | K16: 0 | L16: 0
A17: Purchases of Investments | B17: -78.9 | C17: 0 | D17: 0 | E17: 0 | F17: 0 | G17: -1129.9 | H17: -1351 | I17: -1888.7 | J17: -2760.5 | K17: -75.3 | L17: 0
A18: Proceeds from Sale of Investments | B18: 306.7 | C18: 304.5 | D18: 0 | E18: 0 | F18: 0 | G18: 186.3 | H18: 938.5 | I18: 1198.4 | J18: 0 | K18: 0 | L18: 0
A19: Payments for Business Acquisitions | B19: 0 | C19: 0 | D19: 0 | E19: 0 | F19: 0 | G19: -2905.9 | H19: -999.2 | I19: 0 | J19: -11919.8 | K19: 0 | L19: 0
A20: Proceeds from Business Divestments | B20: 0 | C20: 0 | D20: 0 | E20: 0 | F20: 0 | G20: 0 | H20: 0 | I20: 0 | J20: 0 | K20: 0 | L20: 0
A21: Other Investing Activities | B21: -187.5 | C21: -145.9 | D21: -388.9 | E21: -386.9 | F21: -2542.4 | G21: -166.9 | H21: -392 | I21: -1933.7 | J21: 2823.2 | K21: -2798.5 | L21: -4292.5
A22: Cash from Investing Activities | B22: -1009 | C22: -995.9 | D22: -1912.2 | E22: -1725.4 | F22: -3432.5 | G22: -5023.4 | H22: -3519.1 | I22: -6368.1 | J22: -18699.4 | K22: -11961.5 | L22: -13042.1
A23: Financing Activities | M23: Dec '26 (E)
A24: Issuance of Short-Term Debt | B24: 0 | C24: 0 | D24: 0 | E24: 0 | F24: 0 | G24: 0 | H24: 0 | I24: 0 | J24: 0 | K24: 0 | L24: 0
A25: Net Issuance / (Repayments) of Short-Term Debt | B25: 0 | C25: 0 | D25: 0 | E25: 0 | F25: 0 | G25: 0 | H25: 0 | I25: 0 | J25: 0 | K25: 0 | L25: 0
A26: Issuance of Long-Term Debt | B26: 0 | C26: 0 | D26: 14.9 | E26: 12.1 | F26: 869.3 | G26: 3522.2 | H26: 1583.9 | I26: 0 | J26: 11517.6 | K26: 15704.9 | L26: 10317
A27: Repayments of Long-Term Debt | B27: 0 | C27: 0 | D27: 0 | E27: -123.2 | F27: -145.3 | G27: -1063.2 | H27: -1923.9 | I27: -212.8 | J27: -919.1 | K27: -11966 | L27: -4628
A28: Net Issuance / (Repayments) of Long-Term Debt | B28: 0 | C28: 0 | D28: 14.9 | E28: -111.1 | F28: 723.9 | G28: 2459 | H28: -340.1 | I28: -212.8 | J28: 10598.6 | K28: 3738.9 | L28: 5689
A29: Issuance of Common Shares | B29: 0 | C29: 0 | D29: 0 | E29: 0 | F29: 0 | G29: 0 | H29: 0 | I29: 0 | J29: 0 | K29: 0 | L29: 0
A30: Repurchases of Common Shares | B30: -2237.4 | C30: -2552.9 | D30: -2464.2 | E30: -2298.9 | F30: -2578.6 | G30: -3090.9 | H30: -3401.6 | I30: -4341.5 | J30: -2927.8 | K30: -209.7 | L30: -921
A31: Net Issuance / (Repurchases) of Common Shares | B31: -2237.4 | C31: -2552.9 | D31: -2464.2 | E31: -2298.9 | F31: -2578.6 | G31: -3090.9 | H31: -3401.6 | I31: -4341.5 | J31: -2927.8 | K31: -209.7 | L31: -921
A32: Common Share Dividends Paid | B32: -3541.1 | C32: -2855.9 | D32: -3015.2 | E32: -2909.8 | F32: -3078.3 | G32: -3420 | H32: -3573.5 | I32: -4608.9 | J32: -6403.6 | K32: -7821.9 | L32: -8114.5
A33: Other Financing Activities | B33: 0 | C33: 0 | D33: 0 | E33: 0 | F33: 0 | G33: 0 | H33: 0 | I33: 0 | J33: 0 | K33: 0 | L33: -126
A34: Cash from Financing Activities | B34: -5778.5 | C34: -5408.8 | D34: -5464.5 | E34: -5319.7 | F34: -4933 | G34: -4051.9 | H34: -7315.2 | I34: -9163.3 | J34: 1267.2 | K34: -4292.7 | L34: -3472.5
A35: Free Cash Flow | M35: Dec '26 (E)
A36: Free Cash Flow | B36: 6129 | C36: 5083.5 | D36: 5537.2 | E36: 5674.4 | F36: 7056.8 | G36: 7734.9 | H36: 9425.7 | I36: 12056.8 | J36: 10707.1 | K36: 8909.7 | L36: 11840.1
A37: NOPAT | B37: 5710.3 | C37: 5812.9 | D37: 6067.5 | E37: 6312.2 | F37: 6567.5 | G37: 7534.6 | H37: 8494.2 | I37: 11897.6 | J37: 14783.1 | K37: 15137 | L37: 14869.4
A38: Levered Free Cash Flow | B38: 6129 | C38: 5083.5 | D38: 5537.2 | E38: 5674.4 | F38: 7056.8 | G38: 7734.9 | H38: 9425.7 | I38: 12056.8 | J38: 10707.1 | K38: 8909.7 | L38: 11840.1
A39: Unlevered Free Cash Flow | B39: 6136.8 | C39: 5093.8 | D39: 5548.6 | E39: 5700.9 | F39: 7104.1 | G39: 7772.1 | H39: 9468.6 | I39: 12119.7 | J39: 10896 | K39: 9408.5 | L39: 12452.9
A40: Net Change in Cash | B40: 391.8 | C40: -165.5 | D40: -314.2 | E40: -31.6 | F40: -417.5 | G40: -333.5 | H40: 306.7 | I40: 269.6 | J40: 117.2 | K40: 1743.2 | L40: 4075.1

Sheet Trailing Valuation
A1: ='Input sheet'!A1 -> Novo Nordisk (NYSE:NVO) | C1: Precio | D1: ='Input sheet'!D1 -> 39.4
A2: Trailing Valuation | B2: Dec '16 | C2: Dec '17 | D2: Dec '18 | E2: Dec '19 | F2: Dec '20 | G2: Dec '21 | H2: Dec '22 | I2: Dec '23 | J2: Dec '24 | K2: Dec '25 | L2: LTM
A3: Stock Price | B3: 18.08 | C3: 26.98 | D3: 22.85 | E3: 29.09 | F3: 35.21 | G3: 56.05 | H3: 67.27 | I3: 103.49 | J3: 86.93 | K3: 51.13 | L3: ='Input sheet'!D1 -> 39.4
A4: Total Shares Outstanding | B4: =IFERROR('Income Statement'!B27,"") -> 5060 | C4: =IFERROR('Income Statement'!C27,"") -> 4945.5 | D4: =IFERROR('Income Statement'!D27,"") -> 4840.6 | E4: =IFERROR('Income Statement'!E27,"") -> 4748.6 | F4: =IFERROR('Income Statement'!F27,"") -> 4667.8 | G4: =IFERROR('Income Statement'!G27,"") -> 4593.2 | H4: =IFERROR('Income Statement'!H27,"") -> 4530.6 | I4: =IFERROR('Income Statement'!I27,"") -> 4482.8 | ... L4: =IFERROR('Income Statement'!L27,"") -> 4416.8
A5: Market Cap | B5: =IFERROR(B3*B4,"") -> 91484.8 | C5: =IFERROR(C3*C4,"") -> 133429.59 | D5: =IFERROR(D3*D4,"") -> 110607.71 | E5: =IFERROR(E3*E4,"") -> 138136.77 | F5: =IFERROR(F3*F4,"") -> 164353.24 | G5: =IFERROR(G3*G4,"") -> 257448.86 | H5: =IFERROR(H3*H4,"") -> 304773.46 | I5: =IFERROR(I3*I4,"") -> 463924.97 | ... L5: =IFERROR(L3*L4,"") -> 174021.92
A6: Total Enterprise Value (TEV) | B6: =IFERROR(B5+('Balance Sheet'!B20+'Balance Sheet'!B21+'Balance Sheet'!B25+'Balance Sheet'!B26)-'Balance Sheet'!B5,"") -> 88582.5 | C6: =IFERROR(C5+('Balance Sheet'!C20+'Balance Sheet'!C21+'Balance Sheet'!C25+'Balance Sheet'!C26)-'Balance Sheet'!C5,"") -> 130665.59 | D6: =IFERROR(D5+('Balance Sheet'!D20+'Balance Sheet'!D21+'Balance Sheet'!D25+'Balance Sheet'!D26)-'Balance Sheet'!D5,"") -> 108288.81 | E6: =IFERROR(E5+('Balance Sheet'!E20+'Balance Sheet'!E21+'Balance Sheet'!E25+'Balance Sheet'!E26)-'Balance Sheet'!E5,"") -> 136483.97 | F6: =IFERROR(F5+('Balance Sheet'!F20+'Balance Sheet'!F21+'Balance Sheet'!F25+'Balance Sheet'!F26)-'Balance Sheet'!F5,"") -> 163957.34 | G6: =IFERROR(G5+('Balance Sheet'!G20+'Balance Sheet'!G21+'Balance Sheet'!G25+'Balance Sheet'!G26)-'Balance Sheet'!G5,"") -> 258843.96 | H6: =IFERROR(H5+('Balance Sheet'!H20+'Balance Sheet'!H21+'Balance Sheet'!H25+'Balance Sheet'!H26)-'Balance Sheet'!H5,"") -> 305090.36 | I6: =IFERROR(I5+('Balance Sheet'!I20+'Balance Sheet'!I21+'Balance Sheet'!I25+'Balance Sheet'!I26)-'Balance Sheet'!I5,"") -> 463447.07 | ... L6: =IFERROR(L5+('Balance Sheet'!L20+'Balance Sheet'!L21+'Balance Sheet'!L25+'Balance Sheet'!L26)-'Balance Sheet'!L5,"") -> 188525.82
A7: Dividend Yield | B7: =IFERROR(-'Cash Flow Statement'!B32/B5,"") -> 0.038706976 | C7: =IFERROR(-'Cash Flow Statement'!C32/C5,"") -> 0.021403798 | D7: =IFERROR(-'Cash Flow Statement'!D32/D5,"") -> 0.027260306 | E7: =IFERROR(-'Cash Flow Statement'!E32/E5,"") -> 0.02106463 | F7: =IFERROR(-'Cash Flow Statement'!F32/F5,"") -> 0.01872978 | G7: =IFERROR(-'Cash Flow Statement'!G32/G5,"") -> 0.013284192 | H7: =IFERROR(-'Cash Flow Statement'!H32/H5,"") -> 0.011725102 | I7: =IFERROR(-'Cash Flow Statement'!I32/I5,"") -> 0.0099345805 | ... L7: =IFERROR(-'Cash Flow Statement'!L32/L5,"") -> 0.046629183
A8: Buyback Yield | B8: =IFERROR(-'Cash Flow Statement'!B30/B5,"") -> 0.024456522 | C8: =IFERROR(-'Cash Flow Statement'!C30/C5,"") -> 0.019132937 | D8: =IFERROR(-'Cash Flow Statement'!D30/D5,"") -> 0.022278736 | E8: =IFERROR(-'Cash Flow Statement'!E30/E5,"") -> 0.016642201 | F8: =IFERROR(-'Cash Flow Statement'!F30/F5,"") -> 0.015689378 | G8: =IFERROR(-'Cash Flow Statement'!G30/G5,"") -> 0.01200588 | H8: =IFERROR(-'Cash Flow Statement'!H30/H5,"") -> 0.011161077 | I8: =IFERROR(-'Cash Flow Statement'!I30/I5,"") -> 0.0093581942 | ... L8: =IFERROR(-'Cash Flow Statement'!L30/L5,"") -> 0.0052924367
A9: Debt Paydown Yield | B9: =IFERROR(-'Cash Flow Statement'!B28/B5,"") -> 0 | C9: =IFERROR(-'Cash Flow Statement'!C28/C5,"") -> 0 | D9: =IFERROR(-'Cash Flow Statement'!D28/D5,"") -> -0.00013471032 | E9: =IFERROR(-'Cash Flow Statement'!E28/E5,"") -> 0.00080427533 | F9: =IFERROR(-'Cash Flow Statement'!F28/F5,"") -> -0.0044045375 | G9: =IFERROR(-'Cash Flow Statement'!G28/G5,"") -> -0.0095514115 | H9: =IFERROR(-'Cash Flow Statement'!H28/H5,"") -> 0.0011159108 | I9: =IFERROR(-'Cash Flow Statement'!I28/I5,"") -> 0.00045869486 | ... L9: =IFERROR(-'Cash Flow Statement'!L28/L5,"") -> -0.032691284
A10: Shareholder Yield | B10: =IFERROR(B7+B8+B9,"") -> 0.063163498 | C10: =IFERROR(C7+C8+C9,"") -> 0.040536736 | D10: =IFERROR(D7+D8+D9,"") -> 0.049404332 | E10: =IFERROR(E7+E8+E9,"") -> 0.038511106 | F10: =IFERROR(F7+F8+F9,"") -> 0.03001462 | G10: =IFERROR(G7+G8+G9,"") -> 0.01573866 | H10: =IFERROR(H7+H8+H9,"") -> 0.02400209 | I10: =IFERROR(I7+I8+I9,"") -> 0.01975147 | ... L10: =IFERROR(L7+L8+L9,"") -> 0.019230336
A11: P/S | B11: =IFERROR(B5/'Income Statement'!B3,"") -> 5.5077814 | C11: =IFERROR(C5/'Income Statement'!C3,"") -> 7.8821362 | D11: =IFERROR(D5/'Income Statement'!D3,"") -> 6.2482112 | E11: =IFERROR(E5/'Income Statement'!E3,"") -> 7.5512223 | F11: =IFERROR(F5/'Income Statement'!F3,"") -> 8.4624815 | G11: =IFERROR(G5/'Income Statement'!G3,"") -> 11.503986 | H11: =IFERROR(H5/'Income Statement'!H3,"") -> 12.195426 | I11: =IFERROR(I5/'Income Statement'!I3,"") -> 13.767341 | ... L11: =IFERROR(L5/'Income Statement'!L3,"") -> 3.682684
A12: P/Gross Profit | B12: =IFERROR(B5/'Income Statement'!B6,"") -> 6.5082238 | C12: =IFERROR(C5/'Income Statement'!C6,"") -> 9.3596048 | D12: =IFERROR(D5/'Income Statement'!D6,"") -> 7.4165668 | E12: =IFERROR(E5/'Income Statement'!E6,"") -> 9.0393591 | F12: =IFERROR(F5/'Income Statement'!F6,"") -> 10.133377 | G12: =IFERROR(G5/'Income Statement'!G6,"") -> 13.827361 | H12: =IFERROR(H5/'Income Statement'!H6,"") -> 14.531567 | I12: =IFERROR(I5/'Income Statement'!I6,"") -> 16.273159 | ... L12: =IFERROR(L5/'Income Statement'!L6,"") -> 4.6653169
A13: P/E | B13: =IFERROR(B3/'Income Statement'!B24,"") -> 16.258993 | C13: =IFERROR(C3/'Income Statement'!C24,"") -> 23.138937 | D13: =IFERROR(D3/'Income Statement'!D24,"") -> 18.120539 | E13: =IFERROR(E3/'Income Statement'!E24,"") -> 23.688925 | F13: =IFERROR(F3/'Income Statement'!F24,"") -> 25.551524 | G13: =IFERROR(G3/'Income Statement'!G24,"") -> 34.010922 | H13: =IFERROR(H3/'Income Statement'!H24,"") -> 38.974508 | I13: =IFERROR(I3/'Income Statement'!I24,"") -> 38.315439 | ... L13: =IFERROR(L3/'Income Statement'!L24,"") -> 11.161473
A14: Earnings Yield | B14: =IFERROR('Income Statement'!B22/B5,"") -> 0.061600397 | C14: =IFERROR('Income Statement'!C22/C5,"") -> 0.043309734 | D14: =IFERROR('Income Statement'!D22/D5,"") -> 0.055281861 | E14: =IFERROR('Income Statement'!E22/E5,"") -> 0.04227332 | F14: =IFERROR('Income Statement'!F22/F5,"") -> 0.039224661 | G14: =IFERROR('Income Statement'!G22/G5,"") -> 0.029483914 | H14: =IFERROR('Income Statement'!H22/H5,"") -> 0.025729602 | I14: =IFERROR('Income Statement'!I22/I5,"") -> 0.026170396 | ... L14: =IFERROR('Income Statement'!L22/L5,"") -> 0.090117383
A15: P/OCF | B15: =IFERROR(B5/'Cash Flow Statement'!B13,"") -> 12.742858 | C15: =IFERROR(C5/'Cash Flow Statement'!C13,"") -> 21.385689 | D15: =IFERROR(D5/'Cash Flow Statement'!D13,"") -> 15.661269 | E15: =IFERROR(E5/'Cash Flow Statement'!E13,"") -> 19.69584 | F15: =IFERROR(F5/'Cash Flow Statement'!F13,"") -> 20.678565 | G15: =IFERROR(G5/'Cash Flow Statement'!G13,"") -> 29.450326 | H15: =IFERROR(H5/'Cash Flow Statement'!H13,"") -> 27.356024 | I15: =IFERROR(I5/'Cash Flow Statement'!I13,"") -> 29.360668 | ... L15: =IFERROR(L5/'Cash Flow Statement'!L13,"") -> 8.4518509
A16: P/FCF | B16: =IFERROR(B5/'Cash Flow Statement'!B36,"") -> 14.926546 | C16: =IFERROR(C5/'Cash Flow Statement'!C36,"") -> 26.247583 | D16: =IFERROR(D5/'Cash Flow Statement'!D36,"") -> 19.975386 | E16: =IFERROR(E5/'Cash Flow Statement'!E36,"") -> 24.343856 | F16: =IFERROR(F5/'Cash Flow Statement'!F36,"") -> 23.290052 | G16: =IFERROR(G5/'Cash Flow Statement'!G36,"") -> 33.284058 | H16: =IFERROR(H5/'Cash Flow Statement'!H36,"") -> 32.334305 | I16: =IFERROR(I5/'Cash Flow Statement'!I36,"") -> 38.478284 | ... L16: =IFERROR(L5/'Cash Flow Statement'!L36,"") -> 14.697673
A17: FCF Yield | B17: =IFERROR('Cash Flow Statement'!B36/B5,"") -> 0.066994736 | C17: =IFERROR('Cash Flow Statement'!C36/C5,"") -> 0.038098746 | D17: =IFERROR('Cash Flow Statement'!D36/D5,"") -> 0.05006161 | E17: =IFERROR('Cash Flow Statement'!E36/E5,"") -> 0.041078127 | F17: =IFERROR('Cash Flow Statement'!F36/F5,"") -> 0.042936787 | G17: =IFERROR('Cash Flow Statement'!G36/G5,"") -> 0.030044413 | H17: =IFERROR('Cash Flow Statement'!H36/H5,"") -> 0.030926905 | I17: =IFERROR('Cash Flow Statement'!I36/I5,"") -> 0.025988685 | ... L17: =IFERROR('Cash Flow Statement'!L36/L5,"") -> 0.068037981
A18: P/B | B18: =IFERROR(B5/'Balance Sheet'!B35,"") -> 14.253299 | C18: =IFERROR(C5/'Balance Sheet'!C35,"") -> 16.627362 | D18: =IFERROR(D5/'Balance Sheet'!D35,"") -> 13.915195 | E18: =IFERROR(E5/'Balance Sheet'!E35,"") -> 15.951865 | F18: =IFERROR(F5/'Balance Sheet'!F35,"") -> 15.737974 | G18: =IFERROR(G5/'Balance Sheet'!G35,"") -> 23.893166 | H18: =IFERROR(H5/'Balance Sheet'!H35,"") -> 25.452511 | I18: =IFERROR(I5/'Balance Sheet'!I35,"") -> 29.363827 | ... L18: =IFERROR(L5/'Balance Sheet'!L35,"") -> 5.159033
A19: EV/Sales | B19: =IFERROR(B6/'Income Statement'!B3,"") -> 5.3330504 | C19: =IFERROR(C6/'Income Statement'!C3,"") -> 7.7188574 | D19: =IFERROR(D6/'Income Statement'!D3,"") -> 6.117217 | E19: =IFERROR(E6/'Income Statement'!E3,"") -> 7.4608722 | F19: =IFERROR(F6/'Income Statement'!F3,"") -> 8.4420968 | G19: =IFERROR(G6/'Income Statement'!G3,"") -> 11.566326 | H19: =IFERROR(H6/'Income Statement'!H3,"") -> 12.208107 | I19: =IFERROR(I6/'Income Statement'!I3,"") -> 13.753159 | ... L19: =IFERROR(L6/'Income Statement'!L3,"") -> 3.9896183
A20: EV/Gross Profit | B20: =IFERROR(B6/'Income Statement'!B6,"") -> 6.3017543 | C20: =IFERROR(C6/'Income Statement'!C6,"") -> 9.1657202 | D20: =IFERROR(D6/'Income Statement'!D6,"") -> 7.2610778 | E20: =IFERROR(E6/'Income Statement'!E6,"") -> 8.9312036 | F20: =IFERROR(F6/'Income Statement'!F6,"") -> 10.108967 | G20: =IFERROR(G6/'Income Statement'!G6,"") -> 13.90229 | H20: =IFERROR(H6/'Income Statement'!H6,"") -> 14.546677 | I20: =IFERROR(I6/'Income Statement'!I6,"") -> 16.256395 | ... L20: =IFERROR(L6/'Income Statement'!L6,"") -> 5.0541489
A21: EV/EBITDA | B21: =IFERROR(B6/'Income Statement'!B28,"") -> 11.547261 | C21: =IFERROR(C6/'Income Statement'!C28,"") -> 16.532833 | D21: =IFERROR(D6/'Income Statement'!D28,"") -> 13.368329 | E21: =IFERROR(E6/'Income Statement'!E28,"") -> 15.657398 | F21: =IFERROR(F6/'Income Statement'!F28,"") -> 17.897514 | G21: =IFERROR(G6/'Income Statement'!G28,"") -> 25.182803 | H21: =IFERROR(H6/'Income Statement'!H28,"") -> 26.290015 | I21: =IFERROR(I6/'Income Statement'!I28,"") -> 28.524033 | ... L21: =IFERROR(L6/'Income Statement'!L28,"") -> 8.4742132
A22: EV/EBIT | B22: =IFERROR(B6/'Income Statement'!B12,"") -> 12.308595 | C22: =IFERROR(C6/'Income Statement'!C12,"") -> 17.60707 | D22: =IFERROR(D6/'Income Statement'!D12,"") -> 14.478856 | E22: =IFERROR(E6/'Income Statement'!E12,"") -> 17.346277 | F22: =IFERROR(F6/'Income Statement'!F12,"") -> 19.799937 | G22: =IFERROR(G6/'Income Statement'!G12,"") -> 27.769977 | H22: =IFERROR(H6/'Income Statement'!H12,"") -> 28.877186 | I22: =IFERROR(I6/'Income Statement'!I12,"") -> 31.14166 | ... L22: =IFERROR(L6/'Income Statement'!L12,"") -> 9.9251279
A23: EV/OCF | B23: =IFERROR(B6/'Cash Flow Statement'!B13,"") -> 12.338598 | C23: =IFERROR(C6/'Cash Flow Statement'!C13,"") -> 20.942683 | D23: =IFERROR(D6/'Cash Flow Statement'!D13,"") -> 15.332929 | E23: =IFERROR(E6/'Cash Flow Statement'!E13,"") -> 19.46018 | F23: =IFERROR(F6/'Cash Flow Statement'!F13,"") -> 20.628754 | G23: =IFERROR(G6/'Cash Flow Statement'!G13,"") -> 29.609916 | H23: =IFERROR(H6/'Cash Flow Statement'!H13,"") -> 27.384468 | I23: =IFERROR(I6/'Cash Flow Statement'!I13,"") -> 29.330422 | ... L23: =IFERROR(L6/'Cash Flow Statement'!L13,"") -> 9.1562725
A24: EV/FCF | B24: =IFERROR(B6/'Cash Flow Statement'!B36,"") -> 14.45301 | C24: =IFERROR(C6/'Cash Flow Statement'!C36,"") -> 25.703863 | D24: =IFERROR(D6/'Cash Flow Statement'!D36,"") -> 19.556601 | E24: =IFERROR(E6/'Cash Flow Statement'!E36,"") -> 24.052582 | F24: =IFERROR(F6/'Cash Flow Statement'!F36,"") -> 23.23395 | G24: =IFERROR(G6/'Cash Flow Statement'!G36,"") -> 33.464422 | H24: =IFERROR(H6/'Cash Flow Statement'!H36,"") -> 32.367926 | I24: =IFERROR(I6/'Cash Flow Statement'!I36,"") -> 38.438646 | ... L24: =IFERROR(L6/'Cash Flow Statement'!L36,"") -> 15.922654

Sheet Forward Valuation
A1: ='Input sheet'!A1 -> Novo Nordisk (NYSE:NVO) | C1: Precio | D1: ='Input sheet'!D1 -> 39.4
A2: orward Valuation | B2: Dec '16 | C2: Dec '17 | D2: Nov '18 | E2: Nov '19 | F2: Nov '20 | G2: Dec '21 | H2: Dec '22 | I2: Dec '23 | J2: Nov '24 | K2: Nov '25 | L2: NTM | M2: FY2026E (consenso) | N2: FY2027E (consenso)
A3: Forward P/S | M3: ='Input sheet'!D1*'Income Statement'!L27/(299756.8/6.5512) -> 3.8032578 | N3: ='Input sheet'!D1*'Income Statement'!L27/(303762.8/6.5512) -> 3.7531008
A4: Forward P/E | M4: ='Input sheet'!D1/(21.57638/6.5512) -> 11.962956 | N4: ='Input sheet'!D1/(21.80626/6.5512) -> 11.836843
A5: Forward Earnings Yield | M5: =1/M4 -> 0.083591381 | N5: =1/N4 -> 0.084481984
A6: Forward P/OCF | M6: n.d. | N6: n.d.
A7: Forward P/FCF | M7: n.d. | N7: n.d.
A8: Forward FCF Yield | M8: n.d. | N8: n.d.
A9: Forward EV/Sales | M9: ='Trailing Valuation'!L6/(299756.8/6.5512) -> 4.1202413 | N9: ='Trailing Valuation'!L6/(303762.8/6.5512) -> 4.0659039
A10: Forward EV/EBITDA | M10: n.d. | N10: n.d.
A11: Forward EV/EBIT | M11: n.d. | N11: n.d.
A12: Forward EV/OCF | M12: n.d. | N12: n.d.
A13: Forward EV/FCF | M13: n.d. | N13: n.d.
A15: Fuente: consenso publicado por stockanalysis.com (27 analistas ingresos / 21 BPA para 2026), consultado 23-sep-2026, en DKK convertido a USD al tipo BCE del 23-sep-2026 (6,5512 DKK/USD). El consenso mezcla definiciones (con/sin reversión 340B). Filas sin consenso disponible: n.d.

Sheet Dividendos
A1: ='Input sheet'!A1 -> Novo Nordisk (NYSE:NVO) | C1: Precio | D1: ='Input sheet'!D1 -> 39.4
A2: Dividends | B2: Dec '17 | C2: Dec '18 | D2: Dec '19 | E2: Dec '20 | F2: Dec '21 | G2: Dec '22 | H2: Dec '23 | I2: Dec '24 | J2: Dec '25 | K2: LTM jun-26 (aj.)
A3: Dividend Yield | B3: 0.022 | C3: 0.0282 | D3: 0.0215 | E3: 0.0198 | F3: 0.0147 | G3: 0.013 | H3: 0.0132 | I3: 0.019 | J3: 0.0346 | K3: =K4/'Input sheet'!D1 -> 0.046360406
A4: DPS | B4: 0.5949 | C4: 0.6451 | D4: 0.6259 | E4: 0.6961 | F4: 0.8265 | G4: 0.8756 | H4: 1.3638 | I4: 1.6539 | J4: 1.768 | K4: 1.8266
A5: Payout Ratio | B5: 0.5101 | C5: 0.5116 | D5: 0.5098 | E5: 0.5053 | F5: 0.5014 | G5: 0.5074 | H5: 0.5048 | I5: 0.5038 | J5: 0.508 | K5: 0.5174

Sheet Márgenes
A1: ='Input sheet'!A1 -> Novo Nordisk (NYSE:NVO) | C1: Precio | D1: ='Input sheet'!D1 -> 39.4
A2: Margins | B2: Dec '16 | C2: Dec '17 | D2: Nov '18 | E2: Nov '19 | F2: Nov '20 | G2: Dec '21 | H2: Dec '22 | I2: Dec '23 | J2: Nov '24 | K2: Nov '25 | L2: LTM
A3: Gross Profit Margin | B3: =IFERROR('Income Statement'!B7,"") -> 0.8463 | C3: =IFERROR('Income Statement'!C7,"") -> 0.8421 | D3: =IFERROR('Income Statement'!D7,"") -> 0.8425 | E3: =IFERROR('Income Statement'!E7,"") -> 0.8354 | F3: =IFERROR('Income Statement'!F7,"") -> 0.8351 | G3: =IFERROR('Income Statement'!G7,"") -> 0.832 | H3: =IFERROR('Income Statement'!H7,"") -> 0.8392 | I3: =IFERROR('Income Statement'!I7,"") -> 0.846 | ... L3: =IFERROR('Income Statement'!L7,"") -> 0.7894
A4: Operating Margin | B4: =IFERROR('Income Statement'!B13,"") -> 0.4333 | C4: =IFERROR('Income Statement'!C13,"") -> 0.4384 | D4: =IFERROR('Income Statement'!D13,"") -> 0.4225 | E4: =IFERROR('Income Statement'!E13,"") -> 0.4301 | F4: =IFERROR('Income Statement'!F13,"") -> 0.4264 | G4: =IFERROR('Income Statement'!G13,"") -> 0.4165 | H4: =IFERROR('Income Statement'!H13,"") -> 0.4228 | I4: =IFERROR('Income Statement'!I13,"") -> 0.4416 | ... L4: =IFERROR('Income Statement'!L13,"") -> 0.402
A5: EBITDA Margin | B5: =IFERROR('Income Statement'!B30,"") -> 0.4618455 | C5: =IFERROR('Income Statement'!C30,"") -> 0.46688051 | D5: =IFERROR('Income Statement'!D30,"") -> 0.45759026 | E5: =IFERROR('Income Statement'!E30,"") -> 0.47650779 | F5: =IFERROR('Income Statement'!F30,"") -> 0.47169102 | G5: =IFERROR('Income Statement'!G30,"") -> 0.45929461 | H5: =IFERROR('Income Statement'!H30,"") -> 0.46436289 | I5: =IFERROR('Income Statement'!I30,"") -> 0.4821604 | ... L5: =IFERROR('Income Statement'!L30,"") -> 0.47079513
A6: Net Profit Margin | B6: =IFERROR('Income Statement'!B22/'Income Statement'!B3,"") -> 0.33928152 | C6: =IFERROR('Income Statement'!C22/'Income Statement'!C3,"") -> 0.34137322 | D6: =IFERROR('Income Statement'!D22/'Income Statement'!D3,"") -> 0.34541274 | E6: =IFERROR('Income Statement'!E22/'Income Statement'!E3,"") -> 0.31921523 | F6: =IFERROR('Income Statement'!F22/'Income Statement'!F3,"") -> 0.33193797 | G6: =IFERROR('Income Statement'!G22/'Income Statement'!G3,"") -> 0.33918254 | H6: =IFERROR('Income Statement'!H22/'Income Statement'!H3,"") -> 0.31378347 | I6: =IFERROR('Income Statement'!I22/'Income Statement'!I3,"") -> 0.36029676 | ... L6: =IFERROR('Income Statement'!L22/'Income Statement'!L3,"") -> 0.33187385
A7: Effective Tax Rate | B7: =IFERROR('Income Statement'!B29,"") -> 0.2066 | C7: =IFERROR('Income Statement'!C29,"") -> 0.2167 | D7: =IFERROR('Income Statement'!D29,"") -> 0.1887 | E7: =IFERROR('Income Statement'!E29,"") -> 0.1978 | F7: =IFERROR('Income Statement'!F29,"") -> 0.2069 | G7: =IFERROR('Income Statement'!G29,"") -> 0.1917 | H7: =IFERROR('Income Statement'!H29,"") -> 0.196 | I7: =IFERROR('Income Statement'!I29,"") -> 0.2005 | ... L7: =IFERROR('Income Statement'!L29,"") -> 0.2172
A8: Pre-Tax Profit Margin | B8: =IFERROR('Income Statement'!B19/'Income Statement'!B3,"") -> 0.4276073 | C8: =IFERROR('Income Statement'!C19/'Income Statement'!C3,"") -> 0.43582564 | D8: =IFERROR('Income Statement'!D19/'Income Statement'!D3,"") -> 0.42577518 | E8: =IFERROR('Income Statement'!E19/'Income Statement'!E3,"") -> 0.39790524 | F8: =IFERROR('Income Statement'!F19/'Income Statement'!F3,"") -> 0.41852287 | G8: =IFERROR('Income Statement'!G19/'Income Statement'!G3,"") -> 0.41960132 | H8: =IFERROR('Income Statement'!H19/'Income Statement'!H3,"") -> 0.39028362 | I8: =IFERROR('Income Statement'!I19/'Income Statement'!I3,"") -> 0.45067438 | ... L8: =IFERROR('Income Statement'!L19/'Income Statement'!L3,"") -> 0.4239484
A9: Free Cash Flow Margin | B9: =IFERROR('Cash Flow Statement'!B36/'Income Statement'!B3,"") -> 0.36899236 | C9: =IFERROR('Cash Flow Statement'!C36/'Income Statement'!C3,"") -> 0.3002995 | D9: =IFERROR('Cash Flow Statement'!D36/'Income Statement'!D3,"") -> 0.31279551 | E9: =IFERROR('Cash Flow Statement'!E36/'Income Statement'!E3,"") -> 0.31019007 | F9: =IFERROR('Cash Flow Statement'!F36/'Income Statement'!F3,"") -> 0.36335177 | G9: =IFERROR('Cash Flow Statement'!G36/'Income Statement'!G3,"") -> 0.34563052 | H9: =IFERROR('Cash Flow Statement'!H36/'Income Statement'!H3,"") -> 0.3771668 | I9: =IFERROR('Cash Flow Statement'!I36/'Income Statement'!I3,"") -> 0.35779509 | ... L9: =IFERROR('Cash Flow Statement'!L36/'Income Statement'!L3,"") -> 0.25056239
A10: OCF / Sales | B10: =IFERROR('Cash Flow Statement'!B13/'Income Statement'!B3,"") -> 0.43222497 | C10: =IFERROR('Cash Flow Statement'!C13/'Income Statement'!C3,"") -> 0.3685706 | D10: =IFERROR('Cash Flow Statement'!D13/'Income Statement'!D3,"") -> 0.39895946 | E10: =IFERROR('Cash Flow Statement'!E13/'Income Statement'!E3,"") -> 0.38339173 | F10: =IFERROR('Cash Flow Statement'!F13/'Income Statement'!F3,"") -> 0.40923929 | G10: =IFERROR('Cash Flow Statement'!G13/'Income Statement'!G3,"") -> 0.39062339 | H10: =IFERROR('Cash Flow Statement'!H13/'Income Statement'!H3,"") -> 0.44580406 | I10: =IFERROR('Cash Flow Statement'!I13/'Income Statement'!I3,"") -> 0.46890422 | ... L10: =IFERROR('Cash Flow Statement'!L13/'Income Statement'!L3,"") -> 0.43572515
A11: OCF / Net Income | B11: =IFERROR('Cash Flow Statement'!B13/'Income Statement'!B22,"") -> 1.273942 | C11: =IFERROR('Cash Flow Statement'!C13/'Income Statement'!C22,"") -> 1.0796705 | D11: =IFERROR('Cash Flow Statement'!D13/'Income Statement'!D22,"") -> 1.1550224 | E11: =IFERROR('Cash Flow Statement'!E13/'Income Statement'!E22,"") -> 1.2010446 | F11: =IFERROR('Cash Flow Statement'!F13/'Income Statement'!F22,"") -> 1.2328788 | G11: =IFERROR('Cash Flow Statement'!G13/'Income Statement'!G22,"") -> 1.1516613 | H11: =IFERROR('Cash Flow Statement'!H13/'Income Statement'!H22,"") -> 1.4207379 | I11: =IFERROR('Cash Flow Statement'!I13/'Income Statement'!I22,"") -> 1.3014389 | ... L11: =IFERROR('Cash Flow Statement'!L13/'Income Statement'!L22,"") -> 1.312924
A12: FCF / OCF | B12: =IFERROR('Cash Flow Statement'!B36/'Cash Flow Statement'!B13,"") -> 0.8537044 | C12: =IFERROR('Cash Flow Statement'!C36/'Cash Flow Statement'!C13,"") -> 0.81476792 | D12: =IFERROR('Cash Flow Statement'!D36/'Cash Flow Statement'!D13,"") -> 0.78402832 | E12: =IFERROR('Cash Flow Statement'!E36/'Cash Flow Statement'!E13,"") -> 0.80906823 | F12: =IFERROR('Cash Flow Statement'!F36/'Cash Flow Statement'!F13,"") -> 0.88787116 | G12: =IFERROR('Cash Flow Statement'!G36/'Cash Flow Statement'!G13,"") -> 0.88481777 | H12: =IFERROR('Cash Flow Statement'!H36/'Cash Flow Statement'!H13,"") -> 0.84603716 | I12: =IFERROR('Cash Flow Statement'!I36/'Cash Flow Statement'!I13,"") -> 0.76304514 | ... L12: =IFERROR('Cash Flow Statement'!L36/'Cash Flow Statement'!L13,"") -> 0.57504687
A13: FCF / Net Income | B13: =IFERROR('Cash Flow Statement'!B36/'Income Statement'!B22,"") -> 1.0875699 | C13: =IFERROR('Cash Flow Statement'!C36/'Income Statement'!C22,"") -> 0.8796809 | D13: =IFERROR('Cash Flow Statement'!D36/'Income Statement'!D22,"") -> 0.90557027 | E13: =IFERROR('Cash Flow Statement'!E36/'Income Statement'!E22,"") -> 0.97172703 | F13: =IFERROR('Cash Flow Statement'!F36/'Income Statement'!F22,"") -> 1.0946376 | G13: =IFERROR('Cash Flow Statement'!G36/'Income Statement'!G22,"") -> 1.0190104 | H13: =IFERROR('Cash Flow Statement'!H36/'Income Statement'!H22,"") -> 1.201997 | I13: =IFERROR('Cash Flow Statement'!I36/'Income Statement'!I22,"") -> 0.99305664 | ... L13: =IFERROR('Cash Flow Statement'!L36/'Income Statement'!L22,"") -> 0.75499286
A14: FCF / EBITDA | B14: =IFERROR('Cash Flow Statement'!B36/'Income Statement'!B28,"") -> 0.79895194 | C14: =IFERROR('Cash Flow Statement'!C36/'Income Statement'!C28,"") -> 0.64320419 | D14: =IFERROR('Cash Flow Statement'!D36/'Income Statement'!D28,"") -> 0.68357118 | E14: =IFERROR('Cash Flow Statement'!E36/'Income Statement'!E28,"") -> 0.65096537 | F14: =IFERROR('Cash Flow Statement'!F36/'Income Statement'!F28,"") -> 0.77031733 | G14: =IFERROR('Cash Flow Statement'!G36/'Income Statement'!G28,"") -> 0.75252466 | H14: =IFERROR('Cash Flow Statement'!H36/'Income Statement'!H28,"") -> 0.81222425 | I14: =IFERROR('Cash Flow Statement'!I36/'Income Statement'!I28,"") -> 0.74206652 | ... L14: =IFERROR('Cash Flow Statement'!L36/'Income Statement'!L28,"") -> 0.53221108

Sheet Eficiencia de capital
A1: ='Input sheet'!A1 -> Novo Nordisk (NYSE:NVO) | B1: ='Input sheet'!B1 -> 0 | C1: Precio | D1: ='Input sheet'!D1 -> 39.4
A2: Capital Efficiency | B2: Dec '16 | C2: Dec '17 | D2: Nov '18 | E2: Nov '19 | F2: Nov '20 | G2: Dec '21 | H2: Dec '22 | I2: Dec '23 | J2: Nov '24 | K2: Nov '25 | L2: LTM
A3: Return on Invested Capital | C3: =IFERROR('Cash Flow Statement'!C37/((('Balance Sheet'!C20+'Balance Sheet'!C21+'Balance Sheet'!C25+'Balance Sheet'!C26+'Balance Sheet'!C35-'Balance Sheet'!C5)+('Balance Sheet'!B20+'Balance Sheet'!B21+'Balance Sheet'!B25+'Balance Sheet'!B26+'Balance Sheet'!B35-'Balance Sheet'!B5))/2),"") -> 1.3245907 | D3: =IFERROR('Cash Flow Statement'!D37/((('Balance Sheet'!D20+'Balance Sheet'!D21+'Balance Sheet'!D25+'Balance Sheet'!D26+'Balance Sheet'!D35-'Balance Sheet'!D5)+('Balance Sheet'!C20+'Balance Sheet'!C21+'Balance Sheet'!C25+'Balance Sheet'!C26+'Balance Sheet'!C35-'Balance Sheet'!C5))/2),"") -> 1.1142739 | E3: =IFERROR('Cash Flow Statement'!E37/((('Balance Sheet'!E20+'Balance Sheet'!E21+'Balance Sheet'!E25+'Balance Sheet'!E26+'Balance Sheet'!E35-'Balance Sheet'!E5)+('Balance Sheet'!D20+'Balance Sheet'!D21+'Balance Sheet'!D25+'Balance Sheet'!D26+'Balance Sheet'!D35-'Balance Sheet'!D5))/2),"") -> 0.99903455 | F3: =IFERROR('Cash Flow Statement'!F37/((('Balance Sheet'!F20+'Balance Sheet'!F21+'Balance Sheet'!F25+'Balance Sheet'!F26+'Balance Sheet'!F35-'Balance Sheet'!F5)+('Balance Sheet'!E20+'Balance Sheet'!E21+'Balance Sheet'!E25+'Balance Sheet'!E26+'Balance Sheet'!E35-'Balance Sheet'!E5))/2),"") -> 0.77020054 | G3: =IFERROR('Cash Flow Statement'!G37/((('Balance Sheet'!G20+'Balance Sheet'!G21+'Balance Sheet'!G25+'Balance Sheet'!G26+'Balance Sheet'!G35-'Balance Sheet'!G5)+('Balance Sheet'!F20+'Balance Sheet'!F21+'Balance Sheet'!F25+'Balance Sheet'!F26+'Balance Sheet'!F35-'Balance Sheet'!F5))/2),"") -> 0.67826424 | H3: =IFERROR('Cash Flow Statement'!H37/((('Balance Sheet'!H20+'Balance Sheet'!H21+'Balance Sheet'!H25+'Balance Sheet'!H26+'Balance Sheet'!H35-'Balance Sheet'!H5)+('Balance Sheet'!G20+'Balance Sheet'!G21+'Balance Sheet'!G25+'Balance Sheet'!G26+'Balance Sheet'!G35-'Balance Sheet'!G5))/2),"") -> 0.69450395 | I3: =IFERROR('Cash Flow Statement'!I37/((('Balance Sheet'!I20+'Balance Sheet'!I21+'Balance Sheet'!I25+'Balance Sheet'!I26+'Balance Sheet'!I35-'Balance Sheet'!I5)+('Balance Sheet'!H20+'Balance Sheet'!H21+'Balance Sheet'!H25+'Balance Sheet'!H26+'Balance Sheet'!H35-'Balance Sheet'!H5))/2),"") -> 0.86175776 | J3: =IFERROR('Cash Flow Statement'!J37/((('Balance Sheet'!J20+'Balance Sheet'!J21+'Balance Sheet'!J25+'Balance Sheet'!J26+'Balance Sheet'!J35-'Balance Sheet'!J5)+('Balance Sheet'!I20+'Balance Sheet'!I21+'Balance Sheet'!I25+'Balance Sheet'!I26+'Balance Sheet'!I35-'Balance Sheet'!I5))/2),"") -> 0.64325808 | ... L3: =IFERROR('Cash Flow Statement'!L37/((('Balance Sheet'!L20+'Balance Sheet'!L21+'Balance Sheet'!L25+'Balance Sheet'!L26+'Balance Sheet'!L35-'Balance Sheet'!L5)+('Balance Sheet'!K20+'Balance Sheet'!K21+'Balance Sheet'!K25+'Balance Sheet'!K26+'Balance Sheet'!K35-'Balance Sheet'!K5))/2),"") -> 0.31263423
A4: Return on Assets | C4: =IFERROR('Income Statement'!C22/(('Balance Sheet'!C16+'Balance Sheet'!B16)/2),"") -> 0.38121122 | D4: =IFERROR('Income Statement'!D22/(('Balance Sheet'!D16+'Balance Sheet'!C16)/2),"") -> 0.36534302 | E4: =IFERROR('Income Statement'!E22/(('Balance Sheet'!E16+'Balance Sheet'!D16)/2),"") -> 0.32557789 | F4: =IFERROR('Income Statement'!F22/(('Balance Sheet'!F16+'Balance Sheet'!E16)/2),"") -> 0.30134412 | G4: =IFERROR('Income Statement'!G22/(('Balance Sheet'!G16+'Balance Sheet'!F16)/2),"") -> 0.28363351 | H4: =IFERROR('Income Statement'!H22/(('Balance Sheet'!H16+'Balance Sheet'!G16)/2),"") -> 0.2441855 | I4: =IFERROR('Income Statement'!I22/(('Balance Sheet'!I16+'Balance Sheet'!H16)/2),"") -> 0.29893143 | J4: =IFERROR('Income Statement'!J22/(('Balance Sheet'!J16+'Balance Sheet'!I16)/2),"") -> 0.2628156 | ... L4: =IFERROR('Income Statement'!L22/(('Balance Sheet'!L16+'Balance Sheet'!K16)/2),"") -> 0.17810607
A5: Return on Equity | C5: =IFERROR('Income Statement'!C22/(('Balance Sheet'!C35+'Balance Sheet'!B35)/2),"") -> 0.80021048 | D5: =IFERROR('Income Statement'!D22/(('Balance Sheet'!D35+'Balance Sheet'!C35)/2),"") -> 0.76559781 | E5: =IFERROR('Income Statement'!E22/(('Balance Sheet'!E35+'Balance Sheet'!D35)/2),"") -> 0.70320262 | F5: =IFERROR('Income Statement'!F22/(('Balance Sheet'!F35+'Balance Sheet'!E35)/2),"") -> 0.67495171 | G5: =IFERROR('Income Statement'!G22/(('Balance Sheet'!G35+'Balance Sheet'!F35)/2),"") -> 0.71548348 | H5: =IFERROR('Income Statement'!H22/(('Balance Sheet'!H35+'Balance Sheet'!G35)/2),"") -> 0.68940446 | I5: =IFERROR('Income Statement'!I22/(('Balance Sheet'!I35+'Balance Sheet'!H35)/2),"") -> 0.87429699 | J5: =IFERROR('Income Statement'!J22/(('Balance Sheet'!J35+'Balance Sheet'!I35)/2),"") -> 0.8187709 | ... L5: =IFERROR('Income Statement'!L22/(('Balance Sheet'!L35+'Balance Sheet'!K35)/2),"") -> 0.48810124
A6: Return on Total Capital | C6: =IFERROR('Cash Flow Statement'!C37/((('Balance Sheet'!C20+'Balance Sheet'!C21+'Balance Sheet'!C25+'Balance Sheet'!C26+'Balance Sheet'!C35)+('Balance Sheet'!B20+'Balance Sheet'!B21+'Balance Sheet'!B25+'Balance Sheet'!B26+'Balance Sheet'!B35))/2),"") -> 0.78826465 | D6: =IFERROR('Cash Flow Statement'!D37/((('Balance Sheet'!D20+'Balance Sheet'!D21+'Balance Sheet'!D25+'Balance Sheet'!D26+'Balance Sheet'!D35)+('Balance Sheet'!C20+'Balance Sheet'!C21+'Balance Sheet'!C25+'Balance Sheet'!C26+'Balance Sheet'!C35))/2),"") -> 0.74332478 | E6: =IFERROR('Cash Flow Statement'!E37/((('Balance Sheet'!E20+'Balance Sheet'!E21+'Balance Sheet'!E25+'Balance Sheet'!E26+'Balance Sheet'!E35)+('Balance Sheet'!D20+'Balance Sheet'!D21+'Balance Sheet'!D25+'Balance Sheet'!D26+'Balance Sheet'!D35))/2),"") -> 0.72715753 | F6: =IFERROR('Cash Flow Statement'!F37/((('Balance Sheet'!F20+'Balance Sheet'!F21+'Balance Sheet'!F25+'Balance Sheet'!F26+'Balance Sheet'!F35)+('Balance Sheet'!E20+'Balance Sheet'!E21+'Balance Sheet'!E25+'Balance Sheet'!E26+'Balance Sheet'!E35))/2),"") -> 0.61136814 | G6: =IFERROR('Cash Flow Statement'!G37/((('Balance Sheet'!G20+'Balance Sheet'!G21+'Balance Sheet'!G25+'Balance Sheet'!G26+'Balance Sheet'!G35)+('Balance Sheet'!F20+'Balance Sheet'!F21+'Balance Sheet'!F25+'Balance Sheet'!F26+'Balance Sheet'!F35))/2),"") -> 0.55844531 | H6: =IFERROR('Cash Flow Statement'!H37/((('Balance Sheet'!H20+'Balance Sheet'!H21+'Balance Sheet'!H25+'Balance Sheet'!H26+'Balance Sheet'!H35)+('Balance Sheet'!G20+'Balance Sheet'!G21+'Balance Sheet'!G25+'Balance Sheet'!G26+'Balance Sheet'!G35))/2),"") -> 0.5568963 | I6: =IFERROR('Cash Flow Statement'!I37/((('Balance Sheet'!I20+'Balance Sheet'!I21+'Balance Sheet'!I25+'Balance Sheet'!I26+'Balance Sheet'!I35)+('Balance Sheet'!H20+'Balance Sheet'!H21+'Balance Sheet'!H25+'Balance Sheet'!H26+'Balance Sheet'!H35))/2),"") -> 0.67074835 | J6: =IFERROR('Cash Flow Statement'!J37/((('Balance Sheet'!J20+'Balance Sheet'!J21+'Balance Sheet'!J25+'Balance Sheet'!J26+'Balance Sheet'!J35)+('Balance Sheet'!I20+'Balance Sheet'!I21+'Balance Sheet'!I25+'Balance Sheet'!I26+'Balance Sheet'!I35))/2),"") -> 0.54640917 | ... L6: =IFERROR('Cash Flow Statement'!L37/((('Balance Sheet'!L20+'Balance Sheet'!L21+'Balance Sheet'!L25+'Balance Sheet'!L26+'Balance Sheet'!L35)+('Balance Sheet'!K20+'Balance Sheet'!K21+'Balance Sheet'!K25+'Balance Sheet'!K26+'Balance Sheet'!K35))/2),"") -> 0.27996837
A7: Return on Capital Employed | C7: =IFERROR('Income Statement'!C12/((('Balance Sheet'!C16-'Balance Sheet'!C24)+('Balance Sheet'!B16-'Balance Sheet'!B24))/2),"") -> 0.92695478 | D7: =IFERROR('Income Statement'!D12/((('Balance Sheet'!D16-'Balance Sheet'!D24)+('Balance Sheet'!C16-'Balance Sheet'!C24))/2),"") -> 0.85049211 | E7: =IFERROR('Income Statement'!E12/((('Balance Sheet'!E16-'Balance Sheet'!E24)+('Balance Sheet'!D16-'Balance Sheet'!D24))/2),"") -> 0.84161773 | F7: =IFERROR('Income Statement'!F12/((('Balance Sheet'!F16-'Balance Sheet'!F24)+('Balance Sheet'!E16-'Balance Sheet'!E24))/2),"") -> 0.74170578 | G7: =IFERROR('Income Statement'!G12/((('Balance Sheet'!G16-'Balance Sheet'!G24)+('Balance Sheet'!F16-'Balance Sheet'!F24))/2),"") -> 0.6961607 | H7: =IFERROR('Income Statement'!H12/((('Balance Sheet'!H16-'Balance Sheet'!H24)+('Balance Sheet'!G16-'Balance Sheet'!G24))/2),"") -> 0.66605305 | I7: =IFERROR('Income Statement'!I12/((('Balance Sheet'!I16-'Balance Sheet'!I24)+('Balance Sheet'!H16-'Balance Sheet'!H24))/2),"") -> 0.76849272 | J7: =IFERROR('Income Statement'!J12/((('Balance Sheet'!J16-'Balance Sheet'!J24)+('Balance Sheet'!I16-'Balance Sheet'!I24))/2),"") -> 0.66468652 | ... L7: =IFERROR('Income Statement'!L12/((('Balance Sheet'!L16-'Balance Sheet'!L24)+('Balance Sheet'!K16-'Balance Sheet'!K24))/2),"") -> 0.35931345
A8: Return on Tangible Assets | C8: =IFERROR('Income Statement'!C22/((('Balance Sheet'!C16-'Balance Sheet'!C13-'Balance Sheet'!C12)+('Balance Sheet'!B16-'Balance Sheet'!B13-'Balance Sheet'!B12))/2),"") -> 0.3931464 | D8: =IFERROR('Income Statement'!D22/((('Balance Sheet'!D16-'Balance Sheet'!D13-'Balance Sheet'!D12)+('Balance Sheet'!C16-'Balance Sheet'!C13-'Balance Sheet'!C12))/2),"") -> 0.38039485 | E8: =IFERROR('Income Statement'!E22/((('Balance Sheet'!E16-'Balance Sheet'!E13-'Balance Sheet'!E12)+('Balance Sheet'!D16-'Balance Sheet'!D13-'Balance Sheet'!D12))/2),"") -> 0.34143732 | F8: =IFERROR('Income Statement'!F22/((('Balance Sheet'!F16-'Balance Sheet'!F13-'Balance Sheet'!F12)+('Balance Sheet'!E16-'Balance Sheet'!E13-'Balance Sheet'!E12))/2),"") -> 0.33487263 | G8: =IFERROR('Income Statement'!G22/((('Balance Sheet'!G16-'Balance Sheet'!G13-'Balance Sheet'!G12)+('Balance Sheet'!F16-'Balance Sheet'!F13-'Balance Sheet'!F12))/2),"") -> 0.34865407 | H8: =IFERROR('Income Statement'!H22/((('Balance Sheet'!H16-'Balance Sheet'!H13-'Balance Sheet'!H12)+('Balance Sheet'!G16-'Balance Sheet'!G13-'Balance Sheet'!G12))/2),"") -> 0.31151048 | I8: =IFERROR('Income Statement'!I22/((('Balance Sheet'!I16-'Balance Sheet'!I13-'Balance Sheet'!I12)+('Balance Sheet'!H16-'Balance Sheet'!H13-'Balance Sheet'!H12))/2),"") -> 0.37375689 | J8: =IFERROR('Income Statement'!J22/((('Balance Sheet'!J16-'Balance Sheet'!J13-'Balance Sheet'!J12)+('Balance Sheet'!I16-'Balance Sheet'!I13-'Balance Sheet'!I12))/2),"") -> 0.33642375 | ... L8: =IFERROR('Income Statement'!L22/((('Balance Sheet'!L16-'Balance Sheet'!L13-'Balance Sheet'!L12)+('Balance Sheet'!K16-'Balance Sheet'!K13-'Balance Sheet'!K12))/2),"") -> 0.22888067
A9: Receivables Turnover | C9: =IFERROR('Income Statement'!C3/(('Balance Sheet'!C8+'Balance Sheet'!B8)/2),"") -> 4.6862387 | D9: =IFERROR('Income Statement'!D3/(('Balance Sheet'!D8+'Balance Sheet'!C8)/2),"") -> 4.4720847 | E9: =IFERROR('Income Statement'!E3/(('Balance Sheet'!E8+'Balance Sheet'!D8)/2),"") -> 4.3011686 | F9: =IFERROR('Income Statement'!F3/(('Balance Sheet'!F8+'Balance Sheet'!E8)/2),"") -> 4.008214 | G9: =IFERROR('Income Statement'!G3/(('Balance Sheet'!G8+'Balance Sheet'!F8)/2),"") -> 3.5992859 | H9: =IFERROR('Income Statement'!H3/(('Balance Sheet'!H8+'Balance Sheet'!G8)/2),"") -> 3.2507301 | I9: =IFERROR('Income Statement'!I3/(('Balance Sheet'!I8+'Balance Sheet'!H8)/2),"") -> 3.4728413 | J9: =IFERROR('Income Statement'!J3/(('Balance Sheet'!J8+'Balance Sheet'!I8)/2),"") -> 3.5917083 | ... L9: =IFERROR('Income Statement'!L3/(('Balance Sheet'!L8+'Balance Sheet'!K8)/2),"") -> 3.0913016
A10: Days Sales Outstanding | C10: =IFERROR(365/C9,"") -> 77.887625 | D10: =IFERROR(365/D9,"") -> 81.617417 | E10: =IFERROR(365/E9,"") -> 84.860659 | F10: =IFERROR(365/F9,"") -> 91.063003 | G10: =IFERROR(365/G9,"") -> 101.409 | H10: =IFERROR(365/H9,"") -> 112.28247 | I10: =IFERROR(365/I9,"") -> 105.10126 | J10: =IFERROR(365/J9,"") -> 101.62295 | ... L10: =IFERROR(365/L9,"") -> 118.07324
A11: Payables Turnover | C11: =IFERROR('Income Statement'!C5/(('Balance Sheet'!C18+'Balance Sheet'!B18)/2),"") -> 3.043508 | D11: =IFERROR('Income Statement'!D5/(('Balance Sheet'!D18+'Balance Sheet'!C18)/2),"") -> 2.8755413 | E11: =IFERROR('Income Statement'!E5/(('Balance Sheet'!E18+'Balance Sheet'!D18)/2),"") -> 3.0238466 | F11: =IFERROR('Income Statement'!F5/(('Balance Sheet'!F18+'Balance Sheet'!E18)/2),"") -> 3.3730777 | G11: =IFERROR('Income Statement'!G5/(('Balance Sheet'!G18+'Balance Sheet'!F18)/2),"") -> 3.2788072 | H11: =IFERROR('Income Statement'!H5/(('Balance Sheet'!H18+'Balance Sheet'!G18)/2),"") -> 2.2404015 | I11: =IFERROR('Income Statement'!I5/(('Balance Sheet'!I18+'Balance Sheet'!H18)/2),"") -> 1.7204622 | J11: =IFERROR('Income Statement'!J5/(('Balance Sheet'!J18+'Balance Sheet'!I18)/2),"") -> 2.0888716 | ... L11: =IFERROR('Income Statement'!L5/(('Balance Sheet'!L18+'Balance Sheet'!K18)/2),"") -> 3.7328508
A12: Days Payables Outstanding | C12: =IFERROR(365/C11,"") -> 119.9274 | D12: =IFERROR(365/D11,"") -> 126.93262 | E12: =IFERROR(365/E11,"") -> 120.70718 | F12: =IFERROR(365/F11,"") -> 108.20978 | G12: =IFERROR(365/G11,"") -> 111.32097 | H12: =IFERROR(365/H11,"") -> 162.91723 | I12: =IFERROR(365/I11,"") -> 212.15229 | J12: =IFERROR(365/J11,"") -> 174.73549 | ... L12: =IFERROR(365/L11,"") -> 97.780496
A13: Inventory Turnover
A14: Days Inventory Outstanding
A15: Cash Conversion Cycle | C15: =IFERROR(C10-C12,"") -> -42.039776 | D15: =IFERROR(D10-D12,"") -> -45.315204 | E15: =IFERROR(E10-E12,"") -> -35.846523 | F15: =IFERROR(F10-F12,"") -> -17.146777 | G15: =IFERROR(G10-G12,"") -> -9.9119673 | H15: =IFERROR(H10-H12,"") -> -50.634757 | I15: =IFERROR(I10-I12,"") -> -107.05103 | J15: =IFERROR(J10-J12,"") -> -73.112534 | ... L15: =IFERROR(L10-L12,"") -> 20.292745
A16: Asset Turnover | C16: =IFERROR('Income Statement'!C3/(('Balance Sheet'!C16+'Balance Sheet'!B16)/2),"") -> 1.1166993 | D16: =IFERROR('Income Statement'!D3/(('Balance Sheet'!D16+'Balance Sheet'!C16)/2),"") -> 1.0576999 | E16: =IFERROR('Income Statement'!E3/(('Balance Sheet'!E16+'Balance Sheet'!D16)/2),"") -> 1.0199322 | F16: =IFERROR('Income Statement'!F3/(('Balance Sheet'!F16+'Balance Sheet'!E16)/2),"") -> 0.90783265 | G16: =IFERROR('Income Statement'!G3/(('Balance Sheet'!G16+'Balance Sheet'!F16)/2),"") -> 0.83622674 | H16: =IFERROR('Income Statement'!H3/(('Balance Sheet'!H16+'Balance Sheet'!G16)/2),"") -> 0.77819747 | I16: =IFERROR('Income Statement'!I3/(('Balance Sheet'!I16+'Balance Sheet'!H16)/2),"") -> 0.82968115 | J16: =IFERROR('Income Statement'!J3/(('Balance Sheet'!J16+'Balance Sheet'!I16)/2),"") -> 0.75575898 | ... L16: =IFERROR('Income Statement'!L3/(('Balance Sheet'!L16+'Balance Sheet'!K16)/2),"") -> 0.536668
A17: Fixed Asset Turnover | C17: =IFERROR('Income Statement'!C3/(('Balance Sheet'!C11+'Balance Sheet'!B11)/2),"") -> 3.4002752 | D17: =IFERROR('Income Statement'!D3/(('Balance Sheet'!D11+'Balance Sheet'!C11)/2),"") -> 2.9256857 | E17: =IFERROR('Income Statement'!E3/(('Balance Sheet'!E11+'Balance Sheet'!D11)/2),"") -> 2.6088376 | F17: =IFERROR('Income Statement'!F3/(('Balance Sheet'!F11+'Balance Sheet'!E11)/2),"") -> 2.4443731 | G17: =IFERROR('Income Statement'!G3/(('Balance Sheet'!G11+'Balance Sheet'!F11)/2),"") -> 2.6766217 | H17: =IFERROR('Income Statement'!H3/(('Balance Sheet'!H11+'Balance Sheet'!G11)/2),"") -> 2.7776197 | I17: =IFERROR('Income Statement'!I3/(('Balance Sheet'!I11+'Balance Sheet'!H11)/2),"") -> 2.9240134 | J17: =IFERROR('Income Statement'!J3/(('Balance Sheet'!J11+'Balance Sheet'!I11)/2),"") -> 2.3399882 | ... L17: =IFERROR('Income Statement'!L3/(('Balance Sheet'!L11+'Balance Sheet'!K11)/2),"") -> 1.3875594
A18: Operating Cycle | C18: =IFERROR(C10,"") -> 77.887625 | D18: =IFERROR(D10,"") -> 81.617417 | E18: =IFERROR(E10,"") -> 84.860659 | F18: =IFERROR(F10,"") -> 91.063003 | G18: =IFERROR(G10,"") -> 101.409 | H18: =IFERROR(H10,"") -> 112.28247 | I18: =IFERROR(I10,"") -> 105.10126 | J18: =IFERROR(J10,"") -> 101.62295 | ... L18: =IFERROR(L10,"") -> 118.07324
A19: CapEx to OCF | B19: =IFERROR(-'Cash Flow Statement'!B15/'Cash Flow Statement'!B13,"") -> 0.1462956 | C19: =IFERROR(-'Cash Flow Statement'!C15/'Cash Flow Statement'!C13,"") -> 0.18524811 | D19: =IFERROR(-'Cash Flow Statement'!D15/'Cash Flow Statement'!D13,"") -> 0.21597168 | E19: =IFERROR(-'Cash Flow Statement'!E15/'Cash Flow Statement'!E13,"") -> 0.19093177 | F19: =IFERROR(-'Cash Flow Statement'!F15/'Cash Flow Statement'!F13,"") -> 0.11212884 | G19: =IFERROR(-'Cash Flow Statement'!G15/'Cash Flow Statement'!G13,"") -> 0.11518223 | H19: =IFERROR(-'Cash Flow Statement'!H15/'Cash Flow Statement'!H13,"") -> 0.15397182 | I19: =IFERROR(-'Cash Flow Statement'!I15/'Cash Flow Statement'!I13,"") -> 0.23695486 | ... L19: =IFERROR(-'Cash Flow Statement'!L15/'Cash Flow Statement'!L13,"") -> 0.42494828
A20: CapEx to Revenue | B20: =IFERROR(-'Cash Flow Statement'!B15/'Income Statement'!B3,"") -> 0.063232611 | C20: =IFERROR(-'Cash Flow Statement'!C15/'Income Statement'!C3,"") -> 0.068277007 | D20: =IFERROR(-'Cash Flow Statement'!D15/'Income Statement'!D3,"") -> 0.086163945 | E20: =IFERROR(-'Cash Flow Statement'!E15/'Income Statement'!E3,"") -> 0.073201664 | F20: =IFERROR(-'Cash Flow Statement'!F15/'Income Statement'!F3,"") -> 0.045887526 | G20: =IFERROR(-'Cash Flow Statement'!G15/'Income Statement'!G3,"") -> 0.044992873 | H20: =IFERROR(-'Cash Flow Statement'!H15/'Income Statement'!H3,"") -> 0.06864126 | I20: =IFERROR(-'Cash Flow Statement'!I15/'Income Statement'!I3,"") -> 0.11110913 | ... L20: =IFERROR(-'Cash Flow Statement'!L15/'Income Statement'!L3,"") -> 0.18516065
A21: CapEx to Depreciation | B21: =IFERROR(-'Cash Flow Statement'!B15/'Cash Flow Statement'!B4,"") -> 2.2134879 | C21: =IFERROR(-'Cash Flow Statement'!C15/'Cash Flow Statement'!C4,"") -> 2.3969307 | D21: =IFERROR(-'Cash Flow Statement'!D15/'Cash Flow Statement'!D4,"") -> 2.4550137 | E21: =IFERROR(-'Cash Flow Statement'!E15/'Cash Flow Statement'!E4,"") -> 1.5778249 | F21: =IFERROR(-'Cash Flow Statement'!F15/'Cash Flow Statement'!F4,"") -> 1.0126122 | G21: =IFERROR(-'Cash Flow Statement'!G15/'Cash Flow Statement'!G4,"") -> 1.0514829 | H21: =IFERROR(-'Cash Flow Statement'!H15/'Cash Flow Statement'!H4,"") -> 1.649899 | I21: =IFERROR(-'Cash Flow Statement'!I15/'Cash Flow Statement'!I4,"") -> 2.7415245 | ... L21: =IFERROR(-'Cash Flow Statement'!L15/'Cash Flow Statement'!L4,"") -> 2.6903634

Sheet Salud Financiera
A1: ='Input sheet'!A1 -> Novo Nordisk (NYSE:NVO) | C1: Precio | D1: ='Input sheet'!D1 -> 39.4
A2: Financial Health | B2: Dec '16 | C2: Dec '17 | D2: Nov '18 | E2: Nov '19 | F2: Nov '20 | G2: Dec '21 | H2: Dec '22 | I2: Dec '23 | J2: Nov '24 | K2: Nov '25 | L2: LTM
A3: Total Debt | B3: =IFERROR('Balance Sheet'!B20+'Balance Sheet'!B21+'Balance Sheet'!B25+'Balance Sheet'!B26,"") -> 32.5 | C3: =IFERROR('Balance Sheet'!C20+'Balance Sheet'!C21+'Balance Sheet'!C25+'Balance Sheet'!C26,"") -> 272.9 | D3: =IFERROR('Balance Sheet'!D20+'Balance Sheet'!D21+'Balance Sheet'!D25+'Balance Sheet'!D26,"") -> 79 | E3: =IFERROR('Balance Sheet'!E20+'Balance Sheet'!E21+'Balance Sheet'!E25+'Balance Sheet'!E26,"") -> 674 | F3: =IFERROR('Balance Sheet'!F20+'Balance Sheet'!F21+'Balance Sheet'!F25+'Balance Sheet'!F26,"") -> 1707.9 | G3: =IFERROR('Balance Sheet'!G20+'Balance Sheet'!G21+'Balance Sheet'!G25+'Balance Sheet'!G26,"") -> 4058.2 | H3: =IFERROR('Balance Sheet'!H20+'Balance Sheet'!H21+'Balance Sheet'!H25+'Balance Sheet'!H26,"") -> 3698.1 | I3: =IFERROR('Balance Sheet'!I20+'Balance Sheet'!I21+'Balance Sheet'!I25+'Balance Sheet'!I26,"") -> 4004.1 | ... L3: =IFERROR('Balance Sheet'!L20+'Balance Sheet'!L21+'Balance Sheet'!L25+'Balance Sheet'!L26,"") -> 21361
A4: Net Debt | B4: =IFERROR(B3-'Balance Sheet'!B5,"") -> -2902.3 | C4: =IFERROR(C3-'Balance Sheet'!C5,"") -> -2764 | D4: =IFERROR(D3-'Balance Sheet'!D5,"") -> -2318.9 | E4: =IFERROR(E3-'Balance Sheet'!E5,"") -> -1652.8 | F4: =IFERROR(F3-'Balance Sheet'!F5,"") -> -395.9 | G4: =IFERROR(G3-'Balance Sheet'!G5,"") -> 1395.1 | H4: =IFERROR(H3-'Balance Sheet'!H5,"") -> 316.9 | I4: =IFERROR(I3-'Balance Sheet'!I5,"") -> -477.9 | ... L4: =IFERROR(L3-'Balance Sheet'!L5,"") -> 14503.9
A5: Current Ratio | B5: =IFERROR('Balance Sheet'!B10/'Balance Sheet'!B24,"") -> 1.2599245 | C5: =IFERROR('Balance Sheet'!C10/'Balance Sheet'!C24,"") -> 1.27677 | D5: =IFERROR('Balance Sheet'!D10/'Balance Sheet'!D24,"") -> 1.0905336 | E5: =IFERROR('Balance Sheet'!E10/'Balance Sheet'!E24,"") -> 1.0588819 | F5: =IFERROR('Balance Sheet'!F10/'Balance Sheet'!F24,"") -> 0.93647369 | G5: =IFERROR('Balance Sheet'!G10/'Balance Sheet'!G24,"") -> 0.86010899 | H5: =IFERROR('Balance Sheet'!H10/'Balance Sheet'!H24,"") -> 0.89461032 | I5: =IFERROR('Balance Sheet'!I10/'Balance Sheet'!I24,"") -> 0.82311619 | ... L5: =IFERROR('Balance Sheet'!L10/'Balance Sheet'!L24,"") -> 0.87290203
